Workbook
Name Macro1: #REF!
Name Macro1: #REF!
Name Macro2: #REF!
Name Macro2: #REF!
Name Macro3: #REF!
Name Macro3: #REF!
Name Macro4: #REF!
Name Macro4: #REF!
Name Macro5: #REF!
Name Macro5: #REF!
Name Macro6: #REF!
Name Macro6: #REF!
Name Macro7: #REF!
Name Macro7: #REF!
Name Macro8: #REF!
Name Macro8: #REF!
Name Macro9: #REF!
Name Macro9: #REF!
Name Recover: #REF!
Name Recover: #REF!
Name TableName: "Dummy"

Sheet Data
D1: Country | E1: Series Name
E2: سال میلادی | F2: 1959 | G2: 1960 | H2: 1961 | I2: 1962 | J2: 1963 | K2: 1964 | L2: 1965 | M2: 1966 | N2: 1967 | O2: 1968 | P2: 1969 | Q2: 1970 | R2: 1971 | S2: 1972 | T2: 1973 | U2: 1974 | V2: 1975 | W2: 1976 | X2: 1977 | Y2: 1978 | Z2: 1979 | AA2: 1980 | AB2: 1981 | AC2: 1982 | AD2: 1983 | AE2: 1984 | AF2: 1985 | AG2: 1986 | AH2: 1987 | AI2: 1988 | AJ2: 1989 | AK2: 1990 | AL2: 1991 | AM2: 1992 | AN2: 1993 | AO2: 1994 | AP2: 1995 | AQ2: 1996 | AR2: 1997 | AS2: 1998 | AT2: 1999 | AU2: 2000 | AV2: 2001 | AW2: 2002 | AX2: 2003 | AY2: 2004 | AZ2: 2005 | BA2: 2006 | BB2: 2007 | BC2: 2008 | BD2: 2009 | BE2: 2010 | BF2: 2011 | BG2: 2012 | BH2: 2013 | BI2: 2014 | BJ2: 2015 | BK2: 2016 | BL2: 2017 | BM2: 2018 | BN2: 2019 | BO2: 2020 | BP2: 2021 | BQ2: 2022 | BR2: 2023 | BS2: 2024 | BT2: 2025 | BU2: پیش بینی 2026 | BV2: 2027 پیش بینی
E3: سال شمسی | F3: 1338 | G3: 1339 | H3: 1340 | I3: 1341 | J3: 1342 | K3: 1343 | L3: 1344 | M3: 1345 | N3: 1346 | O3: 1347 | P3: 1348 | Q3: 1349 | R3: 1350 | S3: 1351 | T3: 1352 | U3: 1353 | V3: 1354 | W3: 1355 | X3: 1356 | Y3: 1357 | Z3: 1358 | AA3: 1359 | AB3: 1360 | AC3: 1361 | AD3: 1362 | AE3: 1363 | AF3: 1364 | AG3: 1365 | AH3: 1366 | AI3: 1367 | AJ3: 1368 | AK3: 1369 | AL3: 1370 | AM3: 1371 | AN3: 1372 | AO3: 1373 | AP3: 1374 | AQ3: 1375 | AR3: 1376 | AS3: 1377 | AT3: 1378 | AU3: 1379 | AV3: 1380 | AW3: 1381 | AX3: 1382 | AY3: 1383 | AZ3: 1384 | BA3: 1385 | BB3: 1386 | BC3: 1387 | BD3: 1388 | BE3: 1389 | BF3: 1390 | BG3: 1391 | BH3: 1392 | BI3: 1393 | BJ3: 1394 | BK3: 1395 | BL3: 1396 | BM3: 1397 | BN3: 1398 | BO3: 1399 | BP3: 1400 | BQ3: 1401 | BR3: 1402 | BS3: 1403 | BT3: 1404 | BU3: پیش بینی 1405 | BV3: پیش بینی 1406
D4: IRN | E4: شاخص قیمت مصرف کننده (بانک مرکزی) | F4: 0.1 | G4: 0.1 | H4: 0.1 | I4: 0.1 | J4: 0.1 | K4: 0.1 | L4: 0.1 | M4: 0.1 | N4: 0.1 | O4: 0.1 | P4: 0.1 | Q4: 0.1 | R4: 0.1 | S4: 0.2 | T4: 0.2 | U4: 0.2 | V4: 0.2 | W4: 0.3 | X4: 0.3 | Y4: 0.3 | Z4: 0.4 | AA4: 0.5 | AB4: 0.6 | AC4: 0.7 | AD4: 0.8 | AE4: 0.9 | AF4: 0.9 | AG4: 1.2 | AH4: 1.5 | AI4: 1.9 | AJ4: 2.2 | AK4: 2.45344 | AL4: 2.95856 | AM4: 3.68016 | AN4: 4.51 | AO4: 6.09752 | AP4: 9.09216 | AQ4: 11.1848 | AR4: 13.1 | AS4: 15.5 | AT4: 18.6 | AU4: 21 | AV4: 23.4 | AW4: 27.1 | AX4: 31.3 | AY4: 36.1 | AZ4: 39.8 | BA4: 44.6 | BB4: 52.7 | BC4: 66.1 | BD4: 73.2 | BE4: 82.3 | BF4: 100 | BG4: 130.5 | BH4: 175.9 | BI4: 203.2 | BJ4: 227.5 | BK4: 248 | BL4: 272.056 | BM4: 356.72733 | BN4: 503.812 | BO4: 741.16867 | BP4: 1083.8633 | BQ4: 1587.758 | BR4: 2233.9755 | BS4: =BR4*(1+BS5%) -> 2957.7836 | BT4: =BS4*(1+BT5%) -> 4229.6305 | BU4: =BT4*(1+BU5%) -> 6555.9273 | BV4: 9555
D5: IRN | E5: تورم (بانک مرکزی) | F5: 13 | G5: 7.9 | H5: 1.6 | I5: 0.9 | J5: 1 | K5: 4.5 | L5: 0.3 | M5: 0.8 | N5: 0.8 | O5: 1.5 | P5: 3.6 | Q5: 1.5 | R5: 5.5 | S5: 6.3 | T5: 11.2 | U5: 15.5 | V5: 9.9 | W5: 16.6 | X5: 25.1 | Y5: 10 | Z5: 11.4 | AA5: 23.5 | AB5: 22.8 | AC5: 19.2 | AD5: 14.8 | AE5: 10.4 | AF5: 6.9 | AG5: 23.7 | AH5: 27.7 | AI5: 28.9 | AJ5: 17.4 | AK5: 9 | AL5: 20.7 | AM5: 24.4 | AN5: 22.9 | AO5: 35.2 | AP5: 49.4 | AQ5: 23.2 | AR5: 17.3 | AS5: 18.1 | AT5: 20.1 | AU5: 12.6 | AV5: 11.4 | AW5: 15.8 | AX5: 15.6 | AY5: 15.2 | AZ5: 10.4 | BA5: 11.9 | BB5: 18.4 | BC5: 25.4 | BD5: 10.8 | BE5: 12.4 | BF5: 21.5 | BG5: 30.5 | BH5: 34.7 | BI5: 15.6 | BJ5: 11.9 | BK5: 9 | BL5: 9.6 | BM5: 31.2 | BN5: 41.2 | BO5: 47.1 | BP5: 46.2 | BQ5: 46.5 | BR5: 40.7 | BS5: 32.4 | BT5: 43 | BU5: 55 | BV5: 67
D6: IRN | E6: شاخص قیمت مصرف کننده (مرکز امار) | G6: 0.14143422 | H6: 0.14590717 | I6: 0.14695963 | J6: 0.1475061 | K6: 0.1531327 | L6: 0.15643175 | M6: 0.15582457 | N6: 0.15831404 | O6: 0.15940697 | P6: 0.16513478 | Q6: 0.16788736 | R6: 0.17493074 | S6: 0.18612323 | T6: 0.20439957 | U6: 0.23352434 | V6: 0.26360036 | W6: 0.29327159 | X6: 0.37329891 | Y6: 0.4170569 | Z6: 0.46079464 | AA6: 0.55592069 | AB6: 0.69047345 | AC6: 0.81952105 | AD6: 0.98129605 | AE6: 1.1043527 | AF6: 1.1528265 | AG6: 1.365281 | AH6: 1.7553613 | AI6: 2.2586345 | AJ6: 2.7634314 | AK6: 2.974217 | AL6: 3.4836578 | AM6: 4.3827105 | AN6: 5.3119605 | AO6: 6.9824142 | AP6: 10.449601 | AQ6: 13.473438 | AR6: 15.810975 | AS6: 18.635785 | AT6: 22.376119 | AU6: 25.615454 | AV6: 28.503403 | AW6: 32.589632 | AX6: 37.956497 | AY6: 43.559448 | AZ6: 49.410841 | BA6: 54.35978 | BB6: 63.786332 | BC6: 79.994763 | BD6: 90.835297 | BE6: 100 | BF6: 126.29339 | BG6: 160.71694 | BH6: 219.54421 | BI6: 256.00294 | BJ6: 287.96409 | BK6: 308.82832 | BL6: 333.67332 | BM6: 393.78163 | BN6: 550.92943 | BO6: 719.48154 | BP6: 1031.6575 | BQ6: =BP6+BP6*(BQ7%) -> 1504.1566 | BR6: =BQ6+BQ6*(BR7%) -> 2105.8193 | BS6: =BR6+BR6*(BS7%) -> 2800.7397 | BT6: =BS6+BS6*(BT7%) -> 3865.0207 | BU6: =BT6+BT6*(BU7%) -> 5604.2801 | BV6: 5690 | BX6: Consumer price index (2010 = 100)
D7: IRN | E7: تورم (مرکز امار) | G7: 9.8224108 | H7: 3.1625644 | I7: 0.72132057 | J7: 0.37184961 | K7: 3.8144896 | L7: 2.1543748 | M7: -0.38814853 | N7: 1.5976101 | O7: 0.69036052 | P7: 3.5931945 | Q7: 1.6668709 | R7: 4.1952984 | S7: 6.3982414 | T7: 9.8194867 | U7: 14.248936 | V7: 12.879182 | W7: 11.256143 | X7: 27.287785 | Y7: 11.721969 | Z7: 10.487237 | AA7: 20.643914 | AB7: 24.20359 | AC7: 18.689726 | AD7: 19.740189 | AE7: 12.540219 | AF7: 4.389341 | AG7: 18.429003 | AH7: 28.571429 | AI7: 28.670635 | AJ7: 22.349653 | AK7: 7.6276749 | AL7: 17.128568 | AM7: 25.807723 | AN7: 21.202631 | AO7: 31.447028 | AP7: 49.655986 | AQ7: 28.937344 | AR7: 17.349226 | AS7: 17.866134 | AT7: 20.070708 | AU7: 14.476751 | AV7: 11.274247 | AW7: 14.335934 | AX7: 16.468012 | AY7: 14.761509 | AZ7: 13.433118 | BA7: 10.015898 | BB7: 17.34104 | BC7: 25.410509 | BD7: 13.551555 | BE7: 10.089363 | BF7: 26.293386 | BG7: 27.256813 | BH7: 36.603036 | BI7: 16.606553 | BJ7: 12.484682 | BK7: 7.2454255 | BL7: 8.0449244 | BM7: 18.014118 | BN7: 39.907346 | BO7: 30.594139 | BP7: 43.389016 | BQ7: 45.8 | BR7: 40 | BS7: 33 | BT7: 38 | BU7: 45 | BV7: 73 | BW7: تورم | BX7: Inflation, consumer prices (annual %)
D8: IRN | E8: نقدینگی (همت) | G8: 0.005207 | H8: 0.005714 | I8: 0.007181 | J8: 0.00857 | K8: 0.009944 | L8: 0.011431 | M8: 0.013061 | N8: 0.015562 | O8: 0.017977 | P8: 0.021166 | Q8: 0.024968 | R8: 0.030962 | S8: 0.041877 | T8: 0.05 | U8: 0.08 | V8: 0.11 | W8: 0.16 | X8: 0.21 | Y8: 0.26 | Z8: 0.36 | AA8: 0.45 | AB8: 0.52 | AC8: 0.64 | AD8: 0.75 | AE8: 0.8 | AF8: 0.9 | AG8: 1.07 | AH8: 1.27 | AI8: 1.57 | AJ8: 1.88 | AK8: 2.3 | AL8: 2.86 | AM8: 3.59 | AN8: 4.81 | AO8: 6.18 | AP8: 8.51 | AQ8: 11.66 | AR8: 13.43 | AS8: 16.04 | AT8: 19.27 | AU8: 24.91 | AV8: 32.1 | AW8: 41.75 | AX8: 52.66 | AY8: 68.59 | AZ8: 92.1 | BA8: 128.42 | BB8: 164.03 | BC8: 190.14 | BD8: 235.59 | BE8: 294.89 | BF8: 354.26 | BG8: 460.69 | BH8: 639.55 | BI8: 782.38 | BJ8: 1017.28 | BK8: 1253.39 | BL8: 1529.98 | BM8: 1882.89 | BN8: 2472.15 | BO8: 3476.17 | BP8: 4832.44 | BQ8: 6337.68 | BR8: 7877.45 | BS8: =BR8*(1+BS9%) -> 10083.136 | BT8: 14787.967 | BU8: 21083.105 | BV8: 30058.467 | BX8: Broad money (current LCU)
D9: IRN | E9: رشد نقدینگی | G9: .. | H9: =(H8/G8-1)*100 -> 9.7368926 | I9: 25.673784 | J9: 19.34271 | K9: 16.032672 | L9: 14.953741 | M9: 14.25947 | N9: 19.14861 | O9: 15.518571 | P9: 17.739334 | Q9: 17.96277 | R9: 24.006729 | S9: 35.252891 | T9: 30.291091 | U9: 56.389961 | V9: 41.402296 | W9: 39.109559 | X9: 31.597113 | Y9: 22.966142 | Z9: 37.671605 | AA9: 26.988732 | AB9: 16.14871 | AC9: 22.81469 | AD9: 16.851976 | AE9: 6.0217715 | AF9: 12.993762 | AG9: 19.112207 | AH9: 18.144853 | AI9: 23.834483 | AJ9: 19.542186 | AK9: 22.482443 | AL9: 24.636583 | AM9: 25.281189 | AN9: 34.207885 | AO9: 28.480316 | AP9: 37.559343 | AQ9: 37.004333 | AR9: 15.21519 | AS9: 19.447405 | AT9: 20.129301 | AU9: 29.281091 | AV9: 28.841234 | AW9: 30.087086 | AX9: 26.123624 | AY9: 30.245326 | AZ9: 34.285384 | BA9: 39.432394 | BB9: 27.72884 | BC9: 15.916242 | BD9: 23.905082 | BE9: 25.170332 | BF9: 20.132351 | BG9: 30.045685 | BH9: 38.823395 | BI9: 22.333547 | BJ9: 30.022978 | BK9: 23.209932 | BL9: 22.067353 | BM9: 23.066315 | BN9: 31.295509 | BO9: 40.613231 | BP9: 39.016216 | BQ9: 35.235204 | BR9: 27.423193 | BS9: 28 | BT9: 36 | BU9: 42 | BV9: 42 | BW9: رشد نقدینگی | BX9: Broad money growth (annual %)
D10: IRN | E10: رشد اقتصادی | G10: .. | H10: 10.390918 | I10: 7.9092679 | J10: 7.0420752 | K10: 8.4752282 | L10: 17.035712 | M10: 11.502407 | N10: 11.252803 | O10: 14.404183 | P10: 15.516659 | Q10: 10.927602 | R10: 13.701583 | S10: 14.499016 | T10: 7.4416816 | U10: 5.8010508 | V10: -0.32621624 | W10: 18.260436 | X10: -2.7735777 | Y10: -12.840857 | Z10: -12.02076 | AA10: -21.599649 | AB10: -5.6967872 | AC10: 23.171246 | AD10: 11.086717 | AE10: -7.1398505 | AF10: 1.8676499 | AG10: -9.7849056 | AH10: -0.17210769 | AI10: -6.0819966 | AJ10: 6.1321157 | AK10: 13.594926 | AL10: 12.716148 | AM10: 3.2979819 | AN10: -1.4710115 | AO10: -1.6982861 | AP10: 2.4010446 | AQ10: 6.350526 | AR10: 1.3503993 | AS10: 2.0800118 | AT10: 2.0026962 | AU10: 5.8455275 | AV10: 2.3921727 | AW10: 8.0788293 | AX10: 8.6392984 | AY10: 4.336666 | AZ10: 3.1898041 | BA10: 4.9997953 | BB10: 8.1557735 | BC10: 0.25085655 | BD10: 1.0073855 | BE10: 5.7979383 | BF10: 2.6457179 | BG10: -3.7471714 | BH10: -1.5219792 | BI10: 4.9847751 | BJ10: -1.4248849 | BK10: 8.8150866 | BL10: 2.7585052 | BM10: -2.2538636 | BN10: -2.6582067 | BO10: 3.3302885 | BP10: 4.7197777 | BQ10: 2.7491661 | BR10: 5.5 | BS10: 3 | BT10: 0.5 | BU10: -6.5 | BV10: -3.2 | BW10: رشد اقتصادی | BX10: GDP growth (annual %)
D11: IRN | E11: تولید ناخالص داخلی (GDP)- دلار جاری امریکا | G11: 4.1991344 | H11: 4.4269491 | I11: 4.6935664 | J11: 4.928628 | K11: 5.3798456 | L11: 6.1973199 | M11: 6.7899387 | N11: 7.5553837 | O11: 8.623173 | P11: 9.7430896 | Q11: 10.976245 | R11: 13.731803 | S11: 17.153463 | T11: 27.081698 | U11: 46.209092 | V11: 51.776222 | W11: 68.055295 | X11: 80.600123 | Y11: 77.994317 | Z11: 90.391877 | AA11: 94.362276 | AB11: 100.49931 | AC11: 125.94876 | AD11: 156.36516 | AE11: 162.27673 | AF11: 180.18363 | AG11: 209.09456 | AH11: 134.01 | AI11: 123.05786 | AJ11: 120.49636 | AK11: 124.81326 | AL11: 131.63766 | AM11: 119.76869 | AN11: 63.743623 | AO11: 71.841461 | AP11: 96.419226 | AQ11: 120.40393 | AR11: 113.91916 | AS11: 110.27691 | AT11: 113.84845 | AU11: 109.59171 | AV11: 126.87875 | AW11: 128.62692 | AX11: 151.91122 | AY11: 187.75457 | AZ11: 224.97037 | BA11: 265.60219 | BB11: 349.73659 | BC11: 406.07095 | BD11: 414.05909 | BE11: 487.06957 | BF11: 629.08226 | BG11: 644.01932 | BH11: 500.39984 | BI11: 462.28479 | BJ11: 409.19169 | BK11: 478.61806 | BL11: 510.23989 | BM11: 411.9033 | BN11: 347.9884 | BO11: 280.93433 | BP11: 407.35069 | BQ11: 422.66226 | BR11: 457.51048 | BS11: 475.25209 | BT11: 499 | BU11: =(BT11*0.04)+BT11 -> 518.96 | BV11: =(BU11*0.04)+BU11 -> 539.7184 | BX11: GDP (constant 2015 US$)
D12: IRN | E12: صادرات نفتی (میلیون دلار) | R12: =S12*0.9 -> 6737.58 | S12: =T12*0.9 -> 7486.2 | T12: =T94 -> 8318 | U12: =U94 -> 21014 | V12: =V94 -> 20034 | W12: =W94 -> 24179 | X12: =X94 -> 23451 | Y12: =Y94 -> 15660 | Z12: =Z94 -> 24158 | AA12: =AA94 -> 11648 | ... AQ12: =AQ94 -> 19271 | AR12: =AR95 -> 15931.892 | AS12: =AS95 -> 10659.173 | AT12: =AT95 -> 17976.917 | AU12: =AU95 -> 24955.164 | AV12: =AV95 -> 20152.595 | AW12: =AW95 -> 23784.948 | AX12: =AX95 -> 28406.995 | AY12: =AY95 -> 37448.16 | ... BR12: =BR95 -> 56796.41 | BS12: =BR12-7000 -> 49796.41 | BT12: =BS12*0.8 -> 39837.128 | BU12: 46000 | BV12: 41000
D13: USA | E13: شاخص قیمت مصرف کننده | G13: 13.563061 | H13: 13.708284 | I13: 13.872615 | J13: 14.04459 | K13: 14.224207 | L13: 14.449685 | M13: 14.885354 | N13: 15.298093 | O13: 15.951596 | P13: 16.822934 | Q13: 17.8051 | R13: 18.569431 | S13: 19.177075 | T13: 20.361789 | U13: 22.612745 | V13: 24.680261 | W13: 26.098096 | X13: 27.794912 | Y13: 29.915931 | Z13: 33.282811 | AA13: 37.792366 | AB13: 41.6981 | AC13: 44.254788 | AD13: 45.676445 | AE13: 47.640776 | AF13: 49.329949 | AG13: 50.266255 | AH13: 52.108294 | AI13: 54.233135 | AJ13: 56.85097 | AK13: 59.91976 | AL13: 62.457341 | AM13: 64.349061 | AN13: 66.248425 | AO13: 67.975813 | AP13: 69.88282 | AQ13: 71.931229 | AR13: 73.612758 | AS13: 74.755433 | AT13: 76.391102 | AU13: 78.970721 | AV13: 81.202568 | AW13: 82.490467 | AX13: 84.363079 | AY13: 86.621678 | AZ13: 89.560532 | BA13: 92.449705 | BB13: 95.086992 | BC13: 98.737477 | BD13: 98.38642 | BE13: 100 | BF13: 103.15684 | BG13: 105.2915 | BH13: 106.83385 | BI13: 108.56693 | BJ13: 108.69572 | BK13: 110.06701 | BL13: 112.41156 | BM13: 115.1573 | BN13: 117.2442 | BO13: 118.6905 | BP13: 124.26641 | BQ13: 134.21121 | BR13: =BQ13+(BR14%*BQ13) -> 138.9086 | BS13: =BR13+(BS14%*BR13) -> 142.38131 | BT13: =BS13+(BT14%*BS13) -> 145.65608 | BU13: =BT13+(BU14%*BT13) -> 151.20558 | BV13: 157.04 | BX13: Consumer price index (2010 = 100)
D14: USA | E14: تورم | G14: 1.457976 | H14: 1.0707241 | I14: 1.1987733 | J14: 1.2396694 | K14: 1.2789116 | L14: 1.5851693 | M14: 3.0150754 | N14: 2.7727856 | O14: 4.2717962 | P14: 5.4623862 | Q14: 5.8382553 | R14: 4.2927667 | S14: 3.2722782 | T14: 6.1777601 | U14: 11.054805 | V14: 9.1431469 | W14: 5.7448126 | X14: 6.501684 | Y14: 7.6309638 | Z14: 11.254471 | AA14: 13.549202 | AB14: 10.334715 | AC14: 6.131427 | AD14: 3.2124352 | AE14: 4.3005355 | AF14: 3.5456442 | AG14: 1.8980477 | AH14: 3.6645632 | AI14: 4.0777411 | AJ14: 4.827003 | AK14: 5.3979564 | AL14: 4.234964 | AM14: 3.0288197 | AN14: 2.951657 | AO14: 2.6074416 | AP14: 2.8054197 | AQ14: 2.9312042 | AR14: 2.3376899 | AS14: 1.5522791 | AT14: 2.1880272 | AU14: 3.3768573 | AV14: 2.8261711 | AW14: 1.5860316 | AX14: 2.270095 | AY14: 2.6772367 | AZ14: 3.3927468 | BA14: 3.2259441 | BB14: 2.8526725 | BC14: 3.8391003 | BD14: -0.35554627 | BE14: 1.6400434 | BF14: 3.1568416 | BG14: 2.0693373 | BH14: 1.4648327 | BI14: 1.622223 | BJ14: 0.11862714 | BK14: 1.2615832 | BL14: 2.13011 | BM14: 2.4425833 | BN14: 1.8122101 | BO14: 1.2335844 | BP14: 4.6978589 | BQ14: 8.0027998 | BR14: 3.5 | BS14: 2.5 | BT14: 2.3 | BU14: 3.81 | BV14: 3 | BW14: تورم | BX14: Inflation, consumer prices (annual %)
D15: USA | E15: نقدینگی- میلیارد دلار | G15: 326.239 | H15: 352.973 | I15: 384.507 | J15: 420.332 | K15: 458.295 | L15: 497.807 | M15: 521.303 | N15: 574.88 | O15: 625.349 | P15: 631.342 | Q15: 701.958 | R15: 799.918 | S15: 908.63 | T15: 1001.092 | U15: 1079.685 | V15: 1189.58 | W15: 1311.016 | X15: 1468.795 | Y15: 1634.343 | Z15: 1794.383 | AA15: 1986.011 | AB15: 2225.612 | AC15: 2448.89 | AD15: 2651.444 | AE15: 2983.758 | AF15: 3231.204 | AG15: 3534.144 | AH15: 3677.79 | AI15: 3927.548 | AJ15: 4136.39 | AK15: 4247.161 | AL15: 4310.89 | AM15: 4304.287 | AN15: 4329.959 | AO15: 4347.481 | AP15: 4646.119 | AQ15: 5011.559 | AR15: 5412.659 | AS15: 5932.377 | AT15: 6496.459 | AU15: 7023.352 | AV15: 7580.5002 | AW15: 7917.9987 | AX15: 8266.6831 | AY15: 8741.3599 | AZ15: 9447.0941 | BA15: 10297.599 | BB15: 11503.808 | BC15: 12444.256 | BD15: 13130.258 | BE15: 12768.869 | BF15: 13622.258 | BG15: 14289.979 | BH15: 14933.187 | BI15: 15706.487 | BJ15: 16200.148 | BK15: 16823.762 | BL15: 17631.631 | BM15: 18342.26 | BN15: 19881.524 | BO15: 23301.048 | BP15: 27248.9 | BQ15: 21289.8 | BR15: 19509.606 | BS15: 20875.278 | BT15: =BS15*(1+BT16%) -> 21919.042 | BU15: =BT15*(1+BU16%) -> 22920.743 | BV15: =BU15*(1+BV16%) -> 23968.221 | BX15: Broad money (current LCU)
D16: USA | E16: رشد نقدینگی | G16: .. | H16: 8.1946058 | I16: 8.9338278 | J16: 9.3171256 | K16: 9.0316702 | L16: 8.6215211 | M16: 4.7199015 | N16: 10.277516 | O16: 8.7790495 | P16: 0.95834486 | Q16: 11.185063 | R16: 13.955251 | S16: 13.590393 | T16: 10.175979 | U16: 7.850727 | V16: 10.178432 | W16: 10.208309 | X16: 12.034865 | Y16: 11.271008 | Z16: 9.7923141 | AA16: 10.679325 | AB16: 12.064435 | AC16: 10.032207 | AD16: 8.2712576 | AE16: 12.533321 | AF16: 8.2930988 | AG16: 9.3754526 | AH16: 4.0645203 | AI16: 6.7909805 | AJ16: 5.3173634 | AK16: 2.6779632 | AL16: 1.5005082 | AM16: -0.15317023 | AN16: 0.59642863 | AO16: 0.40466896 | AP16: 6.8692192 | AQ16: 7.8654895 | AR16: 8.0034975 | AS16: 9.6018981 | AT16: 9.5085326 | AU16: 8.1104645 | AV16: 7.9327962 | AW16: 4.4521933 | AX16: 4.4036937 | AY16: 5.7420457 | AZ16: 8.0735061 | BA16: 9.0028239 | BB16: 11.713489 | BC16: 8.1751045 | BD16: 5.5126012 | BE16: -2.7523399 | BF16: 6.6833552 | BG16: 4.9016934 | BH16: 4.5011135 | BI16: 5.1783996 | BJ16: 3.1430398 | BK16: 3.8494318 | BL16: 4.801954 | BM16: 4.03042 | BN16: 8.391899 | BO16: 17.199506 | BP16: 16.942808 | BQ16: =(BQ15/BP15-1)*100 -> -21.869138 | BR16: =(BR15/BQ15-1)*100 -> -8.3617225 | BS16: 7 | BT16: 5 | BU16: 4.57 | BV16: 4.57 | BW16: رشد نقدینگی | BX16: Broad money growth (annual %)
D17: USA | E17: رشد اقتصادی | G17: .. | H17: 2.3 | I17: 6.1 | J17: 4.4 | K17: 5.8 | L17: 6.4 | M17: 6.5 | N17: 2.5 | O17: 4.8 | P17: 3.1 | Q17: -0.28349126 | R17: 3.2933516 | S17: 5.2589074 | T17: 5.6457226 | U17: -0.54055165 | V17: -0.20545607 | W17: 5.3881393 | X17: 4.6241531 | Y17: 5.535305 | Z17: 3.1661453 | AA17: -0.25674967 | AB17: 2.5377193 | AC17: -1.8028874 | AD17: 4.5839134 | AE17: 7.2366332 | AF17: 4.1696562 | AG17: 3.462646 | AH17: 3.459252 | AI17: 4.1770613 | AJ17: 3.6726481 | AK17: 1.885965 | AL17: -0.10826479 | AM17: 3.5224405 | AN17: 2.7517811 | AO17: 4.0287933 | AP17: 2.6842173 | AQ17: 3.7725655 | AR17: 4.4471749 | AS17: 4.4813944 | AT17: 4.794499 | AU17: 4.0771595 | AV17: 0.95433873 | AW17: 1.6959429 | AX17: 2.7962091 | AY17: 3.8525526 | AZ17: 3.4832203 | BA17: 2.7828106 | BB17: 2.0105076 | BC17: 0.12218844 | BD17: -2.5998884 | BE17: 2.7088567 | BF17: 1.549895 | BG17: 2.2806876 | BH17: 1.8418754 | BI17: 2.2877759 | BJ17: 2.7063696 | BK17: 1.6674721 | BL17: 2.2419212 | BM17: 2.9453848 | BN17: 2.2944391 | BO17: -2.7678025 | BP17: 5.9454848 | BQ17: 2.0615931 | BR17: 3 | BS17: 2.5 | BT17: 2.1 | BU17: 1.1 | BV17: 3.1 | BW17: رشد اقتصادی | BX17: GDP growth (annual %)
D18: USA | E18: تولید ناخالص داخلی (GDP)_دلار ثابت 2015_میلیارد دلار | G18: 3457.188 | H18: 3536.7034 | I18: 3752.4423 | J18: 3917.5497 | K18: 4144.7676 | L18: 4410.0327 | M18: 4696.6849 | N18: 4814.102 | O18: 5045.1789 | P18: 5201.5794 | Q18: 5186.8334 | R18: 5357.6541 | S18: 5639.4081 | T18: 5957.7935 | U18: 5925.5885 | V18: 5913.414 | W18: 6232.037 | X18: 6520.216 | Y18: 6881.1298 | Z18: 7098.9964 | AA18: 7080.7697 | AB18: 7260.4598 | AC18: 7129.5619 | AD18: 7456.3748 | AE18: 7995.9653 | AF18: 8329.3695 | AG18: 8617.7861 | AH18: 8915.8971 | AI18: 9288.3195 | AJ18: 9629.4468 | AK18: 9811.0548 | AL18: 9800.4329 | AM18: 10145.647 | AN18: 10424.833 | AO18: 10844.828 | AP18: 11135.927 | AQ18: 11556.037 | AR18: 12069.954 | AS18: 12610.857 | AT18: 13215.484 | AU18: 13754.3 | AV18: 13885.563 | AW18: 14121.054 | AX18: 14515.908 | AY18: 15075.141 | AZ18: 15600.242 | BA18: 16034.367 | BB18: 16356.739 | BC18: 16376.725 | BD18: 15950.949 | BE18: 16383.037 | BF18: 16636.957 | BG18: 17016.394 | BH18: 17329.815 | BI18: 17726.282 | BJ18: 18206.021 | BK18: 18509.601 | BL18: 18924.572 | BM18: 19481.973 | BN18: 19928.975 | BO18: 19377.381 | BP18: 20529.46 | BQ18: 20952.694 | BR18: 21581.274 | BS18: 22120.806 | BT18: =BS18*(1+BT17%) -> 22585.343 | BU18: =BT18*(1+BU17%) -> 22833.782 | BV18: =BU18*(1+BV17%) -> 23541.629 | BX18: GDP (constant 2015 US$)
E23: سال میلادی | F23: 1959 | G23: 1960 | H23: 1961 | I23: 1962 | J23: 1963 | K23: 1964 | L23: 1965 | M23: 1966 | N23: 1967 | O23: 1968 | P23: 1969 | Q23: 1970 | R23: 1971 | S23: 1972 | T23: 1973 | U23: 1974 | V23: 1975 | W23: 1976 | X23: 1977 | Y23: 1978 | Z23: 1979 | AA23: 1980 | AB23: 1981 | AC23: 1982 | AD23: 1983 | AE23: 1984 | AF23: 1985 | AG23: 1986 | AH23: 1987 | AI23: 1988 | AJ23: 1989 | AK23: 1990 | AL23: 1991 | AM23: 1992 | AN23: 1993 | AO23: 1994 | AP23: 1995 | AQ23: 1996 | AR23: 1997 | AS23: 1998 | AT23: 1999 | AU23: 2000 | AV23: 2001 | AW23: 2002 | AX23: 2003 | AY23: 2004 | AZ23: 2005 | BA23: 2006 | BB23: 2007 | BC23: 2008 | BD23: 2009 | BE23: 2010 | BF23: 2011 | BG23: 2012 | BH23: 2013 | BI23: 2014 | BJ23: 2015 | BK23: 2016 | BL23: 2017 | BM23: 2018 | BN23: 2019 | BO23: 2020 | BP23: 2021 | BQ23: 2022 | BR23: 2023 | BS23: 2024 | BT23: 2025 | BU23: 2026 پیش بینی | BV23: 2027 پیش بینی | BZ23: =13534*((1+3%)^(3))-1 -> 14787.967
E24: سال شمسی | F24: 1338 | G24: 1339 | H24: 1340 | I24: 1341 | J24: 1342 | K24: 1343 | L24: 1344 | M24: 1345 | N24: 1346 | O24: 1347 | P24: 1348 | Q24: 1349 | R24: 1350 | S24: 1351 | T24: 1352 | U24: 1353 | V24: 1354 | W24: 1355 | X24: 1356 | Y24: 1357 | Z24: 1358 | AA24: 1359 | AB24: 1360 | AC24: 1361 | AD24: 1362 | AE24: 1363 | AF24: 1364 | AG24: 1365 | AH24: 1366 | AI24: 1367 | AJ24: 1368 | AK24: 1369 | AL24: 1370 | AM24: 1371 | AN24: 1372 | AO24: 1373 | AP24: 1374 | AQ24: 1375 | AR24: 1376 | AS24: 1377 | AT24: 1378 | AU24: 1379 | AV24: 1380 | AW24: 1381 | AX24: 1382 | AY24: 1383 | AZ24: 1384 | BA24: 1385 | BB24: 1386 | BC24: 1387 | BD24: 1388 | BE24: 1389 | BF24: 1390 | BG24: 1391 | BH24: 1392 | BI24: 1393 | BJ24: 1394 | BK24: 1395 | BL24: 1396 | BM24: 1397 | BN24: 1398 | BO24: 1399 | BP24: 1400 | BQ24: 1401 | BR24: 1402 | BS24: 1403 | BT24: 1404 | BU24: پیش بینی 1405 | BV24: پیش بینی 1406 | BZ24: =BZ23*((1+3%)^(12))-1 -> 21083.105
E25: نرخ ارز بازار آزاد (ریال) | F25: 76 | G25: 76 | H25: 76 | I25: 76 | J25: 76 | K25: 76 | L25: 76 | M25: 76 | N25: 76 | O25: 76 | P25: 76 | Q25: 76 | R25: 76 | S25: 69 | T25: 68 | U25: 68 | V25: 68 | W25: 71 | X25: 71 | Y25: 100 | Z25: 141 | AA25: 200 | AB25: 270 | AC25: 350 | AD25: 450 | AE25: 580 | AF25: 614 | AG25: 742 | AH25: 991 | AI25: 966 | AJ25: 1207.1 | AK25: 1412.3 | AL25: 1420.2 | AM25: 1498 | AN25: 1806 | AO25: 2635 | AP25: 4036 | AQ25: 4446 | AR25: 4782 | AS25: 6468 | AT25: 8634 | AU25: 8131 | AV25: 7925 | AW25: 7991 | AX25: 8323 | AY25: 8747 | AZ25: 9042 | BA25: 9226 | BB25: 9357 | BC25: 9667 | BD25: 9979 | BE25: 10601 | BF25: 13568 | BG25: 26059 | BH25: 31839 | BI25: 32801 | BJ25: 34501 | BK25: 36440 | BL25: 40453 | BM25: 103378 | BN25: 129185 | BO25: 228809 | BP25: 259476 | BQ25: 349266 | BR25: 517807.6 | BS25: 690000 | BT25: =BT45 -> 1000643.6 | BU25: =BU45 -> 1494073.4 | BV25: =BV45 -> 2096650.4 | BZ25: =BZ24*((1+3%)^(12))-1 -> 30058.467
E26: نرخ ارز رسمی (ریال) | F26: 76 | G26: 76 | H26: 76 | I26: 76 | J26: 76 | K26: 76 | L26: 76 | M26: 76 | N26: 76 | O26: 76 | P26: 76 | Q26: 76 | R26: 76 | S26: 69 | T26: 68 | U26: 68 | V26: 68 | W26: 71 | X26: 71 | Y26: 70 | Z26: 70 | AA26: 71 | AB26: 80 | AC26: 84 | AD26: 87 | AE26: 92 | AF26: 88 | AG26: 77 | AH26: 70 | AI26: 69 | AJ26: 72 | AK26: 66.9 | AL26: 67.8 | AM26: 1458.5 | AN26: 1653 | AO26: 1750 | AP26: 1750 | AQ26: 1754 | AR26: 1755 | AS26: 1755 | AT26: 1755 | AU26: 1755 | AV26: 1755 | AW26: 7958 | AX26: 8282 | AY26: 8719 | AZ26: 9023 | BA26: 9195 | BB26: 9285 | BC26: 9574 | BD26: 9920 | BE26: 10339 | BF26: 10962 | BG26: 12260 | BH26: 21253 | BI26: 26509 | BJ26: 29580 | BK26: 31389 | BL26: 34214 | BM26: 41950 | BN26: 42000 | BO26: 42000 | BP26: 42000 | BQ26: 42000 | BR26: 42000 | BS26: 285000 | BT26: 1374731 | BU26: 1400000 | BV26: 1500000
E27: اختلاف تورم ایران و امریکا | F27: =F7-F14 -> 0 | G27: =G7-G14 -> 8.3644348 | H27: =H7-H14 -> 2.0918402 | I27: =I7-I14 -> -0.47745278 | J27: =J7-J14 -> -0.86781981 | K27: =K7-K14 -> 2.535578 | L27: =L7-L14 -> 0.56920557 | M27: =M7-M14 -> -3.4032239 | ... BR27: =BR7-BR14 -> 36.5 | BS27: 32 | BT27: 70 | BU27: 84 | BV27: 94
E28: اختلاف رشد نقدینگی ایران و امریکا | F28: =F9-F16 -> 0 | H28: =H9-H16 -> 1.5422868 | I28: =I9-I16 -> 16.739956 | J28: =J9-J16 -> 10.025584 | K28: =K9-K16 -> 7.0010019 | L28: =L9-L16 -> 6.3322199 | M28: =M9-M16 -> 9.5395684 | N28: =N9-N16 -> 8.8710942 | O28: =O9-O16 -> 6.7395213 | ... BV28: =BV9-BV16 -> 37.43
E29: اختلاف رشد اقتصادی ایران با امریکا | F29: =F10-F17 -> 0 | H29: =H10-H17 -> 8.0909184 | I29: =I10-I17 -> 1.8092679 | J29: =J10-J17 -> 2.6420752 | K29: =K10-K17 -> 2.6752282 | L29: =L10-L17 -> 10.635712 | M29: =M10-M17 -> 5.0024073 | N29: =N10-N17 -> 8.7528031 | O29: =O10-O17 -> 9.6041827 | ... BV29: =BV10-BV17 -> -6.3
E30: اختلاف رشد نقدینگی با رشد اقتصادی (USA, IRI) | F30: =F28-F29 -> 0 | H30: =H28-H29 -> -6.5486315 | I30: =I28-I29 -> 14.930688 | J30: =J28-J29 -> 7.3835091 | K30: =K28-K29 -> 4.3257737 | L30: =L28-L29 -> -4.3034916 | M30: =M28-M29 -> 4.5371611 | N30: =N28-N29 -> 0.11829112 | O30: =O28-O29 -> -2.8646613 | ... BV30: =BV28-BV29 -> 43.73
A31: =#REF! -> #REF! | B31: =A32 -> 0 | C31: =B32 -> 0 | D31: =C32 -> 0 | E31: نرخ حقیقی ارز | G31: =G25*(G13/G4) -> 10307.926 | H31: =H25*(H13/H4) -> 10418.296 | I31: =I25*(I13/I4) -> 10543.187 | J31: =J25*(J13/J4) -> 10673.888 | K31: =K25*(K13/K4) -> 10810.398 | L31: =L25*(L13/L4) -> 10981.761 | M31: =M25*(M13/M4) -> 11312.869 | N31: =N25*(N13/N4) -> 11626.551 | ... BV31: =BV25*(BV13/BV4) -> 34459.234 | BW31: =BV32 -> 300556.67 | BX31: =BW32 -> 0 | BY31: =BX32 -> 0 | BZ31: =BY32 -> 0 | CA31: =BZ32 -> 0 | CB31: =CA32 -> 0 | CC31: =CB32 -> 0 | CD31: =CC32 -> 0 | ... XFD31: =XFC32 -> 0
E32: نرخ حقیقی ارز به قیمت های ثابت سال 1400 | G32: =G25*(G13/G4)*($BP$4/$BP$13) -> 89906.7 | H32: =H25*(H13/H4)*($BP$4/$BP$13) -> 90869.353 | I32: =I25*(I13/I4)*($BP$4/$BP$13) -> 91958.671 | J32: =J25*(J13/J4)*($BP$4/$BP$13) -> 93098.654 | K32: =K25*(K13/K4)*($BP$4/$BP$13) -> 94289.304 | L32: =L25*(L13/L4)*($BP$4/$BP$13) -> 95783.949 | M32: =M25*(M13/M4)*($BP$4/$BP$13) -> 98671.907 | N32: =N25*(N13/N4)*($BP$4/$BP$13) -> 101407.87 | ... BV32: =BV25*(BV13/BV4)*($BP$4/$BP$13) -> 300556.67
E33: نرخ حقیقی ارز به قیمت های ثابت سال 1381 | G33: =G25*(G13/G4)*($AW$4/$AW$13) -> 3386.3889 | H33: =H25*(H13/H4)*($AW$4/$AW$13) -> 3422.6478 | I33: =I25*(I13/I4)*($AW$4/$AW$13) -> 3463.6776 | J33: =J25*(J13/J4)*($AW$4/$AW$13) -> 3506.6157 | K33: =K25*(K13/K4)*($AW$4/$AW$13) -> 3551.4622 | L33: =L25*(L13/L4)*($AW$4/$AW$13) -> 3607.7589 | M33: =M25*(M13/M4)*($AW$4/$AW$13) -> 3716.5356 | N33: =N25*(N13/N4)*($AW$4/$AW$13) -> 3819.5871 | ... BV33: =BV25*(BV13/BV4)*($AW$4/$AW$13) -> 11320.644
E34: نرخ حقیقی ارز به قیمت های ثابت سال 1402 | G34: =G25*(G13/G4)*($BR$4/$BR$13) -> 165775.59 | H34: =H25*(H13/H4)*($BR$4/$BR$13) -> 167550.59 | I34: =I25*(I13/I4)*($BR$4/$BR$13) -> 169559.14 | J34: =J25*(J13/J4)*($BR$4/$BR$13) -> 171661.11 | K34: =K25*(K13/K4)*($BR$4/$BR$13) -> 173856.51 | L34: =L25*(L13/L4)*($BR$4/$BR$13) -> 176612.43 | M34: =M25*(M13/M4)*($BR$4/$BR$13) -> 181937.42 | N34: =N25*(N13/N4)*($BR$4/$BR$13) -> 186982.16 | ... BV34: =BV25*(BV13/BV4)*($BR$4/$BR$13) -> 554185.16
E35: نرخ ارز (ppp)- سال پایه 1339 | G35: =$G$25*((G6/$G$6)/(G13/$G$13)) -> 76 | H35: =$G$25*((H6/$G$6)/(H13/$G$13)) -> 77.572957 | I35: =$G$25*((I6/$G$6)/(I13/$G$13)) -> 77.20697 | J35: =$G$25*((J6/$G$6)/(J13/$G$13)) -> 76.545157 | K35: =$G$25*((K6/$G$6)/(K13/$G$13)) -> 78.46151 | L35: =$G$25*((L6/$G$6)/(L13/$G$13)) -> 78.901149 | M35: =$G$25*((M6/$G$6)/(M13/$G$13)) -> 76.294557 | N35: =$G$25*((N6/$G$6)/(N13/$G$13)) -> 75.422151 | ... BV35: =$G$25*((BV6/$G$6)/(BV13/$G$13)) -> 264069.82
E36: نرخ ارز (ppp)- سال پایه 1357 | G36: =$Y$25*((G6/$Y$6)/(G13/$Y$13)) -> 74.800417 | H36: =$Y$25*((H6/$Y$6)/(H13/$Y$13)) -> 76.348546 | I36: =$Y$25*((I6/$Y$6)/(I13/$Y$13)) -> 75.988336 | J36: =$Y$25*((J6/$Y$6)/(J13/$Y$13)) -> 75.336969 | K36: =$Y$25*((K6/$Y$6)/(K13/$Y$13)) -> 77.223075 | L36: =$Y$25*((L6/$Y$6)/(L13/$Y$13)) -> 77.655774 | M36: =$Y$25*((M6/$Y$6)/(M13/$Y$13)) -> 75.090324 | N36: =$Y$25*((N6/$Y$6)/(N13/$Y$13)) -> 74.231689 | ... BV36: =$Y$25*((BV6/$Y$6)/(BV13/$Y$13)) -> 259901.75
E37: نرخ ارز (ppp)- سال پایه 1366 | G37: =$AH$25*(G6/$AH$6)/(G13/$AH$13) -> 306.76852 | H37: =$AH$25*(H6/$AH$6)/(H13/$AH$13) -> 313.11765 | I37: =$AH$25*(I6/$AH$6)/(I13/$AH$13) -> 311.64037 | J37: =$AH$25*(J6/$AH$6)/(J13/$AH$13) -> 308.96901 | K37: =$AH$25*(K6/$AH$6)/(K13/$AH$13) -> 316.70423 | L37: =$AH$25*(L6/$AH$6)/(L13/$AH$13) -> 318.4788 | M37: =$AH$25*(M6/$AH$6)/(M13/$AH$13) -> 307.95748 | N37: =$AH$25*(N6/$AH$6)/(N13/$AH$13) -> 304.43608 | ... AG37: =$AH$25*(AG6/$AH$6)/(AG13/$AH$13) -> 799.02342 | AH37: =$AH$25*((AH6/$AH$6)/(AH13/$AH$13)) -> 991 | AI37: =$AH$25*((AI6/$AH$6)/(AI13/$AH$13)) -> 1225.1669 | AJ37: =$AH$25*((AJ6/$AH$6)/(AJ13/$AH$13)) -> 1429.963 | AK37: =$AH$25*((AK6/$AH$6)/(AK13/$AH$13)) -> 1460.2142 | AL37: =$AH$25*(AL6/$AH$6)/(AL13/$AH$13) -> 1640.8391 | AM37: =$AH$25*((AM6/$AH$6)/(AM13/$AH$13)) -> 2003.6164 | AN37: =$AH$25*(AN6/$AH$6)/(AN13/$AH$13) -> 2358.8117 | AO37: =$AH$25*(AO6/$AH$6)/(AO13/$AH$13) -> 3021.7963 | AP37: =$AH$25*(AP6/$AH$6)/(AP13/$AH$13) -> 4398.8917 | AQ37: =$AH$25*(AQ6/$AH$6)/(AQ13/$AH$13) -> 5510.2961 | AR37: =$AH$25*(AR6/$AH$6)/(AR13/$AH$13) -> 6318.581 | AS37: =$AH$25*(AS6/$AH$6)/(AS13/$AH$13) -> 7333.6288 | AT37: =$AH$25*(AT6/$AH$6)/(AT13/$AH$13) -> 8616.9977 | AU37: =$AH$25*(AU6/$AH$6)/(AU13/$AH$13) -> 9542.2315 | ... BV37: =$AH$25*(BV6/$AH$6)/(BV13/$AH$13) -> 1065898.8
E38: نرخ ارز (ppp)- سال پایه 1370 | G38: =$AL$25*((G6/$AL$6)/(G13/$AL$13)) -> 265.51821 | H38: =$AL$25*((H6/$AL$6)/(H13/$AL$13)) -> 271.01359 | I38: =$AL$25*((I6/$AL$6)/(I13/$AL$13)) -> 269.73495 | J38: =$AL$25*((J6/$AL$6)/(J13/$AL$13)) -> 267.4228 | K38: =$AL$25*((K6/$AL$6)/(K13/$AL$13)) -> 274.11789 | L38: =$AL$25*((L6/$AL$6)/(L13/$AL$13)) -> 275.65384 | M38: =$AL$25*((M6/$AL$6)/(M13/$AL$13)) -> 266.54729 | N38: =$AL$25*((N6/$AL$6)/(N13/$AL$13)) -> 263.4994 | ... BV38: =$AL$25*((BV6/$AL$6)/(BV13/$AL$13)) -> 922570.34
E39: نرخ ارز (ppp)- سال پایه 1371 | G39: =$AM$25*((G6/$AM$6)/(G13/$AM$13)) -> 229.35491 | H39: =$AM$25*((H6/$AM$6)/(H13/$AM$13)) -> 234.10182 | I39: =$AM$25*((I6/$AM$6)/(I13/$AM$13)) -> 232.99733 | J39: =$AM$25*((J6/$AM$6)/(J13/$AM$13)) -> 231.0001 | K39: =$AM$25*((K6/$AM$6)/(K13/$AM$13)) -> 236.78332 | L39: =$AM$25*((L6/$AM$6)/(L13/$AM$13)) -> 238.11007 | M39: =$AM$25*((M6/$AM$6)/(M13/$AM$13)) -> 230.24383 | N39: =$AM$25*((N6/$AM$6)/(N13/$AM$13)) -> 227.61106 | ... BV39: =$AM$25*((BV6/$AM$6)/(BV13/$AM$13)) -> 796917.23
E40: نرخ ارز (ppp)- سال پایه 1381 | G40: =$AW$25*((G6/$AW$6)/(G13/$AW$13)) -> 210.92217 | H40: =$AW$25*((H6/$AW$6)/(H13/$AW$13)) -> 215.28758 | I40: =$AW$25*((I6/$AW$6)/(I13/$AW$13)) -> 214.27186 | J40: =$AW$25*((J6/$AW$6)/(J13/$AW$13)) -> 212.43514 | K40: =$AW$25*((K6/$AW$6)/(K13/$AW$13)) -> 217.75358 | L40: =$AW$25*((L6/$AW$6)/(L13/$AW$13)) -> 218.9737 | M40: =$AW$25*((M6/$AW$6)/(M13/$AW$13)) -> 211.73965 | N40: =$AW$25*((N6/$AW$6)/(N13/$AW$13)) -> 209.31847 | ... BV40: =$AW$25*((BV6/$AW$6)/(BV13/$AW$13)) -> 732870.79
E41: نرخ ارز (ppp)- سال پایه 1390 | G41: =$BF$25*((G6/$BF$6)/((G13/$BF$13))) -> 115.566 | H41: =$BF$25*((H6/$BF$6)/((H13/$BF$13))) -> 117.95784 | I41: =$BF$25*((I6/$BF$6)/((I13/$BF$13))) -> 117.40132 | J41: =$BF$25*((J6/$BF$6)/((J13/$BF$13))) -> 116.39496 | K41: =$BF$25*((K6/$BF$6)/((K13/$BF$13))) -> 119.30898 | L41: =$BF$25*((L6/$BF$6)/((L13/$BF$13))) -> 119.9775 | M41: =$BF$25*((M6/$BF$6)/((M13/$BF$13))) -> 116.0139 | N41: =$BF$25*((N6/$BF$6)/((N13/$BF$13))) -> 114.68732 | ... BV41: =$BF$25*((BV6/$BF$6)/((BV13/$BF$13))) -> 401545.95
E42: نرخ ارز (ppp)- سال پایه 1369 | G42: =$AK$25*((G4/$AK$4)/(G13/$AK$13)) -> 254.31026 | H42: =$AK$25*((H4/$AK$4)/(H13/$AK$13)) -> 251.61614 | I42: =$AK$25*((I4/$AK$4)/(I13/$AK$13)) -> 248.63557 | J42: =$AK$25*((J4/$AK$4)/(J13/$AK$13)) -> 245.59105 | K42: =$AK$25*((K4/$AK$4)/(K13/$AK$13)) -> 242.48982 | L42: =$AK$25*((L4/$AK$4)/(L13/$AK$13)) -> 238.70593 | M42: =$AK$25*((M4/$AK$4)/(M13/$AK$13)) -> 231.71941 | N42: =$AK$25*((N4/$AK$4)/(N13/$AK$13)) -> 225.46768 | ... BV42: =$AK$25*((BV4/$AK$4)/(BV13/$AK$13)) -> 2098659.5
E43: نرخ ارز (ppp)- سال پایه 1366 | G43: =$AH$25*((G4/$AH$4)/(G13/$AH$13)) -> 253.82333 | H43: =$AH$25*((H4/$AH$4)/(H13/$AH$13)) -> 251.13437 | I43: =$AH$25*((I4/$AH$4)/(I13/$AH$13)) -> 248.1595 | J43: =$AH$25*((J4/$AH$4)/(J13/$AH$13)) -> 245.12082 | K43: =$AH$25*((K4/$AH$4)/(K13/$AH$13)) -> 242.02552 | L43: =$AH$25*((L4/$AH$4)/(L13/$AH$13)) -> 238.24888 | M43: =$AH$25*((M4/$AH$4)/(M13/$AH$13)) -> 231.27574 | N43: =$AH$25*((N4/$AH$4)/(N13/$AH$13)) -> 225.03597 | ... BV43: =$AH$25*((BV4/$AH$4)/(BV13/$AH$13)) -> 2094641.2
E44: نرخ ارز (ppp)- سال پایه 1378 | G44: =$AT$25*((G4/$AT$4)/(G13/$AT$13)) -> 261.4473 | H44: =$AT$25*((H4/$AT$4)/(H13/$AT$13)) -> 258.67758 | I44: =$AT$25*((I4/$AT$4)/(I13/$AT$13)) -> 255.61336 | J44: =$AT$25*((J4/$AT$4)/(J13/$AT$13)) -> 252.4834 | K44: =$AT$25*((K4/$AT$4)/(K13/$AT$13)) -> 249.29513 | L44: =$AT$25*((L4/$AT$4)/(L13/$AT$13)) -> 245.40505 | M44: =$AT$25*((M4/$AT$4)/(M13/$AT$13)) -> 238.22246 | N44: =$AT$25*((N4/$AT$4)/(N13/$AT$13)) -> 231.79527 | ... BV44: =$AT$25*((BV4/$AT$4)/(BV13/$AT$13)) -> 2157557
E45: میانگین نرخ ارز برابری قدرت خرید | G45: =AVERAGE(G42,G43) -> 254.06679 | H45: =AVERAGE(H42,H43) -> 251.37526 | I45: =AVERAGE(I42,I43) -> 248.39754 | J45: =AVERAGE(J42,J43) -> 245.35593 | K45: =AVERAGE(K42,K43) -> 242.25767 | L45: =AVERAGE(L42,L43) -> 238.4774 | M45: =AVERAGE(M42,M43) -> 231.49757 | N45: =AVERAGE(N42,N43) -> 225.25182 | ... BV45: =AVERAGE(BV42,BV43) -> 2096650.4
E46: حباب نرخ ارز PPP با بازار آزاد | G46: =(G25-G45)/G45*100 -> -70.086606 | H46: =(H25-H45)/H45*100 -> -69.766317 | I46: =(I25-I45)/I45*100 -> -69.403883 | J46: =(J25-J45)/J45*100 -> -69.024592 | K46: =(K25-K45)/K45*100 -> -68.628444 | L46: =(L25-L45)/L45*100 -> -68.131152 | M46: =(M25-M45)/M45*100 -> -67.170282 | N46: =(N25-N45)/N45*100 -> -66.259985 | ... BU46: =(BU25-BU45)/BU45*100 -> 0 | BV46: 0
E47: (Mt/Yt)/(Mt*/Yt*)-سطح | G47: =((G8/G11)/(G15/G18)) -> 0.013140592 | H47: =((H8/H11)/(H15/H18)) -> 0.012932809 | I47: =((I8/I11)/(I15/I18)) -> 0.014931097 | J47: =((J8/J11)/(J15/J18)) -> 0.016206038 | K47: =((K8/K11)/(K15/K18)) -> 0.016716539 | L47: =((L8/L11)/(L15/L18)) -> 0.016340341 | M47: =((M8/M11)/(M15/M18)) -> 0.017330527 | N47: =((N8/N11)/(N15/N18)) -> 0.017248327 | ... BV47: =((BV8/BV11)/(BV15/BV18)) -> 54.701637
E48: (Mt/Yt)/(Mt*/Yt*)-رشد | H48: =((H9/H10)/(H16/H17)) -> 0.26300634 | I48: =((I9/I10)/(I16/I17)) -> 2.2163883 | J48: =((J9/J10)/(J16/J17)) -> 1.2971416 | K48: =((K9/K10)/(K16/K17)) -> 1.214827 | L48: =((L9/L10)/(L16/L17)) -> 0.65160687 | M48: =((M9/M10)/(M16/M17)) -> 1.7072419 | N48: =((N9/N10)/(N16/N17)) -> 0.41393141 | O48: =((O9/O10)/(O16/O17)) -> 0.58905635 | ... BU48: =((BU9/BU10)/(BU16/BU17)) -> -1.5552937
E49: (M0/Y0)/(M0*/Y0*)-1350رشد | R49: =((R9/R10)/(R16/R17)) -> 0.41348779 | S49: =((S9/S10)/(S16/S17)) -> 0.94084854 | T49: =((T9/T10)/(T16/T17)) -> 2.2583287 | U49: =((U9/U10)/(U16/U17)) -> -0.6693025 | V49: =((V9/V10)/(V16/V17)) -> 2.5618692 | W49: =((W9/W10)/(W16/W17)) -> 1.1304642 | X49: =((X9/X10)/(X16/X17)) -> -4.3772169 | Y49: =((Y9/Y10)/(Y16/Y17)) -> -0.8783606 | ... BU49: =((BU9/BU10)/(BU16/BU17)) -> -1.5552937
E50: (M0/Y0)/(M0*/Y0*)-1350سطح | R50: =((R8/R11)/(R15/R18)) -> 0.015101867
E51: (M0/Y0)/(M0*/Y0*)-1360سطح | AB51: =((AB8/AB11)/(AB15/AB18)) -> 0.016879319
E52: (M0/Y0)/(M0*/Y0*)-1366سطح | AH52: =((AH8/AH11)/(AH15/AH18)) -> 0.022974425
E53: (M0/Y0)/(M0*/Y0*)-1369سطح | AK53: =((AK8/AK11)/(AK15/AK18)) -> 0.042568081
E54: (M0/Y0)/(M0*/Y0*)-1371سطح | AM54: =((AM8/AM11)/(AM15/AM18)) -> 0.07065285
E55: (M0/Y0)/(M0*/Y0*)-1378سطح | AT55: =((AT8/AT11)/(AT15/AT18)) -> 0.34431898
E56: (M0/Y0)/(M0*/Y0*)-1381سطح | AW56: =((AW8/AW11)/(AW15/AW18)) -> 0.5788637
E57: نرخ ارز رویکرد پولی - سال پایه 1350 | G57: =$R$25*(G47/$R$50) -> 66.129901 | H57: =$R$25*(H47/$R$50) -> 65.084235 | I57: =$R$25*(I47/$R$50) -> 75.140603 | J57: =$R$25*(J47/$R$50) -> 81.556727 | K57: =$R$25*(K47/$R$50) -> 84.12582 | L57: =$R$25*(L47/$R$50) -> 82.232609 | M57: =$R$25*(M47/$R$50) -> 87.21571 | N57: =$R$25*(N47/$R$50) -> 86.802037 | ... BV57: =$R$25*(BV47/$R$50) -> 275285.46
E58: نرخ ارز رویکرد پولی - سال پایه 1360 | G58: =$AB$25*(G47/$AB$51) -> 210.19567 | H58: =$AB$25*(H47/$AB$51) -> 206.87199 | I58: =$AB$25*(I47/$AB$51) -> 238.83643 | J58: =$AB$25*(J47/$AB$51) -> 259.23026 | K58: =$AB$25*(K47/$AB$51) -> 267.39619 | L58: =$AB$25*(L47/$AB$51) -> 261.37856 | M58: =$AB$25*(M47/$AB$51) -> 277.21748 | N58: =$AB$25*(N47/$AB$51) -> 275.90262 | ... BV58: =$AB$25*(BV47/$AB$51) -> 875002.25
E59: نرخ ارز رویکرد پولی - سال پایه 1371 | G59: =$AM$25*(G47/$AM$54) -> 278.61023 | H59: =$AM$25*(H47/$AM$54) -> 274.20476 | I59: =$AM$25*(I47/$AM$54) -> 316.57299 | J59: =$AM$25*(J47/$AM$54) -> 343.6046 | K59: =$AM$25*(K47/$AM$54) -> 354.42838 | L59: =$AM$25*(L47/$AM$54) -> 346.45214 | M59: =$AM$25*(M47/$AM$54) -> 367.44632 | N59: =$AM$25*(N47/$AM$54) -> 365.70349 | ... BV59: =$AM$25*(BV47/$AM$54) -> 1159798.3
E60: نرخ ارز رویکرد پولی - سال پایه 1381 | G60: =$AW$25*(G47/$AW$56) -> 181.40103 | H60: =$AW$25*(H47/$AW$56) -> 178.53266 | I60: =$AW$25*(I47/$AW$56) -> 206.1183 | J60: =$AW$25*(J47/$AW$56) -> 223.71838 | K60: =$AW$25*(K47/$AW$56) -> 230.76566 | L60: =$AW$25*(L47/$AW$56) -> 225.57239 | M60: =$AW$25*(M47/$AW$56) -> 239.24154 | N60: =$AW$25*(N47/$AW$56) -> 238.1068 | ... BV60: =$AW$25*(BV47/$AW$56) -> 755135.94
E61: نرخ ارز رویکرد پولی - سال پایه 1366 | G61: =$AH$25*(G47/$AH$52) -> 566.8184 | H61: =$AH$25*(H47/$AH$52) -> 557.85569 | I61: =$AH$25*(I47/$AH$52) -> 644.05171 | J61: =$AH$25*(J47/$AH$52) -> 699.04616 | K61: =$AH$25*(K47/$AH$52) -> 721.06659 | L61: =$AH$25*(L47/$AH$52) -> 704.83933 | M61: =$AH$25*(M47/$AH$52) -> 747.55093 | N61: =$AH$25*(N47/$AH$52) -> 744.00522 | ... BV61: =$AH$25*(BV47/$AH$52) -> 2359550.8
E62: نرخ ارز رویکرد پولی - سال پایه 1369 | G62: =$AK$25*(G47/$AK$53) -> 435.97121 | H62: =$AK$25*(H47/$AK$53) -> 429.0775 | I62: =$AK$25*(I47/$AK$53) -> 495.3756 | J62: =$AK$25*(J47/$AK$53) -> 537.67486 | K62: =$AK$25*(K47/$AK$53) -> 554.61199 | L62: =$AK$25*(L47/$AK$53) -> 542.13071 | M62: =$AK$25*(M47/$AK$53) -> 574.98254 | N62: =$AK$25*(N47/$AK$53) -> 572.25535 | ... BV62: =$AK$25*(BV47/$AK$53) -> 1814860.3
E63: نرخ ارز رویکرد پولی - سال پایه 1378 | G63: =$AT$25*(G47/$AT$55) -> 329.50803 | H63: =$AT$25*(H47/$AT$55) -> 324.29775 | I63: =$AT$25*(I47/$AT$55) -> 374.40601 | J63: =$AT$25*(J47/$AT$55) -> 406.37588 | K63: =$AT$25*(K47/$AT$55) -> 419.177 | L63: =$AT$25*(L47/$AT$55) -> 409.74362 | M63: =$AT$25*(M47/$AT$55) -> 434.57311 | N63: =$AT$25*(N47/$AT$55) -> 432.51189 | ... BV63: =$AT$25*(BV47/$AT$55) -> 1371675.6
E64: میانگین نرخ ارز رویکرد پولی | G64: =AVERAGE(G61,G62) -> 501.3948 | H64: =AVERAGE(H61,H62) -> 493.46659 | I64: =AVERAGE(I61,I62) -> 569.71366 | J64: =AVERAGE(J61,J62) -> 618.36051 | K64: =AVERAGE(K61,K62) -> 637.83929 | L64: =AVERAGE(L61,L62) -> 623.48502 | M64: =AVERAGE(M61,M62) -> 661.26674 | N64: =AVERAGE(N61,N62) -> 658.13028 | ... BV64: =AVERAGE(BV61,BV62) -> 2087205.6
E65: حباب نرخ ارزر رویکرد پولی با بازار آزاد | G65: =(G25-G64)/G64*100 -> -84.842284 | H65: =(H25-H64)/H64*100 -> -84.598755 | I65: =(I25-I64)/I64*100 -> -86.659965 | J65: =(J25-J64)/J64*100 -> -87.709435 | K65: =(K25-K64)/K64*100 -> -88.084773 | L65: =(L25-L64)/L64*100 -> -87.810453 | M65: =(M25-M64)/M64*100 -> -88.506907 | N65: =(N25-N64)/N64*100 -> -88.452134 | ... BU65: =(BU25-BU64)/BU64*100 -> -3.2486211
E66: نرخ ارز رویکرد پولی با نفت - سال پایه 1350 | R66: =R57*($R$80/R80) -> 76 | S66: =S57*($R$80/S80) -> 70.872771 | T66: =T57*($R$80/T80) -> 49.112365 | U66: =U57*($R$80/U80) -> 18.669376 | V66: =V57*($R$80/V80) -> 23.756219 | W66: =W57*($R$80/W80) -> 22.026163 | X66: =X57*($R$80/X80) -> 25.030907 | Y66: =Y57*($R$80/Y80) -> 48.95826 | ... BU66: =BU57*($R$80/BU80) -> 242911.52
E67: نرخ ارز رویکرد پولی با نفت - سال پایه 1360 | R67: =R58*($AB$80/R80) -> 169.55145 | S67: =S58*($AB$80/S80) -> 158.11291 | T67: =T58*($AB$80/T80) -> 109.56675 | U67: =U58*($AB$80/U80) -> 41.650261 | V67: =V58*($AB$80/V80) -> 52.998703 | W67: =W58*($AB$80/W80) -> 49.139053 | X67: =X58*($AB$80/X80) -> 55.842457 | Y67: =Y58*($AB$80/Y80) -> 109.22295 | ... BU67: =BU58*($AB$80/BU80) -> 541921.08
E68: نرخ ارز رویکرد پولی با نفت - سال پایه 1371 | R68: =R59*($AM$80/R80) -> 231.4929 | S68: =S59*($AM$80/S80) -> 215.87557 | T68: =T59*($AM$80/T80) -> 149.59426 | U68: =U59*($AM$80/U80) -> 56.866157 | V68: =V59*($AM$80/V80) -> 72.360473 | W68: =W59*($AM$80/W80) -> 67.090795 | X68: =X59*($AM$80/X80) -> 76.243122 | Y68: =Y59*($AM$80/Y80) -> 149.12486 | ... BU68: =BU59*($AM$80/BU80) -> 739898.6
E69: نرخ ارز رویکرد پولی با نفت - سال پایه 1381 | R69: =R60*($AW$80/R80) -> 165.6718 | S69: =S60*($AW$80/S80) -> 154.49499 | T69: =T60*($AW$80/T80) -> 107.05965 | U69: =U60*($AW$80/U80) -> 40.697224 | V69: =V60*($AW$80/V80) -> 51.785992 | W69: =W60*($AW$80/W80) -> 48.014658 | X69: =X60*($AW$80/X80) -> 54.564675 | Y69: =Y60*($AW$80/Y80) -> 106.72372 | ... BU69: =BU60*($AW$80/BU80) -> 529520.9
E70: نرخ ارز رویکرد پولی با نفت - سال پایه 1366 | R70: =R61*($AH$80/R80) -> 370.55945 | S70: =S61*($AH$80/S80) -> 345.5602 | T70: =T61*($AH$80/T80) -> 239.46119 | U70: =U61*($AH$80/U80) -> 91.027811 | V70: =V61*($AH$80/V80) -> 115.83015 | W70: =W61*($AH$80/W80) -> 107.39478 | X70: =X61*($AH$80/X80) -> 122.04525 | Y70: =Y61*($AH$80/Y80) -> 238.70981 | ... BU70: =BU61*($AH$80/BU80) -> 1184383.7
E71: نرخ ارز رویکرد پولی با نفت - سال پایه 1369 | R71: =R62*($AK$80/R80) -> 414.66914 | S71: =S62*($AK$80/S80) -> 386.69409 | T71: =T62*($AK$80/T80) -> 267.96555 | U71: =U62*($AK$80/U80) -> 101.86334 | V71: =V62*($AK$80/V80) -> 129.61804 | W71: =W62*($AK$80/W80) -> 120.17855 | X71: =X62*($AK$80/X80) -> 136.57296 | Y71: =Y62*($AK$80/Y80) -> 267.12473 | ... BU71: =BU62*($AK$80/BU80) -> 1325367.3
E72: نرخ ارز رویکرد پولی با نفت - سال پایه 1371 | R72: =R59*($AM$80/R80) -> 231.4929 | S72: =S59*($AM$80/S80) -> 215.87557 | T72: =T59*($AM$80/T80) -> 149.59426 | U72: =U59*($AM$80/U80) -> 56.866157 | V72: =V59*($AM$80/V80) -> 72.360473 | W72: =W59*($AM$80/W80) -> 67.090795 | X72: =X59*($AM$80/X80) -> 76.243122 | Y72: =Y59*($AM$80/Y80) -> 149.12486 | ... BT72: =BT59*($AM$80/BT80) -> 620963.42 | BU72: =BU59*($AL$80/BU80) -> 723109.5
E73: نرخ ارز رویکرد پولی با نفت - سال پایه 1378 | R73: =R63*($AT$80/R80) -> 245.61157 | S73: =S63*($AT$80/S80) -> 229.04175 | T73: =T63*($AT$80/T80) -> 158.71796 | U73: =U63*($AT$80/U80) -> 60.334404 | V73: =V63*($AT$80/V80) -> 76.773713 | W73: =W63*($AT$80/W80) -> 71.182639 | X73: =X63*($AT$80/X80) -> 80.893164 | Y73: =Y63*($AT$80/Y80) -> 158.21994 | ... BU73: =BU63*($AT$80/BU80) -> 785024.75
E74: میانگین نرخ ارز رویکرد پولی با نفت | R74: =AVERAGEA(R70,R71,R73) -> 343.61339 | S74: =AVERAGEA(S70,S71,S73) -> 320.43201 | T74: =AVERAGEA(T70,T71,T73) -> 222.04824 | U74: =AVERAGEA(U70,U71,U73) -> 84.408519 | V74: =AVERAGEA(V70,V71,V73) -> 107.4073 | W74: =AVERAGEA(W70,W71,W73) -> 99.585323 | X74: =AVERAGEA(X70,X71,X73) -> 113.17046 | Y74: =AVERAGEA(Y70,Y71,Y73) -> 221.35149 | ... BU74: =AVERAGEA(BU70,BU71,BU73) -> 1098258.6
E75: حباب نرخ ارز رویکرد پولی با نفت با بازار آزاد | R75: =(R25-R74)/R74*100 -> -77.882119 | S75: =(S25-S74)/S74*100 -> -78.466571 | T75: =(T25-T74)/T74*100 -> -69.376023 | U75: =(U25-U74)/U74*100 -> -19.439411 | V75: =(V25-V74)/V74*100 -> -36.689591 | W75: =(W25-W74)/W74*100 -> -28.704353 | X75: =(X25-X74)/X74*100 -> -37.262779 | Y75: =(Y25-Y74)/Y74*100 -> -54.822984 | ... BS75: =(BS25-BS74)/BS74*100 -> 30.019684
E76: نرخ ارز بازار آزاد (ریال) | F76: 76 | G76: 76 | H76: 76 | I76: 76 | J76: 76 | K76: 76 | L76: 76 | M76: 76 | N76: 76 | O76: 76 | P76: 76 | Q76: 76 | R76: 76 | S76: 69 | T76: 68 | U76: 68 | V76: 68 | W76: 71 | X76: 71 | Y76: 100 | Z76: 141 | AA76: 200 | AB76: 270 | AC76: 350 | AD76: 450 | AE76: 580 | AF76: 614 | AG76: 742 | AH76: 991 | AI76: 966 | AJ76: 1207.1 | AK76: 1412.3 | AL76: 1420.2 | AM76: 1498 | AN76: 1806 | AO76: 2635 | AP76: 4036 | AQ76: 4446 | AR76: 4782 | AS76: 6468 | AT76: 8634 | AU76: 8131 | AV76: 7925 | AW76: 7991 | AX76: 8323 | AY76: 8747 | AZ76: 9042 | BA76: 9226 | BB76: 9357 | BC76: 9667 | BD76: 9979 | BE76: 10601 | BF76: 13568 | BG76: 26059 | BH76: 31839 | BI76: 32801 | BJ76: 34501 | BK76: 36440 | BL76: 40453 | BM76: 103378 | BN76: 129185 | BO76: 228809 | BP76: 259476 | BQ76: 349266 | BR76: 517807.6 | BS76: 690000 | BT76: 965656.05 | BU76: 2000000 | BV76: 2500000
E78: صادرات نفتی (میليارد دلار) | G78: =G12/1000 -> 0 | H78: =H12/1000 -> 0 | I78: =I12/1000 -> 0 | J78: =J12/1000 -> 0 | K78: =K12/1000 -> 0 | L78: =L12/1000 -> 0 | M78: =M12/1000 -> 0 | N78: =N12/1000 -> 0 | ... BV78: =BV12/1000 -> 41
E79: صادرات غیر نفتی (میليارد دلار) | G79: =G87/1000 -> 0 | H79: =H87/1000 -> 0 | I79: =I87/1000 -> 0 | J79: =J87/1000 -> 0 | K79: =K87/1000 -> 0 | L79: =L87/1000 -> 0 | M79: =M87/1000 -> 0 | N79: =N87/1000 -> 0 | ... BV79: =BV87/1000 -> 0
E80: ارزش حقیقی صادرات نفتی (میليارد دلار) | G80: =#REF!/1000 -> #REF! | H80: =#REF!/1000 -> #REF! | I80: =#REF!/1000 -> #REF! | J80: =#REF!/1000 -> #REF! | K80: =#REF!/1000 -> #REF! | L80: =#REF!/1000 -> #REF! | M80: =#REF!/1000 -> #REF! | N80: =#REF!/1000 -> #REF! | ... Q80: =#REF!/1000 -> #REF! | R80: =R78*(100/R13) -> 36.283179 | S80: =S78*(100/S13) -> 39.037236 | T80: =T78*(100/T13) -> 40.851028 | U80: =U78*(100/U13) -> 92.929896 | V80: =V78*(100/V13) -> 81.174182 | W80: =W78*(100/W13) -> 92.646606 | X80: =X78*(100/X13) -> 84.371558 | Y80: =Y78*(100/Y13) -> 52.346691 | ... BU80: =BU78*(100/BU13) -> 30.422158 | BV80: =#REF!/1000 -> #REF!
E81: ارزش حقیقی صادرات غیر نفتی (میليارد دلار) | G81: =G79*(100/G13) -> 0 | H81: =H79*(100/H13) -> 0 | I81: =I79*(100/I13) -> 0 | J81: =J79*(100/J13) -> 0 | K81: =K79*(100/K13) -> 0 | L81: =L79*(100/L13) -> 0 | M81: =M79*(100/M13) -> 0 | N81: =N79*(100/N13) -> 0 | ... BU81: =BU79*(100/BU13) -> 35.872521 | BV81: =#REF!/1000 -> #REF!
E82: ارزش حقیقی صادرات نفتی به قیمت های ثابت 1381 (میلیارد دلار) | G82: =G78*($AW$13/G13) -> 0 | H82: =H78*($AW$13/H13) -> 0 | I82: =I78*($AW$13/I13) -> 0 | J82: =J78*($AW$13/J13) -> 0 | K82: =K78*($AW$13/K13) -> 0 | L82: =L78*($AW$13/L13) -> 0 | M82: =M78*($AW$13/M13) -> 0 | N82: =N78*($AW$13/N13) -> 0 | ... BU82: =BU78*($AW$13/BU13) -> 25.09538
E83: ارزش حقیقی صادرات غیر نفتی به قیمت های ثابت 1381 (میلیارد دلار) | G83: =G79*($AW$13/G13) -> 0 | H83: =H79*($AW$13/H13) -> 0 | I83: =I79*($AW$13/I13) -> 0 | J83: =J79*($AW$13/J13) -> 0 | K83: =K79*($AW$13/K13) -> 0 | L83: =L79*($AW$13/L13) -> 0 | M83: =M79*($AW$13/M13) -> 0 | N83: =N79*($AW$13/N13) -> 0 | ... BU83: =BU79*($AW$13/BU13) -> 29.59141
E84: ارزش حقیقی صادرات نفتی به قیمت های ثابت 1402 (میلیارد دلار) | R84: =R78*($BR$13/R13) -> 50.400455 | S84: =S78*($BR$13/S13) -> 54.226077 | T84: =T78*($BR$13/T13) -> 56.745591 | U84: =U78*($BR$13/U13) -> 129.08762 | V84: =V78*($BR$13/V13) -> 112.75792 | W84: =W78*($BR$13/W13) -> 128.6941 | X84: =X78*($BR$13/X13) -> 117.19935 | Y84: =Y78*($BR$13/Y13) -> 72.714054 | ... BU84: =BU78*($BR$13/BU13) -> 42.258993
E85: ارزش حقیقی صادرات غیر نفتی به قیمت های ثابت 1402 (میلیارد دلار) | R85: =R79/R13*$BR$13 -> 3.8475942 | S85: =S79/S13*$BR$13 -> 4.139644 | T85: =T79/T13*$BR$13 -> 4.3319849 | U85: =U79/U13*$BR$13 -> 3.5751876 | V85: =V79/V13*$BR$13 -> 3.33197 | W85: =W79/W13*$BR$13 -> 2.8741807 | X85: =X79/X13*$BR$13 -> 2.6137589 | Y85: =Y79/Y13*$BR$13 -> 2.5213111 | ... BU85: =BU79/BU13*$BR$13 -> 49.830016
E87: صادرات غیر نفتی (میلیون دلار) | R87: =S87*0.9 -> 514.35 | S87: =T87*0.9 -> 571.5 | T87: 635 | U87: 582 | V87: 592 | W87: 540 | X87: 523 | Y87: 543 | Z87: 812 | AA87: 645 | AB87: 340 | AC87: 284 | AD87: 357 | AE87: 361 | AF87: 465 | AG87: 916 | AH87: 1161 | AI87: 1036 | AJ87: 1044 | AK87: 1312 | AL87: 2649 | AM87: 2988 | AN87: 3747 | AO87: 4831 | AP87: 3257 | AQ87: 3120 | AR87: 3131.01 | AS87: 3171.22 | AT87: 3793.34 | AU87: 4194.69 | AV87: 4649.82 | AW87: 5144 | AX87: 6636.65 | AY87: 7519.86 | AZ87: 10705.09 | BA87: 14178.76 | BB87: 16100.57 | BC87: 18886.3 | BD87: 22136.44 | BE87: 26594.82 | BF87: 33183.05 | BG87: 34122.55 | BH87: 34077.8 | BI87: 40201.86 | BJ87: 36046.66 | BK87: 31703.29 | BL87: 36360.64 | BM87: 38511.89 | BN87: 37610.6 | BO87: 31997.85 | BP87: 45497.02 | BQ87: 47246.253 | BR87: 47246.253 | BS87: =BR87+10000 -> 57246.253 | BT87: =BS87-1005 -> 56241.253 | BU87: =BT87-2000 -> 54241.253
E90: قیمت نفت برنت | G90: 8.5149781 | H90: 8.0450248 | I90: 7.6461378 | J90: 7.6863294 | K90: 7.3275697 | L90: 7.107594 | M90: 6.5652247 | N90: 6.3644634 | O90: 6.3721298 | P90: 5.8192247 | Q90: 5.2122356 | R90: 6.9220738 | S90: 6.8337153 | T90: 9.0897024 | U90: 29.157856 | V90: 24.956436 | W90: 27.483717 | X90: 27.469108 | Y90: 24.298757 | Z90: 52.218042 | AA90: 56.526048 | AB90: 54.342465 | AC90: 51.531475 | AD90: 48.088064 | AE90: 47.346007 | AF90: 45.542674 | AG90: 20.902924 | AH90: 24.120404 | AI90: 18.371585 | AJ90: 22.401339 | AK90: 27.665256 | AL90: 23.651811 | AM90: 22.806755 | AN90: 19.515257 | AO90: 18.980486 | AP90: 18.69786 | AQ90: 22.638581 | AR90: 22.317861 | AS90: 15.893481 | AT90: 22.421078 | AU90: 35.464472 | AV90: 31.790894 | AW90: 32.929654 | AX90: 36.305155 | AY90: 44.392221 | AZ90: 60.879161 | BA90: 71.510856 | BB90: 74.545659 | BC90: 94.34869 | BD90: 63.996811 | BE90: 79.040772 | BF90: 93.70216 | BG90: 95.290044 | BH90: 94.874656 | BI90: 88.941774 | BJ90: 51.841448 | BK90: 45.544622 | BL90: 54.270298 | BM90: 67.073111 | BN90: 61.71608 | BO90: 42.142776 | BP90: 63.135791 | BQ90: 87.954157 | BR90: 79.75 | BS90: 80
E91: قیمت حقیقی نفت به قیمت های ثابت 1402 | G91: =G90/G13*$BR$13 -> 87.207725 | H91: =H90/H13*$BR$13 -> 81.521738 | I91: =I90/I13*$BR$13 -> 76.561937 | J91: =J90/J13*$BR$13 -> 76.021961 | K91: =K90/K13*$BR$13 -> 71.558464 | L91: =L90/L13*$BR$13 -> 68.327158 | M91: =M90/M13*$BR$13 -> 61.266004 | N91: =N90/N13*$BR$13 -> 57.790124 | ... BS91: =BS90/BS13*$BR$13 -> 78.04878
C94: صادرات نفت و گاز (میلیون دلار) | E94: بخش خارجي/ موازنه پرداخت ها/ استاندارد شماره 4/ تراز حساب جاري (حساب جاري)/ تراز بازرگاني (حساب کالا)/ صادرات | T94: 8318 | U94: 21014 | V94: 20034 | W94: 24179 | X94: 23451 | Y94: 15660 | Z94: 24158 | AA94: 11648 | AB94: 10619 | AC94: 21798 | AD94: 21150 | AE94: 16726 | AF94: 13710 | AG94: 6255 | AH94: 10755 | AI94: 9673 | AJ94: 12037 | AK94: 17993 | AL94: 16012 | AM94: 16880 | AN94: 14333 | AO94: 14603 | AP94: 15103 | AQ94: 19271 | AR94: 15471.3 | AS94: 9933 | AT94: 17089 | AU94: 24279.9 | AV94: 19338.64 | AW94: 22965.6 | AX94: 27355.02 | AY94: 36314.74 | AZ94: 53819.7 | BA94: 62011.49 | BB94: 81566.66 | BC94: 82402.52 | BD94: 66189.64 | BE94: 86192.87 | BF94: 112622.5 | BG94: 63173.68 | BH94: 58832.03 | BI94: 48773.8 | BJ94: 26948.76 | BK94: 50239.74 | BL94: 59673.1 | BM94: 54139.1 | BN94: 22364.58 | BO94: 17850.36 | BP94: 33973.11 | BQ94: 45764.89
C95: صادرات نفتي (شامل گازو میعانات است) | E95: بخش خارجي/ موازنه پرداخت ها/ استاندارد شماره 5/ حساب جاري/ حساب کالا/ صادرات کالا (فوب) | AR95: 15931.892 | AS95: 10659.173 | AT95: 17976.917 | AU95: 24955.164 | AV95: 20152.595 | AW95: 23784.948 | AX95: 28406.995 | AY95: 37448.16 | AZ95: 55790.708 | BA95: 64665.287 | BB95: 84505.16 | BC95: 86618.868 | BD95: 69957.125 | BE95: 90191.235 | BF95: 119147.77 | BG95: 68083.709 | BH95: 64540.51 | BI95: 55406.623 | BJ95: 31848.436 | BK95: 53362.27 | BL95: 62767.593 | BM95: 56998.713 | BN95: 26049.32 | BO95: 23311.536 | BP95: 38722.502 | BQ95: 55410.01 | BR95: 56796.41
BJ149: 0.1
BJ150: 0.1
BJ151: 0.1
BJ152: 0.1
BJ153: 0.1
BJ154: 0.1
BJ155: 0.1
BJ156: 0.1
BJ157: 0.1
BJ158: 0.1
BJ159: 0.1
BJ160: 0.1
... BJ206: 248
BJ207: =BJ206*(1+BI207%) -> 248
BJ208: =BJ207*(1+BI208%) -> 248
...

Sheet Macro Data
F1: گزارش سری‌های زمانی
G2: شاخص کل | I2: شاخص کل | J2: شاخص کل | Q2: عنوان متغیر: تولید ناخالص داخلی به قیمت پایه | R2: مسیر در درختواره: حساب های ملی/ حساب های ملی بر اساس سال پایه (100=1400)/ تولید(درآمد) ناخالص ملی بر حسب فعالیت های اقتصادی(به قیمت های جاری) | S2: در نظام حساب‌های ملی، تولید ناخالص داخلی به قیمت بازار عبارت است از ارزش بازار کلیه کالاها و خدماتی که در قلمرو داخلی اقتصاد توسط تولیدکنندگان مقیم تولید می‌شوند. با کسر کردن خالص مالیات‌های غیر مستقیم (یا خالص مالیات بر محصول) از تولید ناخالص داخلی به قیمت بازار، تولید ناخالص داخلی به قیمت پایه به دست می‌آید. خالص مالیات‌های غیر مستقیم برابر است با مالیات‌های غیر مستقیم منهای کمک‌های دولت به تولید کنندگان (یارانه‌ها). تولید ناخالص داخلی را می‌توان به سه روش تولید، هزینه و درآمد برآورد نمود. براساس روش تولید، تولید ناخالص داخلی به قیمت پایه برابر است با مجموع ارزش افزوده ناخالص ایجاد شده توسط کلیه تولیدکنندگان مقیم در قلمرو داخلی اقتصاد به قیمت پایه. ارزش افزوده ناخالص به قیمت پایه برابر است با ارزش ستانده به قیمت پایه منهای مصرف واسطه به قیمت خریداران. آمار تواتر سالانه آن از سال 1390 قابل گزارش‌گیری است. | T2: ارزش افزوده رشته فعاليت‌هاي اقتصادي كشور به قيمت‌هاي ثابت در دوره 98-1340 (سال پايه:1390)-(ميليارد ريال)- مرکز آمار
G3: شاخص هاي قيمت/ شاخص بهاي کالاها و خدمات مصرفي/ شاخص بهاي کالاها و خدمات مصرفي(100=1395) | H3: تورم_ شهری_ بانک مرکزی | I3: شاخص هاي قيمت/ شاخص بهاي کالاها و خدمات مصرفي/ شاخص بهاي کالاها و خدمات مصرفي (100=1390) | J3: شاخص هاي قيمت/ شاخص بهاي کالاها و خدمات مصرفي/ شاخص بهاي کالاها و خدمات مصرفي(100=1400) | N3: سال | O3: شاخص بهای کالاها و خدمات مصرفی - خانوارهای شهری-(1395=100)- | P3: نرخ تورم | T3: محصول ناخالص داخلي ( به قيمت بازار ) | U3: محصول ناخالص داخلي بدون نفت ( به قيمت بازار ) | V3: رشد اقتصادی با نفت | W3: رشد اقتصادی بدون نفت
F4: 1338 | H4: 13 | I4: 0.1 | N4: 1315 | O4: 0.004 | P4: -.-
F5: 1339 | H5: 7.9 | I5: 0.1 | N5: 1316 | O5: 0.004 | P5: 21.2
F6: 1340 | H6: 1.6 | I6: 0.1 | N6: 1317 | O6: 0.004 | P6: 8.8 | T6: 1057017.1 | U6: 1057017.1
F7: 1341 | H7: 0.9 | I7: 0.1 | N7: 1318 | O7: 0.004 | P7: 8 | T7: 1165380.1 | U7: 1165380.1
F8: 1342 | H8: 1 | I8: 0.1 | N8: 1319 | O8: 0.004 | P8: 13.8 | T8: 1263309.9 | U8: 1263309.9
F9: 1343 | H9: 4.5 | I9: 0.1 | N9: 1320 | O9: 0.008 | P9: 49.5 | T9: 1404074.2 | U9: 1404074.2
F10: 1344 | H10: 0.3 | I10: 0.1 | M10: رشد تولید | N10: 1321 | O10: 0.012 | P10: 96.2 | T10: 1590778.8 | U10: 1590778.8
F11: 1345 | H11: 0.8 | I11: 0.1 | L11: =(T16/T6-1)*100 -> 234.70317 | M11: دهه 40 | N11: 1322 | O11: 0.028 | P11: 110.5 | T11: 1782032 | U11: 1782032
F12: 1346 | H12: 0.8 | I12: 0.1 | L12: =(T26/T16-1)*100 -> -37.463566 | M12: دهه 50 | N12: 1323 | O12: 0.028 | P12: 2.7 | T12: 2010388.9 | U12: 2010388.9
F13: 1347 | H13: 1.5 | I13: 0.1 | L13: =(T36/T26-1)*100 -> 72.223864 | M13: دهه 60 | N13: 1324 | O13: 0.024 | P13: -14.4 | T13: 2296958.9 | U13: 2296958.9
F14: 1348 | H14: 3.6 | I14: 0.1 | L14: =(T46/T36-1)*100 -> 20.147683 | M14: دهه 70 | N14: 1325 | O14: 0.02 | P14: -11.5 | T14: 2683584.4 | U14: 2683584.4
F15: 1349 | H15: 1.5 | I15: 0.1 | L15: =(T56/T46-1)*100 -> 49.993141 | M15: دهه 80 | N15: 1326 | O15: 0.024 | P15: 6.6 | T15: 2908296.8 | U15: 2908296.8
F16: 1350 | H16: 5.5 | I16: 0.1 | L16: =(T63/T56-1)*100 -> 9.1881498 | M16: 90-97 | N16: 1327 | O16: 0.024 | P16: 11.1 | T16: 3537869.9 | U16: 3537869.9
F17: 1351 | H17: 6.3 | I17: 0.2 | L17: =(T69/T63-1)*100 -> 19.167582 | M17: 97-1403 | N17: 1328 | O17: 0.028 | P17: 2.3 | T17: 4048210.4 | U17: 4048210.4
F18: 1352 | H18: 11.2 | I18: 0.2 | N18: 1329 | O18: 0.02 | P18: -17.2 | T18: 4566216.3 | U18: 4566216.3
F19: 1353 | H19: 15.5 | I19: 0.2 | N19: 1330 | O19: 0.024 | P19: 8.3 | T19: 4882093.8 | U19: 4882093.8
F20: 1354 | H20: 9.9 | I20: 0.2 | N20: 1331 | O20: 0.024 | P20: 7.2 | T20: 4608071.7 | U20: 4608071.7
F21: 1355 | H21: 16.6 | I21: 0.3 | N21: 1332 | O21: 0.028 | P21: 9.2 | T21: 5261669.2 | U21: 5261669.2
F22: 1356 | H22: 25.1 | I22: 0.3 | N22: 1333 | O22: 0.032 | P22: 15.9 | T22: 4994950.8 | U22: 4994950.8
F23: 1357 | H23: 10 | I23: 0.3 | N23: 1334 | O23: 0.032 | P23: 1.7 | T23: 3683448.1 | U23: 3683448.1
F24: 1358 | H24: 11.4 | I24: 0.4 | N24: 1335 | O24: 0.036 | P24: 8.8 | T24: 3243925.6 | U24: 3243925.6
F25: 1359 | H25: 23.5 | I25: 0.5 | N25: 1336 | O25: 0.036 | P25: 4.4 | T25: 2359032.2 | U25: 2359032.2
F26: 1360 | H26: 22.8 | I26: 0.6 | N26: 1337 | O26: 0.036 | P26: 1 | T26: 2212457.7 | U26: 2212457.7
F27: 1361 | H27: 19.2 | I27: 0.7 | N27: 1338 | O27: 0.044 | P27: 13 | T27: 2900881.4 | U27: 2900881.4
F28: 1362 | H28: 14.8 | I28: 0.8 | N28: 1339 | O28: 0.048 | P28: 7.9 | T28: 3099718.4 | U28: 3099718.4
F29: 1363 | H29: 10.4 | I29: 0.9 | N29: 1340 | O29: 0.048 | P29: 1.6 | T29: 2965972.3 | U29: 2965972.3
... F34: 1368 | H34: 17.4 | I34: 2.2 | N34: 1345 | O34: 0.052 | P34: 0.8 | T34: 2977222.7 | U34: 2977222.7
F35: 1369 | G35: 1 | H35: 9 | I35: 2.45344 | N35: 1346 | O35: 0.052 | P35: 0.8 | T35: 3355192.2 | U35: 3355192.2
F36: 1370 | G36: 1.2 | H36: 20.7 | I36: 2.95856 | N36: 1347 | O36: 0.052 | P36: 1.5 | T36: 3810380.1 | U36: 3810380.1
F37: 1371 | G37: 1.5 | H37: 24.4 | I37: 3.68016 | N37: 1348 | O37: 0.052 | P37: 3.6 | T37: 3923017.1 | U37: 3923017.1
F38: 1372 | G38: 1.8 | H38: 22.9 | I38: 4.51 | N38: 1349 | O38: 0.056 | P38: 1.5 | T38: 4107256.1 | U38: 4107256.1
F39: 1373 | G39: 2.5 | H39: 35.2 | I39: 6.09752 | N39: 1350 | O39: 0.056 | P39: 5.5 | T39: 4048920.7 | U39: 4048920.7
F40: 1374 | G40: 3.7 | H40: 49.4 | I40: 9.09216 | N40: 1351 | O40: 0.06 | P40: 6.3 | T40: 4128768.9 | U40: 4128768.9
F41: 1375 | G41: 4.5 | H41: 23.2 | I41: 11.1848 | N41: 1352 | O41: 0.069 | P41: 11.2 | T41: 4328952.5 | U41: 4328952.5
F42: 1376 | G42: 5.3 | H42: 17.3 | I42: 13.1 | N42: 1353 | O42: 0.077 | P42: 15.5 | T42: 4207604.5 | U42: 4207604.5
F43: 1377 | G43: 6.3 | H43: 18.1 | I43: 15.5 | N43: 1354 | O43: 0.085 | P43: 9.9 | T43: 4297854.3 | U43: 4297854.3
F44: 1378 | G44: 7.5 | H44: 20.1 | I44: 18.6 | N44: 1355 | O44: 0.101 | P44: 16.6 | T44: 4279479.4 | U44: 4279479.4
F45: 1379 | G45: 8.5 | H45: 12.6 | I45: 21 | N45: 1356 | O45: 0.125 | P45: 25.1 | T45: 4508707.3 | U45: 4508707.3
F46: 1380 | G46: 9.4 | H46: 11.4 | I46: 23.4 | N46: 1357 | O46: 0.137 | P46: 10 | T46: 4578083.4 | U46: 4578083.4
... F61: 1395 | G61: 100 | H61: 9 | I61: 248 | N61: 1372 | O61: 1.814 | P61: 22.9 | T61: 7508813.7 | U61: 5891423.5
F62: 1396 | G62: 109.7 | H62: 9.6 | I62: =I61*(1+H62%) -> 271.808 | N62: 1373 | O62: 2.456 | P62: 35.2 | T62: 7869763.3 | U62: 6239523.5
F63: 1397 | G63: 143.84167 | H63: 31.2 | I63: =I62*(1+H63%) -> 356.6121 | N63: 1374 | O63: 3.665 | P63: 49.4 | T63: 7497744 | U63: 6085908.2
F64: 1398 | G64: 203.15 | H64: 41.2 | I64: =I63*(1+H64%) -> 503.53628 | N64: 1375 | O64: 4.52 | P64: 23.2 | T64: 7157212 | U64: 6269914
F65: 1399 | G65: 298.85833 | H65: 47.1 | I65: =I64*(1+H65%) -> 740.70187 | N65: 1376 | O65: 5.298 | P65: 17.3 | T65: 7394932.8 | U65: 6433317.5
F66: 1400 | G66: 437.04167 | H66: 46.2 | I66: =I65*(1+H66%) -> 1082.9061 | J66: 100 | N66: 1377 | O66: 6.258 | P66: 18.1 | T66: 7809275.6 | U66: 6754557.4
F67: 1401 | G67: 640.225 | H67: 53.1 | I67: =I66*(1+H67%) -> 1657.9293 | J67: 153.1 | N67: 1378 | O67: 7.516 | P67: 20.1 | T67: 8205345.2 | U67: 7080674.1
F68: 1402 | G68: =G67*(1+H68%) -> 943.69165 | H68: 47.4 | I68: =I67*(1+H68%) -> 2443.7878 | N68: 1379 | O68: 8.463 | P68: 12.6 | T68: 8674641.1 | U68: 7321346.1
F69: 1403 | G69: =G68*(1+H69%) -> 1281.5333 | H69: 35.8 | I69: =I68*(1+H69%) -> 3318.6638 | N69: 1380 | O69: 9.427 | P69: 11.4 | T69: 8934880.3 | U69: 7453130.3
F70: 1404 | G70: =G69*(1+H70%) -> 1832.5926 | H70: 43 | I70: =I69*(1+H70%) -> 4745.6892 | N70: 1381 | O70: 10.915 | P70: 15.8
F71: 1405 | G71: =G70*(1+H71%) -> 2840.5185 | H71: 55 | I71: =I70*(1+H71%) -> 7355.8183 | N71: 1382 | O71: 12.624 | P71: 15.6
N72: 1383 | O72: 14.544 | P72: 15.2
N73: 1384 | O73: 16.048 | P73: 10.4
N74: 1385 | O74: 17.955 | P74: 11.9
N75: 1386 | O75: 21.265 | P75: 18.4
N76: 1387 | O76: 26.66 | P76: 25.4
N77: 1388 | O77: 29.527 | P77: 10.8
N78: 1389 | O78: 33.188 | P78: 12.4
N79: 1390 | O79: 40.321 | P79: 21.5
N80: 1391 | O80: 52.635 | P80: 30.5
N81: 1392 | O81: 70.916 | P81: 34.7
N82: 1393 | O82: 81.948 | P82: 15.6
N83: 1394 | O83: 91.714 | P83: 11.9
N84: 1395 | O84: 100 | P84: 9
M85: =O84+(O84*P85%) -> 109.6 | N85: 1396 | O85: 109.6 | P85: 9.6
M86: =O85+(O85*P86%) -> 143.7952 | N86: 1397 | O86: 143.842 | P86: 31.2
M87: =O86+(O86*P87%) -> 203.1049 | N87: 1398 | O87: 203.15 | P87: 41.2
M88: =O87+(O87*P88%) -> 298.83365 | N88: 1399 | O88: 298.858 | P88: 47.1
M89: =O88+(O88*P89%) -> 436.9304 | N89: 1400 | O89: 437.042 | P89: 46.2 | Q89: رقم اعلامی در دولت رییسی
M90: =O89+(O89*P90%) -> 669.1113 | N90: 1401 | O90: 640.225 | P90: 53.1 | Q90: 46.5
M91: =O90+(O90*P91%) -> 943.69165 | N91: 1402 | O91: 943.69165 | P91: 47.4 | Q91: 40.7
M92: =O91+(O91*P92%) -> 1281.5333 | N92: 1403 | O92: 1281.5333 | P92: 35.8 | Q92: 30
M93: =O92+(O92*P93%) -> 1832.5926 | N93: 1404 | O93: 1832.5926 | P93: 43
M94: =O93+(O93*P94%) -> 2840.5185 | N94: 1405 | O94: 2840.5185 | P94: 55

Sheet Sheet1
E4: 1390 | F4: 21.5 | G4: 14
E5: 1391 | F5: 30.5 | G5: 13
E6: 1392 | F6: 34.7 | G6: 12
E7: 1393 | F7: 15.6 | G7: 11
E8: 1394 | F8: 11.9 | G8: 10
E9: 1395 | F9: 9 | G9: 9
E10: 1396 | F10: 9.6 | G10: 8
E11: 1397 | F11: 31.2 | G11: 7
E12: 1398 | F12: 41.2 | G12: 6
E13: 1399 | F13: 47.1 | G13: 5
E14: 1400 | F14: 46.2 | G14: 4
E15: 1401 | F15: 53.1 | G15: 3
... E17: 1403 | F17: 35.8 | G17: 1

Sheet monthly-yearly
B1: منبع: بانک مرکزی
B2: سال | C2: نرخ رسمی (ريال) | D2: نرخ بازار غیر رسمی (ريال) | E2: نرخ بازار غیر رسمی (ريال) | F2: رشد نرخ غیررسمی | G2: رشد نیما | H2: رشد نرخ غیررسمی | I2: رشد نیما | J2: متوسط نرخ ارز غیر رسمی در دهه های مختلف
B3: 1338 | C3: 76 | D3: 76
B4: 1339 | C4: 76 | D4: 76 | F4: =D4/D3 -> 1 | H4: =D4/D3-1 -> 0 | BV4: 0.25335806 | BW4: 0.03964503 | BX4: 3.6444114 | BY4: 0.25237763 | BZ4: 1.6853513 | CA4: -0.38383717 | CB4: #DIV/0!
B5: 1340 | C5: 76 | D5: 76 | F5: =D5/D4 -> 1 | H5: =D5/D4-1 -> 0
B6: 1341 | C6: 76 | D6: 76 | F6: =D6/D5 -> 1 | H6: =D6/D5-1 -> 0
B7: 1342 | C7: 76 | D7: 76 | F7: =D7/D6 -> 1 | H7: =D7/D6-1 -> 0 | K7: تحولات رشد میانگین سالانه متغیرها طی دوره های مختلف | X7: 40 | Y7: 50 | Z7: 60 | AA7: 70 | AB7: 80 | AC7: 90-97 | AD7: 98-403
B8: 1343 | C8: 76 | D8: 76 | F8: =D8/D7 -> 1 | H8: =D8/D7-1 -> 0 | K8: 1397 الی 1403 | L8: 90-97 | M8: دهه 80 | N8: دهه 70 | O8: دهه 60 | P8: دهه 50 | Q8: دهه 40 | R8: متغیر | W8: صادرات غیرنفتی | X8: 1.7 | Y8: 5.95785 | Z8: 7.276 | AA8: 34.88226 | AB8: 132.55231 | AC8: 284.20774 | AD8: 266.84423
B9: 1344 | C9: 76 | D9: 76 | F9: =D9/D8 -> 1 | H9: =D9/D8-1 -> 0 | K9: =AVERAGE(D62:D67) -> 264653.6 | L9: =AVERAGE(D55:D64) -> 67703.3 | M9: =AVERAGE(D45:D54) -> 9085.8 | N9: =AVERAGE(D35:D44) -> 4385.62 | O9: =AVERAGE(D26:D35) -> 873.26 | P9: =AVERAGE(D16:D25) -> 112.6 | Q9: =AVERAGE(D5:D15) -> 76 | R9: میانگین نرخ ارز در طی دوره (ریال) | Y9: =Y8/X8-1 -> 2.5046176 | Z9: =Z8/Y8-1 -> 0.22124592 | AA9: =AA8/Z8-1 -> 3.7941534 | AB9: =AB8/AA8-1 -> 2.799992 | AC9: =AC8/AB8-1 -> 1.1441176 | AD9: =AD8/AC8-1 -> -0.061094435
B10: 1345 | C10: 76 | D10: 76 | F10: =D10/D9 -> 1 | H10: =D10/D9-1 -> 0 | K10: =GEOMEAN(F62:F67)-1 -> #REF! | L10: =GEOMEAN(F55:F61)-1 -> 0.21083864 | M10: =GEOMEAN(F45:F54)-1 -> 0.0268814 | N10: =GEOMEAN(F35:F44)-1 -> 0.19130153 | O10: =GEOMEAN(F25:F34)-1 -> 0.21587715 | P10: =GEOMEAN(F15:F24)-1 -> 0.1015942 | Q10: 0 | R10: میانگین هندسی رشد
B11: 1346 | C11: 76 | D11: 76 | F11: =D11/D10 -> 1 | H11: =D11/D10-1 -> 0 | K11: =STDEV(D62:D67) -> 152917.89 | L11: =STDEV(D55:D61) -> 8786.2516 | M11: =STDEV(D45:D54) -> 867.25926 | N11: =STDEV(D35:D44) -> 2657.2141 | O11: =STDEV(D25:D34) -> 377.04991 | P11: =STDEV(D15:D24) -> 44.107948 | Q11: =STDEV(D5:D14) -> 0 | R11: انحراف معیار سالانه نرخ دلار در بازار غیررسمی (ریال) | X11: مجموع درآمدهای نفتی دهه 40 | Y11: 11.65 | Z11: 162.7
B12: 1347 | C12: 76 | D12: 76 | F12: =D12/D11 -> 1 | H12: =D12/D11-1 -> 0 | K12: =K11/K9 -> 0.57780394 | L12: =L11/L9 -> 0.12977583 | M12: =M11/M9 -> 0.095452163 | N12: =N11/N9 -> 0.60589247 | O12: =O11/O9 -> 0.4317728 | P12: =P11/P9 -> 0.39172245 | Q12: =Q11/Q9 -> 0 | R12: انحراف معیار سالانه نرخ دلار در بازار غیررسمی (درصد- نسبت به متوسط نرخ سال) | Z12: =Z11/Y11 -> 13.965665
B13: 1348 | C13: 76 | D13: 76 | F13: =D13/D12 -> 1 | H13: =D13/D12-1 -> 0 | K13: =GEOMEAN([1]Data!#REF!)-1 -> #REF! | L13: =GEOMEAN([1]Data!#REF!)-1 -> #REF! | M13: =GEOMEAN([1]Data!#REF!)-1 -> #REF! | N13: =GEOMEAN([1]Data!#REF!)-1 -> #REF! | O13: =GEOMEAN([1]Data!#REF!)-1 -> #REF! | P13: =GEOMEAN([1]Data!#REF!)-1 -> #REF! | Q13: =GEOMEAN([1]Data!#REF!)-1 -> #REF! | R13: میانگین سالانه حباب ارز (ارز آزاد با نرخ ppp)
B14: 1349 | C14: 76 | D14: 76 | F14: =D14/D13 -> 1 | H14: =D14/D13-1 -> 0 | K14: 97063.9 | L14: 5012 | M14: 886 | N14: 2557 | Q14: =STDEV(D5:D14) -> 0 | R14: انحراف معیار نرخ دلار در بازار غیررسمی (ریال)-اعلامی بانک مرکزی
B15: 1350 | C15: 76 | D15: 76 | F15: =D15/D14 -> 1 | H15: =D15/D14-1 -> 0 | K15: 4.3411774 | L15: 6.6192512 | M15: 0.33766562 | N15: 4.72525 | O15: 4.2307407 | P15: 1.6315789 | Q15: 0 | R15: رشد تجمعی نرخ ارز (درصد)
B16: 1351 | C16: 69 | D16: 69 | F16: =D16/D15 -> 0.90789474 | H16: =D16/D15-1 -> -0.092105263 | K16: 4.1542392 | L16: 2.1714258 | M16: 2.4577836 | N16: 6.0909091 | O16: 3.3345906 | P16: 2.3928571 | Q16: 0.16666667 | R16: تورم تجمعی (درصد) | W16: 0.2081597 | X16: 0.072143502 | Y16: 0.53800559 | Z16: 0.21705812 | AA16: 0.31984475 | AB16: -0.10323135 | AC16: 1.6667579
B17: 1352 | C17: 68 | D17: 68 | F17: =D17/D16 -> 0.98550725 | H17: =D17/D16-1 -> -0.014492754 | K17: 3.0603112 | L17: 4.3149946 | M17: 8.1866044 | N17: 7.7097902 | O17: 3.4230769 | P17: 13.533945 | Q17: 3.3696185 | R17: رشد تجمعی نقدینگی (درصد) | W17: 0.9116203 | X17: -0.52161326 | Y17: 3.4754153 | Z17: 0.55852887 | AA17: 0.69441567 | AB17: 0.72881064 | AC17: #DIV/0!
B18: 1353 | C18: 68 | D18: 68 | F18: =D18/D17 -> 1 | H18: =D18/D17-1 -> 0 | K18: 0.9116203 | L18: -0.52161326 | M18: 3.4754153 | N18: 0.55852887 | O18: 0.69441567 | P18: 0.72881064 | Q18: 5.52 | R18: رشد صادرات نفت و گاز ومیعانات (درصد)
B19: 1354 | C19: 68 | D19: 68 | F19: =D19/D18 -> 1 | H19: =D19/D18-1 -> 0 | K19: 0.19167582 | L19: 0.091881498 | M19: 0.49993141 | N19: 0.20147683 | O19: 0.72223864 | P19: -0.37463566 | Q19: 2.3470317 | R19: رشد تولید ناخالص داخلی
B20: 1355 | C20: 71 | D20: 71 | F20: =D20/D19 -> 1.0441176 | H20: =D20/D19-1 -> 0.044117647 | K20: 0.25335806 | L20: 0.03964503 | M20: 3.6444114 | N20: 0.25237763 | O20: 1.6853513 | P20: -0.38383717 | Q20: 2.99 | R20: رشد صادرات غیرنفتی
B21: 1356 | C21: 71 | D21: 71 | F21: =D21/D20 -> 1 | H21: =D21/D20-1 -> 0
B22: 1357 | C22: 70 | D22: 100 | F22: =D22/D21 -> 1.4084507 | H22: =D22/D21-1 -> 0.4084507
B23: 1358 | C23: 70 | D23: 141 | F23: =D23/D22 -> 1.41 | H23: =D23/D22-1 -> 0.41
B24: 1359 | C24: 71 | D24: 200 | F24: =D24/D23 -> 1.4184397 | H24: =D24/D23-1 -> 0.41843972
B25: 1360 | C25: 80 | D25: 270 | F25: =D25/D24 -> 1.35 | H25: =D25/D24-1 -> 0.35
B26: 1361 | C26: 84 | D26: 350 | F26: =D26/D25 -> 1.2962963 | H26: =D26/D25-1 -> 0.2962963
B27: 1362 | C27: 87 | D27: 450 | F27: =D27/D26 -> 1.2857143 | H27: =D27/D26-1 -> 0.28571429
B28: 1363 | C28: 92 | D28: 580 | F28: =D28/D27 -> 1.2888889 | H28: =D28/D27-1 -> 0.28888889
B29: 1364 | C29: 88 | D29: 614 | F29: =D29/D28 -> 1.0586207 | H29: =D29/D28-1 -> 0.05862069
B30: 1365 | C30: 77 | D30: 742 | F30: =D30/D29 -> 1.2084691 | H30: =D30/D29-1 -> 0.20846906
B31: 1366 | C31: 70 | D31: 991 | F31: =D31/D30 -> 1.3355795 | H31: =D31/D30-1 -> 0.33557951
B32: 1367 | C32: 69 | D32: 966 | F32: =D32/D31 -> 0.97477296 | H32: =D32/D31-1 -> -0.025227043
... B34: 1369 | C34: 66.9 | D34: 1412.3 | F34: =D34/D33 -> 1.1699942 | H34: =D34/D33-1 -> 0.1699942
B35: 1370 | C35: 67.8 | D35: 1420.2 | F35: =D35/D34 -> 1.0055937 | H35: =D35/D34-1 -> 0.0055937124 | K35: تورم | P35: بیشتر رشد میانگین سالانه نرخ ارز | S35: 234.70317
B36: 1371 | C36: 1458.5 | D36: 1498 | F36: =D36/D35 -> 1.054781 | H36: =D36/D35-1 -> 0.054781017 | K36: سال میلادی | L36: سال شمسی | M36: تورم شهری ایران | O36: 1397 | P36: 1.5555089 | S36: -37.463566
B37: 1372 | C37: 1653 | D37: 1806 | F37: =D37/D36 -> 1.2056075 | H37: =D37/D36-1 -> 0.20560748 | K37: 2000 | L37: 1379 | M37: 12.292359 | O37: 1391 | P37: 0.92062205 | S37: 72.223864
B38: 1373 | C38: 1750 | D38: 2635 | F38: =D38/D37 -> 1.4590255 | H38: =D38/D37-1 -> 0.45902547 | K38: 2001 | L38: 1380 | M38: 11.538462 | O38: 1399 | P38: 0.77117312 | S38: 20.147683
B39: 1374 | C39: 1750 | D39: 4036 | F39: =D39/D38 -> 1.5316888 | H39: =D39/D38-1 -> 0.5316888 | K39: 2002 | L39: 1381 | M39: 13.225475 | O39: 1374 | P39: 0.5316888 | S39: 49.993141
B40: 1375 | C40: 1754 | D40: 4446 | F40: =D40/D39 -> 1.1015857 | H40: =D40/D39-1 -> 0.10158573 | K40: 2003 | L40: 1382 | M40: 13.896724 | O40: 1402 | P40: 0.48883659 | S40: 9.1881498
B41: 1376 | C41: 1755 | D41: 4782 | F41: =D41/D40 -> 1.0755735 | H41: =D41/D40-1 -> 0.075573549 | K41: 2004 | L41: 1383 | M41: 14.6115 | O41: 1373 | P41: 0.45902547 | S41: 19.167582
B42: 1377 | C42: 1755 | D42: 6468 | F42: =D42/D41 -> 1.3525721 | H42: =D42/D41-1 -> 0.35257215 | K42: 2005 | L42: 1384 | M42: 12.106158 | O42: 1359 | P42: 0.41843972
B43: 1378 | C43: 1755 | D43: 8634 | F43: =D43/D42 -> 1.3348794 | H43: =D43/D42-1 -> 0.33487941 | K43: 2006 | L43: 1385 | M43: 13.698942 | O43: 1358 | P43: 0.41
B44: 1379 | C44: 1755 | D44: 8131 | F44: =D44/D43 -> 0.94174195 | H44: =D44/D43-1 -> -0.05825805 | K44: 2007 | L44: 1386 | M44: 17.229154 | O44: 1357 | P44: 0.4084507
B45: 1380 | C45: 1755 | D45: 7925 | F45: =D45/D44 -> 0.97466486 | H45: =D45/D44-1 -> -0.025335137 | K45: 2008 | L45: 1387 | M45: 25.548119 | O45: 1360,13770 , 1401 | P45: 0.35257215
B46: 1381 | C46: 7958 | D46: 7991 | F46: =D46/D45 -> 1.0083281 | H46: =D46/D45-1 -> 0.0083280757 | K46: 2009 | L46: 1388 | M46: 9.465752
B47: 1382 | C47: 8282 | D47: 8323 | F47: =D47/D46 -> 1.0415467 | H47: =D47/D46-1 -> 0.04154674 | K47: 2010 | L47: 1389 | M47: 13.921117
B48: 1383 | C48: 8719 | D48: 8747 | F48: =D48/D47 -> 1.0509432 | H48: =D48/D47-1 -> 0.05094317 | K48: 2011 | L48: 1390 | M48: 26.364381 | N48: =_xlfn.STDEV.P(D35:D44) -> 2520.8547
B49: 1384 | C49: 9023 | D49: 9042 | F49: =D49/D48 -> 1.0337258 | H49: =D49/D48-1 -> 0.033725849 | K49: 2012 | L49: 1391 | M49: 28.558178 | N49: =STDEVA(D35:D44) -> 2657.2141
B50: 1385 | C50: 9195 | D50: 9226 | F50: =D50/D49 -> 1.0203495 | H50: =D50/D49-1 -> 0.02034948 | K50: 2013 | L50: 1392 | M50: 32.072949
B51: 1386 | C51: 9285 | D51: 9357 | F51: =D51/D50 -> 1.014199 | H51: =D51/D50-1 -> 0.014199003 | K51: 2014 | L51: 1393 | M51: 14.825646
B52: 1387 | C52: 9574 | D52: 9667 | F52: =D52/D51 -> 1.0331303 | H52: =D52/D51-1 -> 0.033130277 | K52: 2015 | L52: 1394 | M52: 11.287159
B53: 1388 | C53: 9920 | D53: 9979 | F53: =D53/D52 -> 1.0322747 | H53: =D53/D52-1 -> 0.032274749 | K53: 2016 | L53: 1395 | M53: 6.7512247
B54: 1389 | C54: 10339 | D54: 10601 | F54: =D54/D53 -> 1.0623309 | H54: =D54/D53-1 -> 0.062330895 | K54: 2017 | L54: 1396 | M54: 8.1290315
B55: 1390 | C55: 10962 | D55: 13568 | F55: =D55/D54 -> 1.2798793 | H55: =D55/D54-1 -> 0.27987926 | K55: 2018 | L55: 1397 | M55: 26.631524
B56: 1391 | C56: 12260 | D56: 26059 | F56: =D56/D55 -> 1.9206221 | H56: =D56/D55-1 -> 0.92062205 | K56: 2019 | L56: 1398 | M56: 34.376669
B57: 1392 | C57: 21253 | D57: 31839 | F57: =D57/D56 -> 1.2218044 | H57: =D57/D56-1 -> 0.22180437 | K57: 2020 | L57: 1399 | M57: 36.199956
B58: 1393 | C58: 26509 | D58: 32801 | F58: =D58/D57 -> 1.0302145 | H58: =D58/D57-1 -> 0.030214517 | K58: 2021 | L58: 1400 | M58: 39.727212
B59: 1394 | C59: 29580 | D59: 34501 | F59: =D59/D58 -> 1.0518277 | H59: =D59/D58-1 -> 0.051827688 | K59: 2022 | L59: 1401 | M59: 45
B60: 1395 | C60: 31389 | D60: 36440 | F60: =D60/D59 -> 1.0562013 | H60: =D60/D59-1 -> 0.05620127
B61: 1396 | C61: 34214 | D61: 40453 | E61: نرخ نیما | F61: =D61/D60 -> 1.1101262 | H61: =D61/D60-1 -> 0.11012623
B62: 1397 | C62: 41950 | D62: 103378 | E62: 91196 | F62: =D62/D61 -> 2.5555089 | H62: =D62/D61-1 -> 1.5555089
B63: 1398 | C63: 42000 | D63: 129185 | E63: 112905 | F63: =D63/D62 -> 1.2496373 | G63: =E63/E62 -> 1.2380477 | H63: =D63/D62-1 -> 0.24963725 | I63: =E63/E62-1 -> 0.23804772
B64: 1399 | C64: 42000 | D64: 228809 | E64: 209579 | F64: =D64/D63 -> 1.7711731 | G64: =E64/E63 -> 1.856242 | H64: =D64/D63-1 -> 0.77117312 | I64: =E64/E63-1 -> 0.85624197
B65: 1400 | C65: 42000 | D65: 259476 | E65: 230835 | F65: =D65/D64 -> 1.1340288 | G65: =E65/E64 -> 1.1014224 | H65: =D65/D64-1 -> 0.13402882 | I65: =E65/E64-1 -> 0.10142238
B66: 1401 | C66: 42000 | D66: 349266 | E66: 273892 | F66: =D66/D65 -> 1.3460436 | G66: =E66/E65 -> 1.1865272 | H66: =D66/D65-1 -> 0.34604356 | I66: =E66/E65-1 -> 0.18652717
B67: 1402 | C67: 285000 | D67: 517807.6 | E67: 380214 | F67: =#REF!/D66 -> #REF! | G67: =E67/E66 -> 1.3881895 | H67: =#REF!/D66-1 -> #REF! | I67: =E67/E66-1 -> 0.38818951
B68: 1403 | C68: 285000 | D68: 690807.6
B69: 1404
B70: 1405
B72: سال | C72: رشد نرخ ارز | E72: رشد تولید در هر دهه
B73: 1359 | C73: 0.41843972 | D73: 7 | E73: 19.167582 | F73: =E73/100 -> 0.19167582 | G73: 0.19167582
B74: 1373 | C74: 0.45902547 | D74: 6 | E74: 9.1881498 | F74: =E74/100 -> 0.091881498 | G74: 0.091881498
B75: 1402 | C75: 0.48883659 | D75: 5 | E75: 49.993141 | F75: =E75/100 -> 0.49993141 | G75: 0.49993141
B76: 1374 | C76: 0.5316888 | D76: 4 | E76: 20.147683 | F76: =E76/100 -> 0.20147683 | G76: 0.20147683
B77: 1399 | C77: 0.77117312 | D77: 3 | E77: 72.223864 | F77: =E77/100 -> 0.72223864 | G77: 0.72223864
B78: 1391 | C78: 0.92062205 | D78: 2 | E78: -37.463566 | F78: =E78/100 -> -0.37463566 | G78: -0.37463566
B79: 1397 | C79: 1.5555089 | D79: 1 | E79: 234.70317 | F79: =E79/100 -> 2.3470317 | G79: 2.3470317
B80: 1338
B81: 1358 | C81: 0.41
B82: 1357 | C82: 0.4084507
B83: 1377,1360 , 1401 | C83: 0.35257215
B84: 1360 | C84: 0.35
B85: 1401 | C85: 0.34604356
B86: 1366 | C86: 0.33557951
B87: 1378 | C87: 0.33487941
B88: 1361 | C88: 0.2962963
B89: 1363 | C89: 0.28888889
B90: 1362 | C90: 0.28571429
B91: 1390 | C91: 0.27987926
B92: 1398 | C92: 0.24963725
B93: 1368 | C93: 0.24958592
B94: 1392 | C94: 0.22180437
B95: 1365 | C95: 0.20846906
... B137: 1351 | C137: -0.092105263

Sheet daily
C1: نرخ روزانه دلار در دهه 80 | F1: نرخ روزانه دلار 90-95 | I1: نرخ روزانه دلار 95-1400 | L1: نرخ روزانه دلار 1400 به بعد (منبع: بورس ویو)
A2: تاریخ میلادی | C2: تاریخ شمسی | D2: نرخ غیررسمی ارز در تهران | F2: تاریخ شمسی | G2: نرخ غیررسمی ارز در تهران | I2: تاریخ شمسی | J2: نرخ غیررسمی ارز در تهران | L2: تاریخ شمسی | M2: نرخ غیررسمی ارز در تهران | O2: تاریخ (ماه) | P2: نرخ متوسط ماهانه دلار | Q2: رشد ماهانه | R2: میانگین رشد هر ماه | S2: چند برابر شدن ماهانه | U2: رشد متوسط ماهانه از سال 90-1403 | AD2: تاریخ (سال) | AE2: نرخ متوسط سالانه دار آزاد
A3: 2002/03/21 | C3: 1381/01/01 | F3: 1390/01/01 | G3: 10364 | I3: 1395/01/01 | L3: 1400/01/01 | O3: 1390:1 | P3: =AVERAGE(G3:G33) -> 10857.034 | Q3: =((P3/AVERAGE(D3261:D3289))-1)*100 -> 5.2516514 | R3: =GEOMEAN(S3,S15,S27,S39,S51,S63,S75,S87,S99,S111,S123,S135,S147,S159)-1 -> 0.027081433 | S3: =(P3/AVERAGE(D3261:D3289)) -> 1.0525165 | T3: فروردین | U3: =R3 -> 0.027081433 | V3: دلار دولتی (روزانه/ ریال) | AD3: 1381
A4: 2002/03/22 | C4: 1381/01/02 | F4: 1390/01/02 | G4: 10364 | I4: 1395/01/02 | L4: 1400/01/02 | O4: 1390:2 | P4: =AVERAGE(G34:G64) -> 11524.4 | Q4: =(P4/P3-1)*100 -> 6.146849 | R4: =GEOMEAN(S4,S16,S28,S40,S52,S64,S76,S88,S100,S112,S124,S136,S148,S160)-1 -> 0.015288914 | S4: =(P4/P3) -> 1.0614685 | T4: اردیبهشت | U4: =R4 -> 0.015288914 | V4: Date | W4: USD | AD4: 1382
A5: 2002/03/23 | C5: 1381/01/03 | F5: 1390/01/03 | G5: 10364 | I5: 1395/01/03 | L5: 1400/01/03 | O5: 1390:3 | P5: =AVERAGE(G65:G95) -> 11999.583 | Q5: =(P5/P4-1)*100 -> 4.1232805 | R5: =GEOMEAN(S5,S17,S29,S41,S53,S65,S77,S89,S101,S113,S125,S137,S149,S161)-1 -> 0.014638708 | S5: =(P5/P4) -> 1.0412328 | T5: خرداد | U5: =R5 -> 0.014638708 | V5: 1371/01/05 | W5: 1439 | Z5: =STDEV(D3:D3289) -> 726.27953 | AA5: =STDEV(D3290:D6942) -> #DIV/0! | AD5: 1383
A6: 2002/03/24 | C6: 1381/01/04 | F6: 1390/01/04 | G6: 10364 | I6: 1395/01/04 | L6: 1400/01/04 | O6: 1390:4 | P6: =AVERAGE(G96:G126) -> 11584 | Q6: =(P6/P5-1)*100 -> -3.4633147 | R6: =GEOMEAN(S6,S18,S30,S42,S54,S66,S78,S90,S102,S114,S126,S138,S150,S162)-1 -> 0.02176665 | S6: =(P6/P5) -> 0.96536685 | T6: تیر | U6: =R6 -> 0.02176665 | V6: 1371/01/08 | W6: 1439 | AD6: 1384
A7: 2002/03/25 | C7: 1381/01/05 | D7: 7924 | F7: 1390/01/05 | G7: 10364 | I7: 1395/01/05 | L7: 1400/01/05 | O7: 1390:5 | P7: =AVERAGE(G127:G157) -> 11527.6 | Q7: =(P7/P6-1)*100 -> -0.48687845 | R7: =GEOMEAN(S7,S19,S31,S43,S55,S67,S79,S91,S103,S115,S127,S139,S151,S163)-1 -> 0.020851317 | S7: =(P7/P6) -> 0.99513122 | T7: مرداد | U7: =R7 -> 0.020851317 | V7: 1371/01/09 | W7: 1439 | AD7: 1385 | AI7: بورس ویو
A8: 2002/03/26 | C8: 1381/01/06 | D8: 7924 | F8: 1390/01/06 | G8: 10384 | I8: 1395/01/06 | J8: 34680 | L8: 1400/01/06 | O8: 1390:6 | P8: =AVERAGE(G158:G188) -> 12352.8 | Q8: =(P8/P7-1)*100 -> 7.1584718 | R8: =GEOMEAN(S8,S20,S32,S44,S56,S68,S80,S92,S104,S116,S128,S140,S152,S164)-1 -> 0.041276893 | S8: =(P8/P7) -> 1.0715847 | T8: شهریور | U8: =R8 -> 0.041276893 | V8: 1371/01/10 | W8: 1439 | AA8: بیشتر رشد ماهانه از سال 1390 | AD8: 1386 | AH8: 2021-03-27 | AI8: 1400-01-07 | AJ8: 247560
A9: 2002/03/27 | C9: 1381/01/07 | D9: 7924 | F9: 1390/01/07 | G9: 10384 | I9: 1395/01/07 | J9: 34660 | L9: 1400/01/07 | M9: 251900 | O9: 1390:7 | P9: =AVERAGE(G219:G248) -> 13155 | Q9: =(P9/P8-1)*100 -> 6.4940742 | R9: =GEOMEAN(S9,S21,S33,S45,S57,S69,S81,S93,S105,S117,S129,S141,S153)-1 -> 0.051944231 | S9: =(P9/P8) -> 1.0649407 | T9: مهر | U9: =R9 -> 0.051944231 | V9: 1371/01/11 | W9: 1439 | Z9: =R3 -> 0.027081433 | AA9: فروردین | AD9: 1387 | AH9: 2021-03-28 | AI9: 1400-01-08 | AJ9: 252330
A10: 2002/03/28 | C10: 1381/01/08 | D10: 7924 | F10: 1390/01/08 | G10: 10392 | I10: 1395/01/08 | L10: 1400/01/08 | M10: 256500 | O10: 1390:8 | P10: =AVERAGE(G100:G130) -> 11525.385 | Q10: =(P10/P9-1)*100 -> -12.387802 | R10: =GEOMEAN(S10,S22,S34,S46,S58,S70,S82,S94,S106,S118,S130,S142,S154,S166)-1 -> -0.00067666676 | S10: =(P10/P9) -> 0.87612198 | T10: آبان | U10: =R10 -> -0.00067666676 | V10: 1371/01/16 | W10: 1439 | Z10: =R4 -> 0.015288914 | AA10: اردیبهشت | AD10: 1388 | AH10: 2021-03-30 | AI10: 1400-01-10 | AJ10: 252540
A11: 2002/03/29 | C11: 1381/01/09 | D11: 7924 | F11: 1390/01/09 | G11: 10394 | I11: 1395/01/09 | J11: 35130 | L11: 1400/01/09 | O11: 1390:9 | P11: =AVERAGE(G249:G278) -> 13760.833 | Q11: =(P11/P10-1)*100 -> 19.395871 | R11: =GEOMEAN(S11,S23,S35,S47,S59,S71,S83,S95,S107,S119,S131,S143,S155,S167)-1 -> 0.011088797 | S11: =(P11/P10) -> 1.1939587 | T11: آذر | U11: =R11 -> 0.011088797 | V11: 1371/01/17 | W11: 1439 | Z11: =R5 -> 0.014638708 | AA11: خرداد | AD11: 1389 | AH11: 2021-03-31 | AI11: 1400-01-11 | AJ11: 252040
A12: 2002/03/30 | C12: 1381/01/10 | D12: 7924 | F12: 1390/01/10 | G12: 10400 | I12: 1395/01/10 | J12: 34820 | L12: 1400/01/10 | M12: 258200 | O12: 1390:10 | P12: =AVERAGE(G279:G308) -> 16170.435 | Q12: =(P12/P11-1)*100 -> 17.510578 | R12: =GEOMEAN(S12,S24,S36,S48,S60,S72,S84,S96,S108,S120,S132,S144,S156,S168)-1 -> 0.026582767 | S12: =(P12/P11) -> 1.1751058 | T12: دی | U12: =R12 -> 0.026582767 | V12: 1371/01/18 | W12: 1439 | Z12: =R6 -> 0.02176665 | AA12: تیر | AD12: 1390 | AE12: =AVERAGE(P3:P14) -> 13527.51 | AH12: 2021-04-01 | AI12: 1400-01-12 | AJ12: 252100
A13: 2002/03/31 | C13: 1381/01/11 | D13: 7924 | F13: 1390/01/11 | G13: 10400 | I13: 1395/01/11 | J13: 34850 | L13: 1400/01/11 | M13: 257200 | O13: 1390:11 | P13: =AVERAGE(G309:G338) -> 18860 | Q13: =(P13/P12-1)*100 -> 16.632609 | R13: =GEOMEAN(S13,S25,S37,S49,S61,S73,S85,S97,S109,S121,S133,S145,S157,S169)-1 -> 0.050868237 | S13: =(P13/P12) -> 1.1663261 | T13: بهمن | U13: =R13 -> 0.050868237 | V13: 1371/01/19 | W13: 1439 | Z13: =R7 -> 0.020851317 | AA13: مرداد | AD13: 1391 | AE13: =AVERAGE(P15:P26) -> 26146.497 | AH13: 2021-04-03 | AI13: 1400-01-14 | AJ13: 244650
A14: 2002/04/01 | C14: 1381/01/12 | D14: 7924 | F14: 1390/01/12 | G14: 10400 | I14: 1395/01/12 | L14: 1400/01/12 | O14: 1390:12 | P14: =AVERAGE(G339:G367) -> 19013.043 | Q14: =(P14/P13-1)*100 -> 0.81147125 | R14: =GEOMEAN(S14,S26,S38,S50,S62,S74,S86,S98,S110,S122,S134,S146,S158,S170,S182)-1 -> 0.025424336 | S14: =(P14/P13) -> 1.0081147 | T14: اسفند | U14: =R14 -> 0.025424336 | V14: 1371/01/20 | W14: 1439 | Z14: =R8 -> 0.041276893 | AA14: شهریور | AD14: 1392 | AE14: =AVERAGE(P27:P38) -> 31861.737 | AH14: 2021-04-04 | AI14: 1400-01-15 | AJ14: 242720
A15: 2002/04/02 | C15: 1381/01/13 | D15: 7924 | F15: 1390/01/13 | G15: 10400 | I15: 1395/01/13 | J15: 34750 | L15: 1400/01/13 | O15: 1391:01 | P15: =AVERAGE(G368:G398) -> 18704.5 | Q15: =(P15/P14-1)*100 -> -1.622799 | S15: =(P15/P14) -> 0.98377201 | V15: 1371/01/22 | W15: 1439 | Z15: =R9 -> 0.051944231 | AA15: مهر | AD15: 1393 | AE15: =AVERAGE(P39:P50) -> 32704.493 | AH15: 2021-04-05 | AI15: 1400-01-16 | AJ15: 244050
A16: 2002/04/03 | C16: 1381/01/14 | D16: 7924 | F16: 1390/01/14 | G16: 11120 | I16: 1395/01/14 | J16: 34490 | L16: 1400/01/14 | M16: 246000 | O16: 1391:02 | P16: =AVERAGE(G399:G429) -> 16882.609 | Q16: =(P16/P15-1)*100 -> -9.7403903 | S16: =(P16/P15) -> 0.9025961 | V16: 1371/01/23 | W16: 1439 | Z16: =R10 -> -0.00067666676 | AA16: آبان | AD16: 1394 | AE16: =AVERAGE(P51:P62) -> 33595.534 | AH16: 2021-04-06 | AI16: 1400-01-17 | AJ16: 247110
A17: 2002/04/04 | C17: 1381/01/15 | F17: 1390/01/15 | G17: 11120 | I17: 1395/01/15 | J17: 34500 | L17: 1400/01/15 | M17: 249700 | O17: 1391:03 | P17: =AVERAGE(G430:G460) -> 17672.5 | Q17: =(P17/P16-1)*100 -> 4.6787278 | S17: =(P17/P16) -> 1.0467873 | V17: 1371/01/24 | W17: 1439 | Z17: =R11 -> 0.011088797 | AA17: آذر | AD17: 1395 | AE17: =AVERAGE(P63:P74) -> 36305.738 | AH17: 2021-04-07 | AI17: 1400-01-18 | AJ17: 244620
A18: 2002/04/05 | C18: 1381/01/16 | D18: 7924 | F18: 1390/01/16 | G18: 11150 | I18: 1395/01/16 | J18: 34760 | L18: 1400/01/16 | M18: 251000 | O18: 1391:04 | P18: =AVERAGE(G461:G491) -> 19298.4 | Q18: =(P18/P17-1)*100 -> 9.2001698 | S18: =(P18/P17) -> 1.0920017 | V18: 1371/01/25 | W18: 1439 | Z18: =R12 -> 0.026582767 | AA18: دی | AD18: 1396 | AE18: =AVERAGE(P75:P86) -> 40545.729 | AH18: 2021-04-08 | AI18: 1400-01-19 | AJ18: 244660
A19: 2002/04/06 | C19: 1381/01/17 | D19: 7924 | F19: 1390/01/17 | G19: 11200 | I19: 1395/01/17 | J19: 34700 | L19: 1400/01/17 | M19: 250500 | O19: 1391:05 | P19: =AVERAGE(G492:G522) -> 20433.2 | Q19: =(P19/P18-1)*100 -> 5.8802802 | S19: =(P19/P18) -> 1.0588028 | V19: 1371/01/26 | W19: 1439 | Z19: =R13 -> 0.050868237 | AA19: بهمن | AD19: 1397 | AE19: =AVERAGE(P87:P98) -> 104041.57 | AH19: 2021-04-10 | AI19: 1400-01-21 | AJ19: 241880
A20: 2002/04/07 | C20: 1381/01/18 | D20: 7924 | F20: 1390/01/18 | G20: 11250 | I20: 1395/01/18 | J20: 34650 | L20: 1400/01/18 | M20: 251500 | O20: 1391:06 | P20: =AVERAGE(G523:G553) -> 23020.417 | Q20: =(P20/P19-1)*100 -> 12.661828 | S20: =(P20/P19) -> 1.1266183 | V20: 1371/01/27 | W20: 1439 | Z20: =R14 -> 0.025424336 | AA20: اسفند | AD20: 1398 | AE20: =AVERAGE(P99:P110) -> 128346.11 | AH20: 2021-04-11 | AI20: 1400-01-22 | AJ20: 242850
A21: 2002/04/08 | C21: 1381/01/19 | D21: 7924 | F21: 1390/01/19 | I21: 1395/01/19 | J21: 34650 | L21: 1400/01/19 | M21: 248000 | O21: 1391:07 | P21: =AVERAGE(G554:G583) -> 31481.538 | Q21: =(P21/P20-1)*100 -> 36.754859 | S21: =(P21/P20) -> 1.3675486 | V21: 1371/01/29 | W21: 1439 | AD21: 1399 | AE21: =AVERAGE(P111:P122) -> 228057.07 | AH21: 2021-04-12 | AI21: 1400-01-23 | AJ21: 242960
A22: 2002/04/09 | C22: 1381/01/20 | D22: 7924 | F22: 1390/01/20 | G22: 11280 | I22: 1395/01/20 | J22: 34690 | L22: 1400/01/20 | O22: 1391:08 | P22: =AVERAGE(G584:G613) -> 31513.333 | Q22: =(P22/P21-1)*100 -> 0.10099529 | S22: =(P22/P21) -> 1.00101 | V22: 1371/01/30 | W22: 1439 | AD22: 1400 | AE22: =AVERAGE(P123:P134) -> 264772.57 | AH22: 2021-04-13 | AI22: 1400-01-24 | AJ22: 240900
A23: 2002/04/10 | C23: 1381/01/21 | D23: 7924 | F23: 1390/01/21 | G23: 11270 | I23: 1395/01/21 | J23: 34720 | L23: 1400/01/21 | M23: 248300 | O23: 1391:09 | P23: =AVERAGE(G614:G643) -> 29522.5 | Q23: =(P23/P22-1)*100 -> -6.3174318 | S23: =(P23/P22) -> 0.93682568 | V23: 1371/01/31 | W23: 1439 | AD23: 1401 | AE23: =AVERAGE(P135:P146) -> 355251.22 | AH23: 2021-04-14 | AI23: 1400-01-25 | AJ23: 242350
A24: 2002/04/11 | C24: 1381/01/22 | D24: 7924 | F24: 1390/01/22 | G24: 11250 | I24: 1395/01/22 | J24: 34700 | L24: 1400/01/22 | M24: 248000 | O24: 1391:10 | P24: =AVERAGE(G644:G673) -> 32675.652 | Q24: =(P24/P23-1)*100 -> 10.680505 | S24: =(P24/P23) -> 1.1068051 | V24: 1371/02/01 | W24: 1444 | AD24: 1402 | AE24: =AVERAGE(P147:P158) -> 517562.26 | AH24: 2021-04-15 | AI24: 1400-01-26 | AJ24: 239870
A25: 2002/04/12 | C25: 1381/01/23 | D25: 7924 | F25: 1390/01/23 | G25: 11250 | I25: 1395/01/23 | J25: 34690 | L25: 1400/01/23 | M25: 250000 | O25: 1391:11 | P25: =AVERAGE(G674:G703) -> 37010.4 | Q25: =(P25/P24-1)*100 -> 13.265987 | S25: =(P25/P24) -> 1.1326599 | V25: 1371/02/02 | W25: 1444 | AD25: 1403 | AH25: 2021-04-17 | AI25: 1400-01-28 | AJ25: 239930
A26: 2002/04/13 | C26: 1381/01/24 | D26: 7924 | F26: 1390/01/24 | G26: 11270 | I26: 1395/01/24 | J26: 34660 | L26: 1400/01/24 | M26: 248800 | O26: 1391:12 | P26: =AVERAGE(G704:G733) -> 35542.917 | Q26: =(P26/P25-1)*100 -> -3.9650567 | S26: =(P26/P25) -> 0.96034943 | V26: 1371/02/03 | W26: 1444 | AD26: 1404 | AH26: 2021-04-18 | AI26: 1400-01-29 | AJ26: 238820
A27: 2002/04/14 | C27: 1381/01/25 | D27: 7924 | F27: 1390/01/25 | G27: 11350 | I27: 1395/01/25 | J27: 34620 | L27: 1400/01/25 | M27: 249400 | O27: 1392:01 | P27: =AVERAGE(G734:G764) -> 35287.5 | Q27: =(P27/P26-1)*100 -> -0.71861482 | S27: =(P27/P26) -> 0.99281385 | V27: 1371/02/05 | W27: 1444 | AD27: 1405 | AH27: 2021-04-19 | AI27: 1400-01-30 | AJ27: 238170
A28: 2002/04/15 | C28: 1381/01/26 | D28: 7924 | F28: 1390/01/26 | I28: 1395/01/26 | L28: 1400/01/26 | M28: 249000 | O28: 1392:02 | P28: =AVERAGE(G765:G795) -> 35498 | Q28: =(P28/P27-1)*100 -> 0.59652852 | S28: =(P28/P27) -> 1.0059653 | V28: 1371/02/06 | W28: 1452 | AH28: 2021-04-20 | AI28: 1400-01-31 | AJ28: 233740 | AK28: =AVERAGE(AJ7:AJ28) -> 244088.1 | AL28: فروردین1400
A29: 2002/04/16 | C29: 1381/01/27 | D29: 7924 | F29: 1390/01/27 | G29: 11350 | I29: 1395/01/27 | J29: 34640 | L29: 1400/01/27 | O29: 1392:03 | P29: =AVERAGE(G796:G826) -> 35725.652 | Q29: =(P29/P28-1)*100 -> 0.64130986 | S29: =(P29/P28) -> 1.0064131 | V29: 1371/02/07 | W29: 1452 | AH29: 2021-04-21 | AI29: 1400-02-01 | AJ29: 233690
A30: 2002/04/17 | C30: 1381/01/28 | D30: 7924 | F30: 1390/01/28 | G30: 11350 | I30: 1395/01/28 | J30: 34550 | L30: 1400/01/28 | M30: 248300 | O30: 1392:04 | P30: =AVERAGE(G827:G857) -> 32782 | Q30: =(P30/P29-1)*100 -> -8.2396037 | S30: =(P30/P29) -> 0.91760396 | V30: 1371/02/09 | W30: 1452 | AH30: 2021-04-22 | AI30: 1400-02-02 | AJ30: 233300
A31: 2002/04/18 | C31: 1381/01/29 | D31: 7924 | F31: 1390/01/29 | G31: 11250 | I31: 1395/01/29 | J31: 34510 | L31: 1400/01/29 | M31: 245700 | O31: 1392:05 | P31: =AVERAGE(G858:G888) -> 31797.2 | Q31: =(P31/P30-1)*100 -> -3.0040876 | S31: =(P31/P30) -> 0.96995912 | V31: 1371/02/10 | W31: 1452 | AH31: 2021-04-24 | AI31: 1400-02-04 | AJ31: 233370
A32: 2002/04/19 | C32: 1381/01/30 | D32: 7924 | F32: 1390/01/30 | G32: 11200 | I32: 1395/01/30 | J32: 34640 | L32: 1400/01/30 | M32: 242000 | O32: 1392:06 | P32: =AVERAGE(G889:G919) -> 31872.917 | Q32: =(P32/P31-1)*100 -> 0.23812369 | S32: =(P32/P31) -> 1.0023812 | V32: 1371/02/12 | W32: 1452 | AH32: 2021-04-25 | AI32: 1400-02-05 | AJ32: 233390
A33: 2002/04/20 | C33: 1381/01/31 | D33: 7924 | F33: 1390/01/31 | G33: 11220 | I33: 1395/01/31 | J33: 34580 | L33: 1400/01/31 | M33: 239400 | O33: 1392:07 | P33: =AVERAGE(G920:G949) -> 30304 | Q33: =(P33/P32-1)*100 -> -4.9224132 | S33: =(P33/P32) -> 0.95077587 | V33: 1371/02/13 | W33: 1452 | AH33: 2021-04-26 | AI33: 1400-02-06 | AJ33: 232760
A34: 2002/04/21 | C34: 1381/02/01 | D34: 7924 | F34: 1390/02/01 | G34: 11200 | I34: 1395/02/01 | L34: 1400/02/01 | M34: 241000 | O34: 1392:08 | P34: =AVERAGE(G950:G979) -> 30128.696 | Q34: =(P34/P33-1)*100 -> -0.57848584 | S34: =(P34/P33) -> 0.99421514 | V34: 1371/02/14 | W34: 1452 | AH34: 2021-04-27 | AI34: 1400-02-07 | AJ34: 232610
A35: 2002/04/22 | C35: 1381/02/02 | D35: 7924 | F35: 1390/02/02 | I35: 1395/02/02 | L35: 1400/02/02 | M35: 239000 | O35: 1392:09 | P35: =AVERAGE(G980:G1009) -> 29520.4 | Q35: =(P35/P34-1)*100 -> -2.018991 | S35: =(P35/P34) -> 0.97981009 | V35: 1371/02/15 | W35: 1452 | AH35: 2021-04-28 | AI35: 1400-02-08 | AJ35: 232330
A36: 2002/04/23 | C36: 1381/02/03 | D36: 7924 | F36: 1390/02/03 | G36: 11200 | I36: 1395/02/03 | J36: 34590 | L36: 1400/02/03 | O36: 1392:10 | P36: =AVERAGE(G1010:G1039) -> 29740 | Q36: =(P36/P35-1)*100 -> 0.74389236 | S36: =(P36/P35) -> 1.0074389 | V36: 1371/02/16 | W36: 1452 | AH36: 2021-04-29 | AI36: 1400-02-09 | AJ36: 232310
A37: 2002/04/24 | C37: 1381/02/04 | D37: 7924 | F37: 1390/02/04 | G37: 11250 | I37: 1395/02/04 | J37: 34690 | L37: 1400/02/04 | M37: 238300 | O37: 1392:11 | P37: =AVERAGE(G1040:G1069) -> 29487.931 | Q37: =(P37/P36-1)*100 -> -0.84757554 | S37: =(P37/P36) -> 0.99152424 | V37: 1371/02/17 | W37: 1450 | AH37: 2021-05-01 | AI37: 1400-02-11 | AJ37: 229100
A38: 2002/04/25 | C38: 1381/02/05 | D38: 7924 | F38: 1390/02/05 | G38: 11270 | I38: 1395/02/05 | J38: 34670 | L38: 1400/02/05 | M38: 239000 | O38: 1392:12 | P38: =AVERAGE(G1070:G1098) -> 30196.552 | Q38: =(P38/P37-1)*100 -> 2.4030872 | S38: =(P38/P37) -> 1.0240309 | V38: 1371/02/19 | W38: 1450 | AH38: 2021-05-02 | AI38: 1400-02-12 | AJ38: 218380
A39: 2002/04/26 | C39: 1381/02/06 | D39: 7924 | F39: 1390/02/06 | G39: 11270 | I39: 1395/02/06 | J39: 34600 | L39: 1400/02/06 | M39: 236500 | O39: 1393:01 | P39: =AVERAGE(G1099:G1129) -> 30902.222 | Q39: =(P39/P38-1)*100 -> 2.3369241 | S39: =(P39/P38) -> 1.0233692 | V39: 1371/02/20 | W39: 1448 | AH39: 2021-05-03 | AI39: 1400-02-13 | AJ39: 217310
A40: 2002/04/27 | C40: 1381/02/07 | D40: 7924 | F40: 1390/02/07 | G40: 11250 | I40: 1395/02/07 | J40: 34600 | L40: 1400/02/07 | M40: 237000 | O40: 1393:02 | P40: =AVERAGE(G1130:G1160) -> 32805.714 | Q40: =(P40/P39-1)*100 -> 6.1597255 | S40: =(P40/P39) -> 1.0615973 | V40: 1371/02/21 | W40: 1445 | AH40: 2021-05-05 | AI40: 1400-02-15 | AJ40: 209450
A41: 2002/04/28 | C41: 1381/02/08 | D41: 7924 | F41: 1390/02/08 | G41: 11250 | I41: 1395/02/08 | J41: 34570 | L41: 1400/02/08 | M41: 237000 | O41: 1393:03 | P41: =AVERAGE(G1161:G1191) -> 32518 | Q41: =(P41/P40-1)*100 -> -0.87702491 | S41: =(P41/P40) -> 0.99122975 | V41: 1371/02/22 | W41: 1445 | AH41: 2021-05-06 | AI41: 1400-02-16 | AJ41: 206480
A42: 2002/04/29 | C42: 1381/02/09 | D42: 7924 | F42: 1390/02/09 | I42: 1395/02/09 | L42: 1400/02/09 | M42: 235700 | O42: 1393:04 | P42: =AVERAGE(G1192:G1222) -> 31328.667 | Q42: =(P42/P41-1)*100 -> -3.6574615 | S42: =(P42/P41) -> 0.96342538 | V42: 1371/02/23 | W42: 1445 | AH42: 2021-05-08 | AI42: 1400-02-18 | AJ42: 206370
A43: 2002/04/30 | C43: 1381/02/10 | D43: 7924 | F43: 1390/02/10 | G43: 11250 | I43: 1395/02/10 | J43: 34550 | L43: 1400/02/10 | O43: 1393:05 | P43: =AVERAGE(G1223:G1253) -> 31234 | Q43: =(P43/P42-1)*100 -> -0.30217266 | S43: =(P43/P42) -> 0.99697827 | V43: 1371/02/26 | W43: 1445 | AH43: 2021-05-09 | AI43: 1400-02-19 | AJ43: 207260
A44: 2002/05/01 | C44: 1381/02/11 | D44: 7924 | F44: 1390/02/11 | G44: 11280 | I44: 1395/02/11 | J44: 34510 | L44: 1400/02/11 | M44: 230500 | O44: 1393:06 | P44: =AVERAGE(G1254:G1284) -> 31673 | Q44: =(P44/P43-1)*100 -> 1.4055196 | S44: =(P44/P43) -> 1.0140552 | V44: 1371/02/27 | W44: 1445 | AH44: 2021-05-10 | AI44: 1400-02-20 | AJ44: 216130
A45: 2002/05/02 | C45: 1381/02/12 | D45: 7924 | F45: 1390/02/12 | G45: 11350 | I45: 1395/02/12 | J45: 34500 | L45: 1400/02/12 | M45: 220000 | O45: 1393:07 | P45: =AVERAGE(G1285:G1314) -> 32350.667 | Q45: =(P45/P44-1)*100 -> 2.1395721 | S45: =(P45/P44) -> 1.0213957 | V45: 1371/02/28 | W45: 1445 | AH45: 2021-05-11 | AI45: 1400-02-21 | AJ45: 221850
A46: 2002/05/03 | C46: 1381/02/13 | D46: 7924 | F46: 1390/02/13 | G46: 11480 | I46: 1395/02/13 | J46: 34470 | L46: 1400/02/13 | M46: 221000 | O46: 1393:08 | P46: =AVERAGE(G1315:G1344) -> 32458.929 | Q46: =(P46/P45-1)*100 -> 0.33465123 | S46: =(P46/P45) -> 1.0033465 | V46: 1371/02/29 | W46: 1445 | AH46: 2021-05-12 | AI46: 1400-02-22 | AJ46: 219750
A47: 2002/05/04 | C47: 1381/02/14 | D47: 7924 | F47: 1390/02/14 | G47: 11480 | I47: 1395/02/14 | J47: 34430 | L47: 1400/02/14 | O47: 1393:09 | P47: =AVERAGE(G1345:G1374) -> 33933.667 | Q47: =(P47/P46-1)*100 -> 4.5433973 | S47: =(P47/P46) -> 1.045434 | V47: 1371/02/30 | W47: 1445 | AH47: 2021-05-13 | AI47: 1400-02-23 | AJ47: 216130
A48: 2002/05/05 | C48: 1381/02/15 | D48: 7924 | F48: 1390/02/15 | G48: 11450 | I48: 1395/02/15 | L48: 1400/02/15 | M48: 211500 | O48: 1393:10 | P48: =AVERAGE(G1375:G1404) -> 35061 | Q48: =(P48/P47-1)*100 -> 3.3221678 | S48: =(P48/P47) -> 1.0332217 | V48: 1371/02/31 | W48: 1445 | AH48: 2021-05-15 | AI48: 1400-02-25 | AJ48: 220500
A49: 2002/05/06 | C49: 1381/02/16 | D49: 7924 | F49: 1390/02/16 | I49: 1395/02/16 | L49: 1400/02/16 | M49: 217500 | O49: 1393:11 | P49: =AVERAGE(G1405:G1434) -> 34399.2 | Q49: =(P49/P48-1)*100 -> -1.8875674 | S49: =(P49/P48) -> 0.98112433 | V49: 1371/03/02 | W49: 1445 | AH49: 2021-05-16 | AI49: 1400-02-26 | AJ49: 224140
A50: 2002/05/07 | C50: 1381/02/17 | D50: 7925 | F50: 1390/02/17 | I50: 1395/02/17 | J50: 34440 | L50: 1400/02/17 | O50: 1393:12 | P50: =AVERAGE(G1435:G1463) -> 33788.846 | Q50: =(P50/P49-1)*100 -> -1.7743257 | S50: =(P50/P49) -> 0.98225674 | V50: 1371/03/04 | W50: 1445 | AH50: 2021-05-17 | AI50: 1400-02-27 | AJ50: 222190
A51: 2002/05/08 | C51: 1381/02/18 | D51: 7925 | F51: 1390/02/18 | G51: 11450 | I51: 1395/02/18 | J51: 34460 | L51: 1400/02/18 | M51: 215000 | O51: 1394:01 | P51: =AVERAGE(G1464:G1494) -> 33208.889 | Q51: =(P51/P50-1)*100 -> -1.7164163 | S51: =(P51/P50) -> 0.98283584 | V51: 1371/03/05 | W51: 1445 | AH51: 2021-05-18 | AI51: 1400-02-28 | AJ51: 225340
A52: 2002/05/09 | C52: 1381/02/19 | D52: 7925 | F52: 1390/02/19 | G52: 11500 | I52: 1395/02/19 | J52: 34450 | L52: 1400/02/19 | M52: 216500 | O52: 1394:02 | P52: =AVERAGE(G1495:G1525) -> 33268.519 | Q52: =(P52/P51-1)*100 -> 0.17955924 | S52: =(P52/P51) -> 1.0017956 | V52: 1371/03/06 | W52: 1445 | AH52: 2021-05-19 | AI52: 1400-02-29 | AJ52: 221790
A53: 2002/05/10 | C53: 1381/02/20 | D53: 7925 | F53: 1390/02/20 | G53: 11650 | I53: 1395/02/20 | J53: 34500 | L53: 1400/02/20 | M53: 220500 | O53: 1394:03 | P53: =AVERAGE(G1526:G1556) -> 32981.25 | Q53: =(P53/P52-1)*100 -> -0.86348455 | S53: =(P53/P52) -> 0.99136515 | V53: 1371/03/07 | W53: 1439 | AH53: 2021-05-20 | AI53: 1400-02-30 | AJ53: 223000 | AK53: =AVERAGE(AJ28:AJ53) -> 223179.62 | AL53: اردیبهشت 1400
A54: 2002/05/11 | C54: 1381/02/21 | D54: 7925 | F54: 1390/02/21 | G54: 11850 | I54: 1395/02/21 | J54: 34490 | L54: 1400/02/21 | M54: 225000 | O54: 1394:04 | P54: =AVERAGE(G1557:G1587) -> 32644.783 | Q54: =(P54/P53-1)*100 -> -1.0201778 | S54: =(P54/P53) -> 0.98979822 | V54: 1371/03/09 | W54: 1439 | AH54: 2021-05-22 | AI54: 1400-03-01 | AJ54: 223490
A55: 2002/05/12 | C55: 1381/02/22 | D55: 7925 | F55: 1390/02/22 | G55: 11880 | I55: 1395/02/22 | J55: 34430 | L55: 1400/02/22 | M55: 225500 | O55: 1394:05 | P55: =AVERAGE(G1588:G1618) -> 33210.4 | Q55: =(P55/P54-1)*100 -> 1.7326425 | S55: =(P55/P54) -> 1.0173264 | V55: 1371/03/10 | W55: 1439 | AH55: 2021-05-23 | AI55: 1400-03-02 | AJ55: 223510
A56: 2002/05/13 | C56: 1381/02/23 | D56: 7925 | F56: 1390/02/23 | I56: 1395/02/23 | L56: 1400/02/23 | O56: 1394:06 | P56: =AVERAGE(G1619:G1648) -> 33814.231 | Q56: =(P56/P55-1)*100 -> 1.8181978 | S56: =(P56/P55) -> 1.018182 | V56: 1371/03/11 | W56: 1439 | AH56: 2021-05-24 | AI56: 1400-03-03 | AJ56: 224110
A57: 2002/05/14 | C57: 1381/02/24 | D57: 7925 | F57: 1390/02/24 | G57: 11900 | I57: 1395/02/24 | J57: 34400 | L57: 1400/02/24 | O57: 1394:07 | P57: =AVERAGE(G1650:G1679) -> 33928.8 | Q57: =(P57/P56-1)*100 -> 0.33881957 | S57: =(P57/P56) -> 1.0033882 | V57: 1371/03/12 | W57: 1439 | AH57: 2021-05-25 | AI57: 1400-03-04 | AJ57: 224100
A58: 2002/05/15 | C58: 1381/02/25 | D58: 7925 | F58: 1390/02/25 | G58: 11780 | I58: 1395/02/25 | J58: 34420 | L58: 1400/02/25 | M58: 228000 | O58: 1394:08 | P58: =AVERAGE(G1680:G1709) -> 33925.417 | Q58: =(P58/P57-1)*100 -> -0.0099718626 | S58: =(P58/P57) -> 0.99990028 | V58: 1371/03/13 | W58: 1439 | AH58: 2021-05-26 | AI58: 1400-03-05 | AJ58: 225160
A59: 2002/05/16 | C59: 1381/02/26 | D59: 7925 | F59: 1390/02/26 | G59: 11780 | I59: 1395/02/26 | J59: 34390 | L59: 1400/02/26 | M59: 233000 | O59: 1394:09 | P59: =AVERAGE(G1710:G1739) -> 33942.083 | Q59: =(P59/P58-1)*100 -> 0.049127375 | S59: =(P59/P58) -> 1.0004913 | V59: 1371/03/16 | W59: 1439 | AH59: 2021-05-27 | AI59: 1400-03-06 | AJ59: 226470
A60: 2002/05/17 | C60: 1381/02/27 | D60: 7925 | F60: 1390/02/27 | G60: 11780 | I60: 1395/02/27 | J60: 34370 | L60: 1400/02/27 | M60: 228500 | O60: 1394:10 | P60: =AVERAGE(G1740:G1769) -> 33870.8 | Q60: =(P60/P59-1)*100 -> -0.21001461 | S60: =(P60/P59) -> 0.99789985 | V60: 1371/03/17 | W60: 1439 | AH60: 2021-05-29 | AI60: 1400-03-08 | AJ60: 234660
A61: 2002/05/18 | C61: 1381/02/28 | D61: 7924 | F61: 1390/02/28 | G61: 11850 | I61: 1395/02/28 | L61: 1400/02/28 | M61: 231500 | O61: 1394:11 | P61: =AVERAGE(G1770:G1799) -> 33921.667 | Q61: =(P61/P60-1)*100 -> 0.15017852 | S61: =(P61/P60) -> 1.0015018 | V61: 1371/03/18 | W61: 1439 | AH61: 2021-05-30 | AI61: 1400-03-09 | AJ61: 238570
A62: 2002/05/19 | C62: 1381/02/29 | D62: 7925 | F62: 1390/02/29 | G62: 11850 | I62: 1395/02/29 | L62: 1400/02/29 | M62: 227000 | O62: 1394:12 | P62: =AVERAGE(G1800:G1828) -> 34429.565 | Q62: =(P62/P61-1)*100 -> 1.4972689 | S62: =(P62/P61) -> 1.0149727 | V62: 1371/03/19 | W62: 1439 | AH62: 2021-05-31 | AI62: 1400-03-10 | AJ62: 234060
A63: 2002/05/20 | C63: 1381/02/30 | D63: 7925 | F63: 1390/02/30 | I63: 1395/02/30 | L63: 1400/02/30 | M63: 229500 | O63: 1395:01 | P63: =AVERAGE(J3:J32) -> 34684.545 | Q63: =(P63/P62-1)*100 -> 0.74058512 | S63: =(P63/P62) -> 1.0074059 | V63: 1371/03/20 | W63: 1439 | AH63: 2021-06-01 | AI63: 1400-03-11 | AJ63: 234160
A64: 2002/05/21 | C64: 1381/02/31 | D64: 7925 | F64: 1390/02/31 | G64: 11860 | I64: 1395/02/31 | J64: 34390 | L64: 1400/02/31 | O64: 1395:02 | P64: =AVERAGE(J33:J60) -> 34505 | Q64: =(P64/P63-1)*100 -> -0.51765261 | S64: =(P64/P63) -> 0.99482347 | V64: 1371/03/21 | W64: 1439 | AH64: 2021-06-02 | AI64: 1400-03-12 | AJ64: 234240
A65: 2002/05/22 | C65: 1381/03/01 | D65: 7925 | F65: 1390/03/01 | G65: 11870 | I65: 1395/03/01 | L65: 1400/03/01 | M65: 228500 | O65: 1395:03 | P65: =AVERAGE(J64:J94) -> 34596.667 | Q65: =(P65/P64-1)*100 -> 0.26566198 | S65: =(P65/P64) -> 1.0026566 | V65: 1371/03/23 | W65: 1439 | AH65: 2021-06-03 | AI65: 1400-03-13 | AJ65: 234330
A66: 2002/05/23 | C66: 1381/03/02 | D66: 7925 | F66: 1390/03/02 | G66: 11900 | I66: 1395/03/02 | J66: 34490 | L66: 1400/03/02 | M66: 229500 | O66: 1395:04 | P66: =AVERAGE(J95:J125) -> 34974.091 | Q66: =(P66/P65-1)*100 -> 1.0909266 | S66: =(P66/P65) -> 1.0109093 | V66: 1371/03/24 | W66: 1439 | AH66: 2021-06-07 | AI66: 1400-03-17 | AJ66: 235950
A67: 2002/05/24 | C67: 1381/03/03 | D67: 7925 | F67: 1390/03/03 | G67: 12000 | I67: 1395/03/03 | J67: 34550 | L67: 1400/03/03 | M67: 231000 | O67: 1395:05 | P67: =AVERAGE(J126:J156) -> 35312.308 | Q67: =(P67/P66-1)*100 -> 0.96704953 | S67: =(P67/P66) -> 1.0096705 | V67: 1371/03/25 | W67: 1439 | AH67: 2021-06-08 | AI67: 1400-03-18 | AJ67: 235490
A68: 2002/05/25 | C68: 1381/03/04 | D68: 7925 | F68: 1390/03/04 | G68: 12100 | I68: 1395/03/04 | J68: 34540 | L68: 1400/03/04 | M68: 230000 | O68: 1395:06 | P68: =AVERAGE(J157:J187) -> 35540.417 | Q68: =(P68/P67-1)*100 -> 0.64597583 | S68: =(P68/P67) -> 1.0064598 | V68: 1371/03/26 | W68: 1439 | AH68: 2021-06-09 | AI68: 1400-03-19 | AJ68: 241440
A69: 2002/05/26 | C69: 1381/03/05 | D69: 7925 | F69: 1390/03/05 | G69: 12000 | I69: 1395/03/05 | J69: 34550 | L69: 1400/03/05 | M69: 232500 | O69: 1395:07 | P69: =AVERAGE(J188:J217) -> 35784.783 | Q69: =(P69/P68-1)*100 -> 0.68757197 | S69: =(P69/P68) -> 1.0068757 | V69: 1371/03/27 | W69: 1439 | AH69: 2021-06-10 | AI69: 1400-03-20 | AJ69: 239230
A70: 2002/05/27 | C70: 1381/03/06 | D70: 7925 | F70: 1390/03/06 | I70: 1395/03/06 | L70: 1400/03/06 | M70: 232000 | O70: 1395:08 | P70: =AVERAGE(J218:J247) -> 36309.6 | Q70: =(P70/P69-1)*100 -> 1.4665938 | S70: =(P70/P69) -> 1.0146659 | V70: 1371/03/28 | W70: 1439 | AH70: 2021-06-12 | AI70: 1400-03-22 | AJ70: 237750
A71: 2002/05/28 | C71: 1381/03/07 | D71: 7925 | F71: 1390/03/07 | G71: 11950 | I71: 1395/03/07 | J71: 34790 | L71: 1400/03/07 | O71: 1395:09 | P71: =AVERAGE(J248:J277) -> 38445.217 | Q71: =(P71/P70-1)*100 -> 5.881688 | S71: =(P71/P70) -> 1.0588169 | V71: 1371/03/31 | W71: 1439 | AH71: 2021-06-13 | AI71: 1400-03-23 | AJ71: 241030
A72: 2002/05/29 | C72: 1381/03/08 | D72: 7925 | F72: 1390/03/08 | G72: 11850 | I72: 1395/03/08 | J72: 34700 | L72: 1400/03/08 | M72: 241000 | O72: 1395:10 | P72: =AVERAGE(J278:J307) -> 39500.8 | Q72: =(P72/P71-1)*100 -> 2.7456799 | S72: =(P72/P71) -> 1.0274568 | V72: 1371/04/01 | W72: 1439 | AH72: 2021-06-14 | AI72: 1400-03-24 | AJ72: 239720
A73: 2002/05/30 | C73: 1381/03/09 | D73: 7925 | F73: 1390/03/09 | G73: 11700 | I73: 1395/03/09 | J73: 34630 | L73: 1400/03/09 | M73: 241000 | O73: 1395:11 | P73: =AVERAGE(J308:J337) -> 38319.6 | Q73: =(P73/P72-1)*100 -> -2.9903192 | S73: =(P73/P72) -> 0.97009681 | V73: 1371/04/02 | W73: 1439 | AH73: 2021-06-15 | AI73: 1400-03-25 | AJ73: 240490
A74: 2002/05/31 | C74: 1381/03/10 | D74: 7925 | F74: 1390/03/10 | G74: 11800 | I74: 1395/03/10 | J74: 34650 | L74: 1400/03/10 | M74: 239000 | O74: 1395:12 | P74: =AVERAGE(J338:J367) -> 37695.833 | Q74: =(P74/P73-1)*100 -> -1.6278006 | S74: =(P74/P73) -> 0.98372199 | V74: 1371/04/03 | W74: 1439 | AH74: 2021-06-16 | AI74: 1400-03-26 | AJ74: 241750
A75: 2002/06/01 | C75: 1381/03/11 | D75: 7925 | F75: 1390/03/11 | G75: 11750 | I75: 1395/03/11 | J75: 34650 | L75: 1400/03/11 | M75: 240500 | O75: 1396:01 | P75: =AVERAGE(J368:J398) -> 37570.87 | Q75: =(P75/P74-1)*100 -> -0.33150552 | S75: =(P75/P74) -> 0.99668494 | V75: 1371/04/04 | W75: 1439 | AH75: 2021-06-17 | AI75: 1400-03-27 | AJ75: 244290
A76: 2002/06/02 | C76: 1381/03/12 | D76: 7925 | F76: 1390/03/12 | G76: 11850 | I76: 1395/03/12 | J76: 34710 | L76: 1400/03/12 | M76: 239500 | O76: 1396:02 | P76: =AVERAGE(J399:J426) -> 37607.826 | Q76: =(P76/P75-1)*100 -> 0.098364829 | S76: =(P76/P75) -> 1.0009836 | V76: 1371/04/06 | W76: 1439 | AH76: 2021-06-19 | AI76: 1400-03-29 | AJ76: 234890
A77: 2002/06/03 | C77: 1381/03/13 | D77: 7925 | F77: 1390/03/13 | I77: 1395/03/13 | J77: 34710 | L77: 1400/03/13 | M77: 236500 | O77: 1396:03 | P77: =AVERAGE(J399:J426) -> 37607.826 | Q77: =(P77/P76-1)*100 -> 0 | S77: =(P77/P76) -> 1 | V77: 1371/05/10 | W77: 1439 | AH77: 2021-06-20 | AI77: 1400-03-30 | AJ77: 239600
A78: 2002/06/04 | C78: 1381/03/14 | D78: 7925 | F78: 1390/03/14 | I78: 1395/03/14 | J78: 34710 | L78: 1400/03/14 | O78: 1396:04 | P78: =AVERAGE(J461:J489) -> 37772.083 | Q78: =(P78/P77-1)*100 -> 0.43676347 | S78: =(P78/P77) -> 1.0043676 | V78: 1371/05/11 | W78: 1439 | AH78: 2021-06-21 | AI78: 1400-03-31 | AJ78: 240990 | AK78: =AVERAGE(AJ53:AJ78) -> 234326.15 | AL78: خرداد 1400
A79: 2002/06/05 | C79: 1381/03/15 | D79: 7925 | F79: 1390/03/15 | I79: 1395/03/15 | J79: 34670 | L79: 1400/03/15 | O79: 1396:05 | P79: =AVERAGE(J492:J522) -> 38116 | Q79: =(P79/P78-1)*100 -> 0.91050489 | S79: =(P79/P78) -> 1.009105 | V79: 1371/05/12 | W79: 1439 | AH79: 2021-06-22 | AI79: 1400-04-01 | AJ79: 242670
A80: 2002/06/06 | C80: 1381/03/16 | D80: 7925 | F80: 1390/03/16 | G80: 11800 | I80: 1395/03/16 | J80: 34530 | L80: 1400/03/16 | O80: 1396:06 | P80: =AVERAGE(J523:J553) -> 38840 | Q80: =(P80/P79-1)*100 -> 1.8994648 | S80: =(P80/P79) -> 1.0189946 | V80: 1371/05/13 | W80: 1439 | AH80: 2021-06-23 | AI80: 1400-04-02 | AJ80: 241790
A81: 2002/06/07 | C81: 1381/03/17 | D81: 7925 | F81: 1390/03/17 | G81: 11900 | I81: 1395/03/17 | J81: 34550 | L81: 1400/03/17 | M81: 241000 | O81: 1396:07 | P81: =AVERAGE(J554:J583) -> 39700 | Q81: =(P81/P80-1)*100 -> 2.2142122 | S81: =(P81/P80) -> 1.0221421 | V81: 1371/05/14 | W81: 1439 | AH81: 2021-06-24 | AI81: 1400-04-03 | AJ81: 241890
A82: 2002/06/08 | C82: 1381/03/18 | D82: 7925 | F82: 1390/03/18 | G82: 11850 | I82: 1395/03/18 | J82: 34580 | L82: 1400/03/18 | M82: 240000 | O82: 1396:08 | P82: =AVERAGE(J584:J613) -> 40715 | Q82: =(P82/P81-1)*100 -> 2.5566751 | S82: =(P82/P81) -> 1.0255668 | V82: 1371/05/15 | W82: 1439 | AH82: 2021-06-26 | AI82: 1400-04-05 | AJ82: 244540
A83: 2002/06/09 | C83: 1381/03/19 | D83: 7925 | F83: 1390/03/19 | G83: 12150 | I83: 1395/03/19 | J83: 34600 | L83: 1400/03/19 | M83: 241000 | O83: 1396:09 | P83: =AVERAGE(J614:J643) -> 41725.6 | Q83: =(P83/P82-1)*100 -> 2.4821319 | S83: =(P83/P82) -> 1.0248213 | V83: 1371/05/17 | W83: 1439 | AH83: 2021-06-27 | AI83: 1400-04-06 | AJ83: 246770
A84: 2002/06/10 | C84: 1381/03/20 | D84: 7925 | F84: 1390/03/20 | I84: 1395/03/20 | L84: 1400/03/20 | M84: 240000 | O84: 1396:10 | P84: =AVERAGE(J644:J673) -> 43350.4 | Q84: =(P84/P83-1)*100 -> 3.8940123 | S84: =(P84/P83) -> 1.0389401 | V84: 1371/05/18 | W84: 1439 | AH84: 2021-06-28 | AI84: 1400-04-07 | AJ84: 247120
A85: 2002/06/11 | C85: 1381/03/21 | D85: 7925 | F85: 1390/03/21 | G85: 12150 | I85: 1395/03/21 | J85: 34610 | L85: 1400/03/21 | O85: 1396:11 | P85: =AVERAGE(J674:J703) -> 46535 | Q85: =(P85/P84-1)*100 -> 7.3461837 | S85: =(P85/P84) -> 1.0734618 | V85: 1371/05/19 | W85: 1439 | AH85: 2021-06-29 | AI85: 1400-04-08 | AJ85: 249650
A86: 2002/06/12 | C86: 1381/03/22 | D86: 7925 | F86: 1390/03/22 | G86: 12200 | I86: 1395/03/22 | J86: 34600 | L86: 1400/03/22 | M86: 237000 | O86: 1396:12 | P86: =AVERAGE(J704:J732) -> 47008.148 | Q86: =(P86/P85-1)*100 -> 1.0167576 | S86: =(P86/P85) -> 1.0101676 | V86: 1371/05/20 | W86: 1439 | AH86: 2021-06-30 | AI86: 1400-04-09 | AJ86: 254000
A87: 2002/06/13 | C87: 1381/03/23 | D87: 7925 | F87: 1390/03/23 | G87: 12350 | I87: 1395/03/23 | J87: 34530 | L87: 1400/03/23 | M87: 240500 | O87: 1397:01 | P87: =AVERAGE(J733:J763) -> 51662.5 | Q87: =(P87/P86-1)*100 -> 9.9011598 | S87: =(P87/P86) -> 1.0990116 | V87: 1371/05/21 | W87: 1439 | AH87: 2021-07-01 | AI87: 1400-04-10 | AJ87: 251510
A88: 2002/06/14 | C88: 1381/03/24 | D88: 7925 | F88: 1390/03/24 | G88: 12500 | I88: 1395/03/24 | J88: 34590 | L88: 1400/03/24 | M88: 239500 | O88: 1397:02 | P88: =AVERAGE(J764:J794) -> 60750 | Q88: =(P88/P87-1)*100 -> 17.590128 | S88: =(P88/P87) -> 1.1759013 | V88: 1371/05/22 | W88: 1439 | AH88: 2021-07-03 | AI88: 1400-04-12 | AJ88: 252360
A89: 2002/06/15 | C89: 1381/03/25 | D89: 7925 | F89: 1390/03/25 | G89: 12150 | I89: 1395/03/25 | J89: 34600 | L89: 1400/03/25 | M89: 241000 | O89: 1397:03 | P89: =AVERAGE(J795:J825) -> 66581.613 | Q89: =(P89/P88-1)*100 -> 9.5993628 | S89: =(P89/P88) -> 1.0959936 | V89: 1371/05/24 | W89: 1439 | AH89: 2021-07-04 | AI89: 1400-04-13 | AJ89: 251510
A90: 2002/06/16 | C90: 1381/03/26 | D90: 7925 | F90: 1390/03/26 | I90: 1395/03/26 | J90: 34550 | L90: 1400/03/26 | M90: 242000 | O90: 1397:04 | P90: =AVERAGE(J826:J856) -> 80726.786 | Q90: =(P90/P89-1)*100 -> 21.244864 | S90: =(P90/P89) -> 1.2124486 | V90: 1371/05/25 | W90: 1439 | AH90: 2021-07-05 | AI90: 1400-04-14 | AJ90: 249720
A91: 2002/06/17 | C91: 1381/03/27 | D91: 7925 | F91: 1390/03/27 | I91: 1395/03/27 | L91: 1400/03/27 | M91: 244000 | O91: 1397:05 | P91: =AVERAGE(J857:J887) -> 102708.39 | Q91: =(P91/P90-1)*100 -> 27.229625 | S91: =(P91/P90) -> 1.2722963 | V91: 1371/05/26 | W91: 1439 | AH91: 2021-07-06 | AI91: 1400-04-15 | AJ91: 251090
A92: 2002/06/18 | C92: 1381/03/28 | D92: 7925 | F92: 1390/03/28 | G92: 12170 | I92: 1395/03/28 | J92: 34540 | L92: 1400/03/28 | O92: 1397:06 | P92: =AVERAGE(J888:J918) -> 126694.44 | Q92: =(P92/P91-1)*100 -> 23.353553 | S92: =(P92/P91) -> 1.2335355 | V92: 1371/05/27 | W92: 1439 | AH92: 2021-07-07 | AI92: 1400-04-16 | AJ92: 250860
A93: 2002/06/19 | C93: 1381/03/29 | D93: 7925 | F93: 1390/03/29 | G93: 12200 | I93: 1395/03/29 | J93: 34540 | L93: 1400/03/29 | M93: 239500 | O93: 1397:07 | P93: =AVERAGE(J919:J948) -> 150309.62 | Q93: =(P93/P92-1)*100 -> 18.639468 | S93: =(P93/P92) -> 1.1863947 | V93: 1371/05/28 | W93: 1439 | AH93: 2021-07-08 | AI93: 1400-04-17 | AJ93: 250190
A94: 2002/06/20 | C94: 1381/03/30 | D94: 7925 | F94: 1390/03/30 | G94: 12050 | I94: 1395/03/30 | J94: 34550 | L94: 1400/03/30 | M94: 239000 | O94: 1397:08 | P94: =AVERAGE(J949:J978) -> 139657.57 | Q94: =(P94/P93-1)*100 -> -7.086739 | S94: =(P94/P93) -> 0.92913261 | V94: 1371/05/30 | W94: 1439 | AH94: 2021-07-10 | AI94: 1400-04-19 | AJ94: 249490
A95: 2002/06/21 | C95: 1381/03/31 | D95: 7925 | F95: 1390/03/31 | G95: 11750 | I95: 1395/03/31 | J95: 34600 | L95: 1400/03/31 | M95: 240400 | O95: 1397:09 | P95: =AVERAGE(J979:J1008) -> 111819.6 | Q95: =(P95/P94-1)*100 -> -19.933016 | S95: =(P95/P94) -> 0.80066984 | V95: 1371/06/01 | W95: 1439 | AH95: 2021-07-11 | AI95: 1400-04-20 | AJ95: 249990
A96: 2002/06/22 | C96: 1381/04/01 | D96: 7925 | F96: 1390/04/01 | G96: 11800 | I96: 1395/04/01 | J96: 34630 | L96: 1400/04/01 | M96: 242500 | O96: 1397:10 | P96: =AVERAGE(J1009:J1038) -> 108512 | Q96: =(P96/P95-1)*100 -> -2.9579787 | S96: =(P96/P95) -> 0.97042021 | V96: 1371/06/02 | W96: 1439 | AH96: 2021-07-12 | AI96: 1400-04-21 | AJ96: 249690
A97: 2002/06/23 | C97: 1381/04/02 | D97: 7925 | F97: 1390/04/02 | G97: 11750 | I97: 1395/04/02 | L97: 1400/04/02 | M97: 242500 | O97: 1397:11 | P97: =AVERAGE(J1039:J1068) -> 119377.27 | Q97: =(P97/P96-1)*100 -> 10.012969 | S97: =(P97/P96) -> 1.1001297 | V97: 1371/06/03 | W97: 1439 | AH97: 2021-07-13 | AI97: 1400-04-22 | AJ97: 247590
A98: 2002/06/24 | C98: 1381/04/03 | D98: 7925 | F98: 1390/04/03 | I98: 1395/04/03 | L98: 1400/04/03 | M98: 242000 | O98: 1397:12 | P98: =AVERAGE(J1069:J1097) -> 129699.09 | Q98: =(P98/P97-1)*100 -> 8.6463846 | S98: =(P98/P97) -> 1.0864638 | V98: 1371/06/04 | W98: 1439 | AH98: 2021-07-14 | AI98: 1400-04-23 | AJ98: 246040
A99: 2002/06/25 | C99: 1381/04/04 | D99: 7925 | F99: 1390/04/04 | G99: 11700 | I99: 1395/04/04 | J99: 34610 | L99: 1400/04/04 | O99: 1398:01 | P99: =AVERAGE(J1098:J1128) -> 136870.59 | Q99: =(P99/P98-1)*100 -> 5.5293351 | S99: =(P99/P98) -> 1.0552934 | V99: 1371/06/05 | W99: 1439 | AH99: 2021-07-15 | AI99: 1400-04-24 | AJ99: 246990
A100: 2002/06/26 | C100: 1381/04/05 | D100: 7925 | F100: 1390/04/05 | G100: 11650 | I100: 1395/04/05 | J100: 34850 | L100: 1400/04/05 | M100: 246000 | O100: 1398:02 | P100: =AVERAGE(J1129:J1159) -> 145865.38 | Q100: =(P100/P99-1)*100 -> 6.5717526 | S100: =(P100/P99) -> 1.0657175 | V100: 1371/06/07 | W100: 1439 | AH100: 2021-07-17 | AI100: 1400-04-26 | AJ100: 247290
...

Sheet usa data
D1: ماهانه (1954-2010) | N1: ماهانه (2010 به بعد) | V1: سالانه
B2: observation_date | C2: Consumer Price Index for All Urban Consumers: All Items Less Food and Energy in U.S. City Average, Index 1982-1984=100, Monthly, Not Seasonally Adjusted | D2: Federal Funds Effective Rate, Percent, Monthly, Not Seasonally Adjusted | E2: M2, Billions of Dollars, Monthly,Seasonally Adjusted | F2: M2SL:M2, Percent Change from Year Ago, Monthly, Seasonally Adjusted | H2: Consumer Price Index for All Urban Consumers: All Items in U.S. City Average, Percent Change from Year Ago, Monthly, Seasonally Adjusted | K2: M2, Billions of Dollars, Monthly, Seasonally Adjusted | L2: M2SL:M2, Percent Change from Year Ago, Monthly, Seasonally Adjusted | N2: Federal Funds Effective Rate, Percent, Monthly, Not Seasonally Adjusted | O2: Consumer Price Index for All Urban Consumers: All Items Less Food and Energy in U.S. City Average, Index 1982-1984=100, Monthly, Not Seasonally Adjusted | P2: Consumer Price Index: All Items: Total for United States, Contribution to annual inflation, Annual, Not Seasonally Adjusted | S2: M2, Billions of Dollars, Annual, Seasonally Adjusted | T2: Federal Funds Effective Rate, Percent, Annual, Not Seasonally Adjusted | U2: Inflation, consumer prices for the United States, Percent, Annual, Not Seasonally Adjusted | V2: Consumer Price Index: All Items: Total for United States, Contribution to annual inflation, Annual, Not Seasonally Adjusted | W2: Consumer Price Index for All Urban Consumers: All Items Less Food and Energy in U.S. City Average, Percent Change, Annual, Not Seasonally Adjusted | X2: Gross Domestic Product, Billions of Dollars, Annual, Seasonally Adjusted Annual Rate
B3: تاریخ | C3: CPI هسته | D3: نرخ بهره فدرال رزرو | E3: نقدینگی | F3: رشد نقطه ای نقدینگی | G3: تورم هسته نقطه ای | H3: تورم نقطه ای شهری | J3: 2010 به بعد | K3: نقدینگی | L3: رشد نقطه ای نقدینگی | M3: تورم نقطه ای شهری | N3: نرخ بهره فدرال رزرو | O3: تورم هسته نقطه ای | P3: تورم 12 ماهه منتهی به هر ماه | R3: سال | S3: نقدینگی | T3: نرخ بهره فدرال رزرو | U3: تورم | V3: تورم کل | W3: تورم هسته | X3: GDP
B4: 19906 | D4: 0.8 | H4: 0.26129 | J4: 40179 | K4: 8458.1 | L4: 2.22875 | M4: 2.62111 | N4: 0.11 | O4: =(C670/C658-1)*100 -> 1.5536247 | P4: -0.16061698 | R4: 1955 | T4: 1.79 | X4: 425.4795
B5: 19937 | D5: 1.22 | H5: 0 | J5: 40210 | K5: 8507.4 | L5: 2.46053 | M5: 2.15134 | N5: 0.13 | O5: =(C671/C659-1)*100 -> 1.3400096 | P5: -0.1203986 | R5: 1956 | T5: 2.73 | X5: 449.3525
B6: 19968 | D6: 1.07 | H6: -0.29751 | J6: 40238 | K6: 8504.5 | L6: 1.61543 | M6: 2.28617 | N6: 0.16 | O6: =(C672/C660-1)*100 -> 1.1068474 | P6: -0.054216345 | R6: 1957 | T6: 3.11 | X6: 474.0395
B7: 19998 | D7: 0.85 | H7: -0.85343 | J7: 40269 | K7: 8535.2 | L7: 1.9384 | M7: 2.20677 | N7: 0.2 | O7: =(C673/C661-1)*100 -> 0.92314151 | P7: -0.0010689561 | R7: 1958 | T7: 1.57 | W7: 2.27535 | X7: 481.2285
B8: 20029 | D8: 0.83 | H8: -0.26071 | J8: 40299 | K8: 8589.9 | L8: 1.88834 | M8: 2.00355 | N8: 0.2 | O8: =(C674/C662-1)*100 -> 0.94237158 | P8: 0.026481894 | R8: 1959 | S8: 293.3 | T8: 3.31 | W8: 1.99944 | X8: 521.65425
B9: 20059 | D9: 1.28 | H9: -0.37216 | J9: 40330 | K9: 8609 | L9: 1.99633 | M9: 1.12156 | N9: 0.18 | O9: =(C675/C663-1)*100 -> 0.90385484 | P9: 0.02003782 | R9: 1960 | S9: 304.28333 | T9: 3.21 | U9: 1.457976 | W9: 1.5185 | X9: 542.38225 | AE9: inflation
B10: 20090 | D10: 1.39 | H10: -0.63103 | J10: 40360 | K10: 8618.8 | L10: 2.05681 | M10: 1.34078 | N10: 0.18 | O10: =(C676/C664-1)*100 -> 0.86984272 | P10: 0.052954793 | R10: 1961 | S10: 324.83333 | T10: 1.95 | U10: 1.0707241 | W10: 1.11504 | X10: 562.20975
B11: 20121 | D11: 1.29 | H11: -0.62986 | J11: 40391 | K11: 8669.1 | L11: 2.65364 | M11: 1.15018 | N11: 0.19 | O11: =(C677/C665-1)*100 -> 0.89027123 | P11: 0.060824265 | R11: 1962 | S11: 350.1 | T11: 2.71 | U11: 1.1987733 | W11: 1.37171 | X11: 603.9215 | AB11: =AVERAGE(P124:P135) -> 1.1989342 | AC11: 2020 | AE11: Year | AF11: Jan | AG11: Feb | AH11: Mar | AI11: Apr | AJ11: May | AK11: Jun | AL11: Jul | AM11: Aug | AN11: Sep | AO11: Oct | AP11: Nov | AQ11: Dec | AR11: Annual
B12: 20149 | D12: 1.35 | H12: -0.51987 | J12: 40422 | K12: 8700.1 | L12: 3.03048 | M12: 1.11831 | N12: 0.19 | O12: =(C678/C666-1)*100 -> 0.80404475 | P12: 0.10723795 | R12: 1963 | S12: 379.60833 | T12: 3.18 | U12: 1.2396694 | W12: 1.24702 | X12: 637.4515 | AB12: =AVERAGE(P136:P147) -> 4.6296959 | AC12: 2021 | AE12: 2022 | AF12: 0.0748 | AG12: 0.07871 | AH12: 0.08542 | AI12: 0.08259 | AJ12: 0.08582 | AK12: 0.0906 | AL12: 0.08525 | AM12: 0.08263 | AN12: 0.08202 | AO12: 0.07745 | AP12: 0.0711 | AQ12: 0.07 | AS12: =AVERAGE(AF12:AQ12) -> 0.0805325
B13: 20180 | D13: 1.43 | H13: -0.26061 | J13: 40452 | K13: 8749.4 | L13: 3.28529 | M13: 1.1667 | N13: 0.19 | O13: =(C679/C667-1)*100 -> 0.61069809 | P13: 0.11304007 | R13: 1964 | S13: 409.31667 | T13: 3.5 | U13: 1.2789116 | W13: 1.49371 | X13: 684.4615 | AB13: =AVERAGE(P148:P159) -> 7.9720367 | AC13: 2022 | AE13: 2021 | AF13: 0.014 | AG13: 0.01676 | AH13: 0.0262 | AI13: 0.0416 | AJ13: 0.04993 | AK13: 0.05391 | AL13: 0.05365 | AM13: 0.05251 | AN13: 0.0539 | AO13: 0.06222 | AP13: 0.06809 | AQ13: 0.07036 | AR13: 0.04698 | AS13: =AVERAGE(AF13:AQ13) -> 0.0469275
B14: 20210 | D14: 1.43 | H14: -0.59413 | J14: 40483 | K14: 8770 | L14: 3.16676 | M14: 1.08454 | N14: 0.19 | O14: =(C680/C668-1)*100 -> 0.76820459 | P14: 0.13571552 | R14: 1965 | S14: 442.45 | T14: 4.08 | U14: 1.5851693 | W14: 1.44591 | X14: 742.29025 | AB14: =AVERAGE(P160:P171) -> 4.3816171 | AC14: 2023 | AE14: 2020 | AF14: 0.02487 | AG14: 0.02335 | AH14: 0.01539 | AI14: 0.00329 | AJ14: 0.00118 | AK14: 0.00646 | AL14: 0.00986 | AM14: 0.0131 | AN14: 0.01371 | AO14: 0.01182 | AP14: 0.01175 | AQ14: 0.01362 | AR14: 0.01234 | AS14: =AVERAGE(AF14:AQ14) -> 0.012366667
B15: 20241 | D15: 1.64 | H15: -0.85375 | J15: 40513 | K15: 8801.8 | L15: 3.59934 | M15: 1.43779 | N15: 0.18 | O15: =(C681/C669-1)*100 -> 0.80445404 | P15: 0.13148809 | R15: 1966 | S15: 471.375 | T15: 5.11 | U15: 3.0150754 | W15: 2.44337 | X15: 813.41375 | AC15: 2024 | AE15: 2019 | AF15: 0.01551 | AG15: 0.0152 | AH15: 0.01863 | AI15: 0.01996 | AJ15: 0.0179 | AK15: 0.01648 | AL15: 0.01811 | AM15: 0.0175 | AN15: 0.01711 | AO15: 0.01764 | AP15: 0.02051 | AQ15: 0.02285 | AR15: 0.01812 | AS15: =AVERAGE(AF15:AQ15) -> 0.018116667
B16: 20271 | D16: 1.68 | H16: -0.3723 | J16: 40544 | K16: 8823.1 | L16: 4.31539 | M16: 1.70078 | N16: 0.17 | O16: =(C682/C670-1)*100 -> 0.95008315 | P16: 0.16813418 | R16: 1967 | S16: 503.64167 | T16: 4.22 | U16: 2.7727856 | W16: 3.47826 | X16: 859.95625 | AC16: 2025 | AE16: 2018 | AF16: 0.02071 | AG16: 0.02212 | AH16: 0.0236 | AI16: 0.02463 | AJ16: 0.02801 | AK16: 0.02872 | AL16: 0.0295 | AM16: 0.02699 | AN16: 0.02277 | AO16: 0.02522 | AP16: 0.02177 | AQ16: 0.0191 | AR16: 0.02443
B17: 20302 | D17: 1.96 | H17: -0.48417 | J17: 40575 | K17: 8886.9 | L17: 4.46082 | M17: 2.1249 | N17: 0.16 | O17: =(C683/C671-1)*100 -> 1.0920119 | P17: 0.22316839 | R17: 1968 | S17: 545.3 | T17: 5.66 | U17: 4.2717962 | W17: 4.63385 | X17: 940.6465
B18: 20333 | D18: 2.18 | H18: 0.1492 | J18: 40603 | K18: 8943.5 | L18: 5.16197 | M18: 2.61924 | N18: 0.14 | O18: =(C684/C672-1)*100 -> 1.19018 | P18: 0.28340552 | R18: 1969 | S18: 578.725 | T18: 8.21 | U18: 5.4623862 | W18: 5.80542 | X18: 1017.615
B19: 20363 | D19: 2.24 | H19: 0.37425 | J19: 40634 | K19: 9004.9 | L19: 5.50309 | M19: 3.07723 | N19: 0.1 | O19: =(C685/C673-1)*100 -> 1.334744 | P19: 0.30788776 | R19: 1970 | S19: 601.45833 | T19: 7.17 | U19: 5.8382553 | W19: 6.24593 | X19: 1073.3105
B20: 20394 | D20: 2.35 | H20: 0.37341 | J20: 40664 | K20: 9075.5 | L20: 5.65315 | M20: 3.45897 | N20: 0.09 | O20: =(C686/C674-1)*100 -> 1.5104456 | P20: 0.34629125 | R20: 1971 | S20: 674.4 | T20: 4.67 | U20: 4.2927667 | W20: 4.69484 | X20: 1164.8498
B21: 20424 | D21: 2.48 | H21: 0.37355 | J21: 40695 | K21: 9151 | L21: 6.29574 | M21: 3.50232 | N21: 0.09 | O21: =(C687/C675-1)*100 -> 1.638759 | P21: 0.37068962 | R21: 1972 | S21: 758.15833 | T21: 4.44 | U21: 3.2722782 | W21: 3.06103 | X21: 1279.112
B22: 20455 | D22: 2.45 | H22: 0.22413 | J22: 40725 | K22: 9316.6 | L22: 8.09625 | M22: 3.57988 | N22: 0.07 | O22: =(C688/C676-1)*100 -> 1.7653599 | P22: 0.42163786 | R22: 1973 | S22: 831.75833 | T22: 8.74 | U22: 6.1777601 | W22: 3.48089 | X22: 1425.376
B23: 20486 | D23: 2.5 | H23: 0.14914 | J23: 40756 | K23: 9507.6 | L23: 9.67228 | M23: 3.755 | N23: 0.1 | O23: =(C689/C677-1)*100 -> 1.9512437 | P23: 0.46944825 | R23: 1974 | S23: 880.55833 | T23: 10.51 | U23: 11.054805 | W23: 8.24497 | X23: 1545.2425
B24: 20515 | D24: 2.5 | H24: 0.37327 | J24: 40787 | K24: 9528.3 | L24: 9.51943 | M24: 3.81262 | N24: 0.08 | O24: =(C690/C678-1)*100 -> 1.9747011 | P24: 0.49111273 | R24: 1975 | S24: 963.5 | T24: 5.82 | U24: 9.1431469 | W24: 9.22142 | X24: 1684.905
B25: 20546 | D25: 2.62 | H25: 0.52258 | J25: 40817 | K25: 9562.1 | L25: 9.28864 | M25: 3.52227 | N25: 0.07 | O25: =(C691/C679-1)*100 -> 2.1001535 | P25: 0.48762409 | R25: 1976 | S25: 1086.5333 | T25: 5.05 | U25: 5.7448126 | W25: 6.57183 | X25: 1873.4125
B26: 20576 | D26: 2.75 | H26: 0.97124 | J26: 40848 | K26: 9612.6 | L26: 9.60775 | M26: 3.45143 | N26: 0.08 | O26: =(C692/C680-1)*100 -> 2.1533072 | P26: 0.46372667 | R26: 1977 | S26: 1221.1917 | T26: 5.54 | U26: 6.501684 | W26: 6.25363 | X26: 2081.825
B27: 20607 | D27: 2.71 | H27: 1.64732 | J27: 40878 | K27: 9660.1 | L27: 9.75141 | M27: 3.06207 | N27: 0.07 | O27: =(C693/C681-1)*100 -> 2.2295363 | P27: 2.9873106 | R27: 1978 | S27: 1322.2333 | T27: 7.94 | U27: 7.6309638 | W27: 7.30575 | X27: 2351.5988
B28: 20637 | D28: 2.75 | H28: 1.98057 | J28: 40909 | K28: 9733.3 | L28: 10.3161 | M28: 3.00877 | N28: 0.08 | O28: =(C694/C682-1)*100 -> 2.2774635 | P28: 2.9019547 | R28: 1979 | S28: 1425.6667 | T28: 11.2 | U28: 11.254471 | W28: 9.7353 | X28: 2627.3263
... B33: 20790 | D33: 2.94 | H33: 2.82843 | J33: 41061 | K33: 9999.3 | L33: 9.27003 | M33: 1.65387 | N33: 0.16 | O33: =(C699/C687-1)*100 -> 2.2179634 | P33: 1.3614932 | R33: 1984 | S33: 2218.9583 | T33: 10.23 | U33: 4.3005355 | W33: 4.94395 | X33: 4037.614
B34: 20821 | C34: 28.5 | D34: 2.84 | H34: 3.13082 | J34: 41091 | K34: 10051.8 | L34: 7.89129 | M34: 1.41751 | N34: 0.16 | O34: =(C700/C688-1)*100 -> 2.1002469 | P34: 1.0071544 | R34: 1985 | S34: 2416.5 | T34: 8.1 | U34: 3.5456442 | W34: 4.37625 | X34: 4338.9805
B35: 20852 | C35: 28.5 | D35: 3 | H35: 3.49963 | J35: 41122 | K35: 10121.3 | L35: 6.45484 | M35: 1.68593 | N35: 0.13 | O35: =(C701/C689-1)*100 -> 1.9134562 | P35: 1.3861234 | R35: 1986 | S35: 2612.775 | T35: 6.8 | U35: 1.8980477 | W35: 4.04002 | X35: 4579.6325
B36: 20880 | C36: 28.7 | D36: 2.96 | H36: 3.60729 | J36: 41153 | K36: 10200.8 | L36: 7.05792 | M36: 1.94972 | N36: 0.14 | O36: =(C702/C690-1)*100 -> 1.9846303 | P36: 1.7974025 | R36: 1987 | S36: 2782.2583 | T36: 6.66 | U36: 3.6645632 | W36: 4.11804 | X36: 4855.2163
B37: 20911 | C37: 28.8 | D37: 3 | H37: 3.71333 | J37: 41183 | K37: 10267.3 | L37: 7.37495 | M37: 2.15568 | N37: 0.16 | O37: =(C703/C691-1)*100 -> 1.9991797 | P37: 2.0674953 | R37: 1988 | S37: 2931.1167 | T37: 7.57 | U37: 4.0777411 | W37: 4.41342 | X37: 5236.438
B38: 20941 | C38: 28.8 | D38: 3 | H38: 3.58861 | J38: 41214 | K38: 10337.6 | L38: 7.54218 | M38: 1.79602 | N38: 0.16 | O38: =(C704/C692-1)*100 -> 1.9412939 | P38: 1.7321404 | R38: 1989 | S38: 3054.025 | T38: 9.21 | U38: 4.827003 | W38: 4.50371 | X38: 5641.5795
B39: 20972 | C39: 28.9 | D39: 3 | H39: 3.53591 | J39: 41244 | K39: 10459.7 | L39: 8.27735 | M39: 1.7595 | N39: 0.16 | O39: =(C705/C693-1)*100 -> 1.893358 | P39: 1.7224162 | R39: 1990 | S39: 3222.2333 | T39: 8.1 | U39: 5.3979564 | W39: 5.02681 | X39: 5963.1445
B40: 21002 | C40: 28.9 | D40: 2.99 | H40: 3.29791 | J40: 41275 | K40: 10482.9 | L40: 7.7014 | M40: 1.68406 | N40: 0.14 | O40: =(C706/C694-1)*100 -> 1.9253027 | P40: 1.5612648 | R40: 1991 | S40: 3342.1 | T40: 5.69 | U40: 4.234964 | W40: 4.90926 | X40: 6158.1292
B41: 21033 | C41: 29 | D41: 3.24 | H41: 3.55181 | J41: 41306 | K41: 10501.3 | L41: 7.31271 | M41: 2.01814 | N41: 0.15 | O41: =(C707/C695-1)*100 -> 2.0042569 | P41: 1.9470694 | R41: 1992 | S41: 3404.5667 | T41: 3.52 | U41: 3.0288197 | W41: 3.65918 | X41: 6520.3273
B42: 21064 | C42: 29.1 | D42: 3.47 | H42: 3.54662 | J42: 41334 | K42: 10558.3 | L42: 7.4024 | M42: 1.51875 | N42: 0.14 | O42: =(C708/C696-1)*100 -> 1.8873369 | P42: 1.3999114 | R42: 1993 | S42: 3439.7583 | T42: 3.02 | U42: 2.951657 | W42: 3.30373 | X42: 6858.5585
B43: 21094 | C43: 29.2 | D43: 3.5 | H43: 2.94438 | J43: 41365 | K43: 10586.3 | L43: 7.09892 | M43: 1.13881 | N43: 0.15 | O43: =(C709/C697-1)*100 -> 1.7151978 | P43: 0.97425265 | R43: 1994 | S43: 3483.35 | T43: 4.21 | U43: 2.6074416 | W43: 2.85307 | X43: 7287.2365
B44: 21125 | C44: 29.4 | D44: 3.28 | H44: 3.27154 | J44: 41395 | K44: 10621 | L44: 6.97595 | M44: 1.39039 | N44: 0.11 | O44: =(C710/C698-1)*100 -> 1.68117 | P44: 1.2787711 | R44: 1995 | S44: 3555.5833 | T44: 5.83 | U44: 2.8054197 | W44: 2.99223 | X44: 7639.7492
B45: 21155 | C45: 29.4 | D45: 2.98 | H45: 3.04017 | J45: 41426 | K45: 10678.7 | L45: 6.79448 | M45: 1.71579 | N45: 0.09 | O45: =(C711/C699-1)*100 -> 1.6360781 | P45: 1.7112485 | R45: 1996 | S45: 3728.95 | T45: 5.3 | U45: 2.9312042 | W45: 2.70368 | X45: 8073.1218
B46: 21186 | C46: 29.4 | D46: 2.72 | G46: =(C46/C34-1)*100 -> 3.1578947 | H46: 3.5056 | J46: 41456 | K46: 10718.4 | L46: 6.63165 | M46: 1.88547 | N46: 0.09 | O46: =(C712/C700-1)*100 -> 1.6960064 | P46: 1.9376391 | R46: 1997 | S46: 3925.725 | T46: 5.46 | U46: 2.3376899 | W46: 2.38587 | X46: 8577.5525
B47: 21217 | C47: 29.4 | D47: 1.67 | G47: =(C47/C35-1)*100 -> 3.1578947 | H47: 3.23741 | J47: 41487 | K47: 10776.6 | L47: 6.47446 | M47: 1.53881 | N47: 0.08 | O47: =(C713/C701-1)*100 -> 1.7645832 | P47: 1.4749662 | R47: 1998 | S47: 4206.4583 | T47: 5.35 | U47: 1.5522791 | W47: 2.28602 | X47: 9062.8167
B48: 21245 | C48: 29.5 | D48: 1.2 | G48: =(C48/C36-1)*100 -> 2.7874564 | H48: 3.62527 | J48: 41518 | K48: 10837.2 | L48: 6.23873 | M48: 1.09473 | N48: 0.08 | O48: =(C714/C702-1)*100 -> 1.7341191 | P48: 1.1171461 | R48: 1999 | S48: 4517.2583 | T48: 4.97 | U48: 2.1880272 | W48: 2.07632 | X48: 9631.1717
B49: 21276 | C49: 29.5 | D49: 1.26 | G49: =(C49/C37-1)*100 -> 2.4305556 | H49: 3.61618 | J49: 41548 | K49: 10961.6 | L49: 6.76225 | M49: 0.8768 | N49: 0.09 | O49: =(C715/C703-1)*100 -> 1.6802435 | P49: 0.90433308 | R49: 2000 | S49: 4790.1833 | T49: 6.24 | U49: 3.3768573 | W49: 2.43432 | X49: 10250.952
B50: 21306 | C50: 29.5 | D50: 0.63 | G50: =(C50/C38-1)*100 -> 2.4305556 | H50: 3.35714 | J50: 41579 | K50: 10969.7 | L50: 6.11457 | M50: 1.23287 | N50: 0.08 | O50: =(C716/C704-1)*100 -> 1.7209843 | P50: 1.2066733 | R50: 2001 | S50: 5203.7417 | T50: 3.88 | U50: 2.8261711 | W50: 2.67065 | X50: 10581.929
B51: 21337 | C51: 29.5 | D51: 0.93 | G51: =(C51/C39-1)*100 -> 2.0761246 | H51: 2.84596 | J51: 41609 | K51: 11035 | L51: 5.50016 | M51: 1.51284 | N51: 0.09 | O51: =(C717/C705-1)*100 -> 1.7170707 | P51: 1.5007052 | R51: 2002 | S51: 5591.3167 | T51: 1.67 | U51: 1.5860316 | W51: 2.31913 | X51: 10929.108
B52: 21367 | C52: 29.6 | D52: 0.68 | G52: =(C52/C40-1)*100 -> 2.4221453 | H52: 2.48315 | J52: 41640 | K52: 11080.8 | L52: 5.70357 | M52: 1.55776 | N52: 0.07 | O52: =(C718/C706-1)*100 -> 1.6212459 | P52: 1.5790492 | R52: 2003 | S52: 5981.425 | T52: 1.13 | U52: 2.270095 | W52: 1.45708 | X52: 11456.45
B53: 21398 | C53: 29.6 | D53: 1.53 | G53: =(C53/C41-1)*100 -> 2.0689655 | H53: 2.3338 | J53: 41671 | K53: 11178.8 | L53: 6.45158 | M53: 1.12047 | N53: 0.07 | O53: =(C719/C707-1)*100 -> 1.5673401 | P53: 1.10457 | R53: 2004 | S53: 6266.775 | T53: 1.35 | U53: 2.6772367 | W53: 1.75961 | X53: 12217.196
B54: 21429 | C54: 29.6 | D54: 1.76 | G54: =(C54/C42-1)*100 -> 1.7182131 | H54: 2.08333 | J54: 41699 | K54: 11208.1 | L54: 6.1544 | M54: 1.61269 | N54: 0.08 | O54: =(C720/C708-1)*100 -> 1.6567118 | P54: 1.4982152 | R54: 2005 | S54: 6535.1333 | T54: 3.22 | U54: 3.3927468 | W54: 2.16995 | X54: 13039.197
B55: 21459 | C55: 29.7 | D55: 1.8 | G55: =(C55/C43-1)*100 -> 1.7123288 | H55: 2.08333 | J55: 41730 | K55: 11257.7 | L55: 6.34216 | M55: 2.01513 | N55: 0.09 | O55: =(C721/C709-1)*100 -> 1.8320499 | P55: 1.9539302 | R55: 2006 | S55: 6877.3833 | T55: 4.97 | U55: 3.2259441 | W55: 2.50135 | X55: 13815.583
B56: 21490 | C56: 29.9 | D56: 2.27 | G56: =(C56/C44-1)*100 -> 1.7006803 | H56: 1.90074 | J56: 41760 | K56: 11321 | L56: 6.59072 | M56: 2.16695 | N56: 0.09 | O56: =(C722/C710-1)*100 -> 1.956207 | P56: 2.1400564 | R56: 2007 | S56: 7298.1 | T56: 5.02 | U56: 2.8526725 | W56: 2.33707 | X56: 14474.227
B57: 21520 | C57: 29.9 | D57: 2.42 | G57: =(C57/C45-1)*100 -> 1.7006803 | H57: 1.75623 | J57: 41791 | K57: 11374.9 | L57: 6.51952 | M57: 2.05898 | N57: 0.1 | O57: =(C723/C711-1)*100 -> 1.9333162 | P57: 2.0885765 | R57: 2008 | S57: 7790.825 | T57: 1.92 | U57: 3.8391003 | W57: 2.29793 | X57: 14769.862
B58: 21551 | C58: 29.9 | D58: 2.48 | E58: 286.6 | F58: 0 | G58: =(C58/C46-1)*100 -> 1.7006803 | H58: 1.2919 | J58: 41821 | K58: 11429.9 | L58: 6.63812 | M58: 1.97424 | N58: 0.09 | O58: =(C724/C712-1)*100 -> 1.8589173 | P58: 2.0125924 | R58: 2009 | S58: 8416.0333 | T58: 0.16 | U58: -0.35554627 | W58: 1.69944 | X58: 14478.067
B59: 21582 | C59: 29.9 | D59: 2.43 | E59: 287.7 | F59: 0 | G59: =(C59/C47-1)*100 -> 1.7006803 | H59: 1.0453 | J59: 41852 | K59: 11458.9 | L59: 6.33131 | M59: 1.7151 | N59: 0.09 | O59: =(C725/C713-1)*100 -> 1.7237405 | P59: 1.7234322 | R59: 2010 | S59: 8626.1083 | T59: 0.18 | U59: 1.6400434 | V59: 0.025956627 | W59: 0.95856 | X59: 15048.971
B60: 21610 | C60: 30 | D60: 2.8 | E60: 289.2 | F60: 0 | G60: =(C60/C48-1)*100 -> 1.6949153 | H60: 0.34638 | J60: 41883 | K60: 11499.8 | L60: 6.11413 | M60: 1.68405 | N60: 0.09 | O60: =(C726/C714-1)*100 -> 1.7288378 | P60: 1.6771341 | R60: 2011 | S60: 9256.0167 | T60: 0.1 | U60: 3.1568416 | V60: 0.58503641 | W60: 1.65856 | X60: 15599.731
B61: 21641 | C61: 30 | D61: 2.96 | E61: 290.1 | F61: 0 | G61: =(C61/C49-1)*100 -> 1.6949153 | H61: 0.13822 | J61: 41913 | K61: 11566 | L61: 5.51379 | M61: 1.60954 | N61: 0.09 | O61: =(C727/C715-1)*100 -> 1.80769 | P61: 1.6826962 | R61: 2012 | S61: 10050.033 | T61: 0.14 | U61: 2.0693373 | V61: 1.9170027 | W61: 2.11 | X61: 16253.97
B62: 21671 | C62: 30.1 | D62: 2.9 | E62: 292.2 | F62: 0 | G62: =(C62/C50-1)*100 -> 2.0338983 | H62: 0.34554 | J62: 41944 | K62: 11604.8 | L62: 5.78958 | M62: 1.23152 | N62: 0.09 | O62: =(C728/C716-1)*100 -> 1.7024949 | P62: 1.3365907 | R62: 2013 | S62: 10727.25 | T62: 0.11 | U62: 1.4648327 | V62: 1.4178317 | W62: 1.76307 | X62: 16880.683
B63: 21702 | C63: 30.1 | D63: 3.39 | E63: 294.1 | F63: 0 | G63: =(C63/C51-1)*100 -> 2.0338983 | H63: 0.6918 | J63: 41974 | K63: 11684.9 | L63: 5.88944 | M63: 0.65312 | N63: 0.12 | O63: =(C729/C717-1)*100 -> 1.606383 | P63: 0.75500856 | R63: 2014 | S63: 11388.8 | T63: 0.09 | U63: 1.622223 | V63: 1.629321 | W63: 1.74967 | X63: 17608.138
B64: 21732 | C64: 30.2 | D64: 3.47 | E64: 295.2 | F64: 0 | G64: =(C64/C52-1)*100 -> 2.027027 | H64: 0.89997 | J64: 42005 | K64: 11745.6 | L64: 5.99957 | M64: -0.22993 | N64: 0.11 | O64: =(C730/C718-1)*100 -> 1.6489142 | P64: -0.15882669 | R64: 2015 | S64: 12045.1 | T64: 0.13 | U64: 0.11862714 | V64: 0.076751893 | W64: 1.82842 | X64: 18295.019
B65: 21763 | C65: 30.2 | D65: 3.5 | E65: 296.4 | F65: 0 | G65: =(C65/C53-1)*100 -> 2.027027 | H65: 0.8293 | J65: 42036 | K65: 11879 | L65: 6.26364 | M65: -0.08703 | N65: 0.11 | O65: =(C731/C719-1)*100 -> 1.6977655 | P65: -0.079117326 | R65: 2016 | S65: 12860.058 | T65: 0.39 | U65: 1.2615832 | V65: 1.192293 | W65: 2.2109 | X65: 18804.913
B66: 21794 | C66: 30.3 | D66: 3.76 | E66: 296.7 | F66: 0 | G66: =(C66/C54-1)*100 -> 2.3648649 | H66: 1.17606 | J66: 42064 | K66: 11886.8 | L66: 6.05544 | M66: -0.02203 | N66: 0.11 | O66: =(C732/C720-1)*100 -> 1.7533863 | P66: -0.10092602 | R66: 2017 | S66: 13590.792 | T66: 1 | U66: 2.13011 | V66: 2.1175215 | W66: 1.84449 | X66: 19612.103
B67: 21824 | C67: 30.5 | D67: 3.98 | E67: 296.5 | F67: 0 | G67: =(C67/C55-1)*100 -> 2.6936027 | H67: 1.52196 | J67: 42095 | K67: 11928.9 | L67: 5.96214 | M67: -0.10403 | N67: 0.12 | O67: =(C733/C721-1)*100 -> 1.8075105 | P67: -0.22685099 | R67: 2018 | S67: 14103.933 | T67: 1.83 | U67: 2.4425833 | V67: 2.405147 | W67: 2.13973 | X67: 20656.516
B68: 21855 | C68: 30.5 | D68: 4 | E68: 297.1 | F68: 0 | G68: =(C68/C56-1)*100 -> 2.006689 | H68: 1.38169 | J68: 42125 | K68: 11957.9 | L68: 5.62583 | M68: 0.03503 | N68: 0.12 | O68: =(C734/C722-1)*100 -> 1.718278 | P68: -0.03127274 | R68: 2019 | S68: 14818.225 | T68: 2.16 | U68: 1.8122101 | V68: 1.885336 | W68: 2.19197 | X68: 21521.395
B69: 21885 | C69: 30.5 | D69: 3.99 | E69: 297.8 | F69: 0 | G69: =(C69/C57-1)*100 -> 2.006689 | H69: 1.51881 | J69: 42156 | K69: 12001.7 | L69: 5.51038 | M69: 0.17957 | N69: 0.13 | O69: =(C735/C723-1)*100 -> 1.7622829 | P69: 0.13588068 | R69: 2020 | S69: 17650.65 | T69: 0.37 | U69: 1.2335844 | V69: 1.1989342 | W69: 1.70282 | X69: 21322.949
B70: 21916 | C70: 30.5 | D70: 3.99 | E70: 298.2 | F70: 4.04745 | G70: =(C70/C58-1)*100 -> 2.006689 | H70: 1.24095 | J70: 42186 | K70: 12051.3 | L70: 5.43662 | M70: 0.22569 | N70: 0.13 | O70: =(C736/C724-1)*100 -> 1.8048359 | P70: 0.1772963 | R70: 2021 | S70: 20525.85 | T70: 0.08 | U70: 4.6978589 | V70: 4.6296959 | W70: 3.57204 | X70: 23594.031
B71: 21947 | C71: 30.6 | D71: 3.97 | E71: 298.4 | F71: 3.71915 | G71: =(C71/C59-1)*100 -> 2.3411371 | H71: 1.41379 | J71: 42217 | K71: 12101.9 | L71: 5.61136 | M71: 0.2413 | N71: 0.14 | O71: =(C737/C725-1)*100 -> 1.827559 | P71: 0.17262369 | R71: 2022 | S71: 21576.575 | T71: 1.69 | U71: 8.0027998 | V71: 7.9720367 | W71: 6.15039 | X71: 25744.108
B72: 21976 | C72: 30.6 | D72: 3.84 | E72: 299.3 | F72: 3.49239 | G72: =(C72/C60-1)*100 -> 2 | H72: 1.51881 | J72: 42248 | K72: 12160.8 | L72: 5.74793 | M72: 0.00884 | N72: 0.14 | O72: =(C738/C726-1)*100 -> 1.891635 | P72: -0.10788843 | R72: 2023
B73: 22007 | C73: 30.6 | D73: 3.92 | E73: 300.1 | F73: 3.44709 | G73: =(C73/C61-1)*100 -> 2 | H73: 1.93237 | J73: 42278 | K73: 12195.9 | L73: 5.44614 | M73: 0.12762 | N73: 0.12 | O73: =(C739/C727-1)*100 -> 1.9096707 | P73: 0.09047221 | R73: 2024
B74: 22037 | C74: 30.6 | D74: 3.85 | E74: 300.9 | F74: 2.97741 | G74: =(C74/C62-1)*100 -> 1.6611296 | H74: 1.82507 | J74: 42309 | K74: 12284.6 | L74: 5.85792 | M74: 0.43632 | N74: 0.12 | O74: =(C740/C728-1)*100 -> 2.0175717 | P74: 0.41665529 | R74: 2025
B75: 22068 | C75: 30.6 | D75: 3.32 | E75: 302.3 | F75: 2.78817 | G75: =(C75/C63-1)*100 -> 1.6611296 | H75: 1.71762 | J75: 42339 | K75: 12346.8 | L75: 5.66458 | M75: 0.63872 | N75: 0.24 | O75: =(C741/C729-1)*100 -> 2.0956968 | P75: 0.63297674 | R75: 2026
B76: 22098 | C76: 30.6 | D76: 3.23 | E76: 304.1 | F76: 3.01491 | G76: =(C76/C64-1)*100 -> 1.3245033 | H76: 1.37221 | J76: 42370 | K76: 12469.9 | L76: 6.16656 | M76: 1.2375 | N76: 0.34 | O76: =(C742/C730-1)*100 -> 2.206915 | P76: 1.3437776 | R76: 2027
B77: 22129 | C77: 30.6 | D77: 2.98 | E77: 306.9 | F77: 3.54251 | G77: =(C77/C65-1)*100 -> 1.3245033 | H77: 1.47361 | J77: 42401 | K77: 12556.7 | L77: 5.70503 | M77: 0.84728 | N77: 0.38 | O77: =(C743/C731-1)*100 -> 2.3312771 | P77: 0.97863247 | R77: 2028
B78: 22160 | C78: 30.6 | D78: 2.6 | E78: 308.4 | F78: 3.94338 | G78: =(C78/C66-1)*100 -> 0.99009901 | H78: 1.23077 | J78: 42430 | K78: 12616.7 | L78: 6.14042 | M78: 0.89162 | N78: 0.36 | O78: =(C744/C732-1)*100 -> 2.1948255 | P78: 0.77630699 | R78: 2029
B79: 22190 | C79: 30.8 | D79: 2.47 | E79: 309.5 | F79: 4.38449 | G79: =(C79/C67-1)*100 -> 0.98360656 | H79: 1.36286 | J79: 42461 | K79: 12700.4 | L79: 6.46749 | M79: 1.17263 | N79: 0.37 | O79: =(C745/C733-1)*100 -> 2.1463842 | P79: 1.0399025 | R79: 2030
B80: 22221 | C80: 30.8 | D80: 2.44 | E80: 310.9 | F80: 4.6449 | G80: =(C80/C68-1)*100 -> 0.98360656 | H80: 1.46508 | J80: 42491 | K80: 12766.2 | L80: 6.75955 | M80: 1.07848 | N80: 0.37 | O80: =(C746/C734-1)*100 -> 2.2406337 | P80: 0.89033389 | R80: 2031
B81: 22251 | C81: 30.8 | D81: 1.98 | E81: 312.4 | F81: 4.90262 | G81: =(C81/C69-1)*100 -> 0.98360656 | H81: 1.36008 | J81: 42522 | K81: 12829.4 | L81: 6.89652 | M81: 1.07929 | N81: 0.38 | O81: =(C747/C735-1)*100 -> 2.2446504 | P81: 0.85759919 | R81: 2032
B82: 22282 | C82: 30.8 | D82: 1.45 | E82: 314.1 | F82: 5.33199 | G82: =(C82/C70-1)*100 -> 0.98360656 | H82: 1.60027 | J82: 42552 | K82: 12887.7 | L82: 6.94033 | M82: 0.86836 | N82: 0.39 | O82: =(C748/C736-1)*100 -> 2.1894438 | P82: 0.69604036 | R82: 2033
B83: 22313 | C83: 30.8 | D83: 2.54 | E83: 316.5 | F83: 6.06568 | G83: =(C83/C71-1)*100 -> 0.65359477 | H83: 1.46209 | J83: 42583 | K83: 12972.8 | L83: 7.19639 | M83: 1.05532 | N83: 0.4 | O83: =(C749/C737-1)*100 -> 2.3189684 | P83: 0.96318551 | R83: 2034
... B149: 24320 | C149: 33.7 | D149: 5.53 | E149: 472.6 | F149: 6.01166 | G149: =(C149/C137-1)*100 -> 3.058104 | H149: 3.48653 | J149: 44593 | K149: 21570.5 | L149: 10.05076 | M149: 7.95485 | N149: 0.08 | O149: =(C815/C803-1)*100 -> 6.4142063 | P149: 7.8314185 | R149: 2100
B150: 24351 | C150: 33.8 | D150: 5.4 | E150: 475.4 | F150: 5.76196 | G150: =(C150/C138-1)*100 -> 3.0487805 | H150: 3.57369 | J150: 44621 | K150: 21697.6 | L150: 9.35739 | M150: 8.51522 | N150: 0.2 | O150: =(C816/C804-1)*100 -> 6.4744786 | P150: 8.4595243
B151: 24381 | C151: 34 | D151: 5.53 | E151: 475.7 | F151: 5.10384 | G151: =(C151/C139-1)*100 -> 3.343465 | H151: 3.79147 | J151: 44652 | K151: 21677.2 | L151: 7.75617 | M151: 8.22777 | N151: 0.33 | O151: =(C817/C805-1)*100 -> 6.1605735 | P151: 8.1966115
B152: 24412 | C152: 34.1 | D152: 5.76 | E152: 477.3 | F152: 4.73996 | G152: =(C152/C140-1)*100 -> 3.6474164 | H152: 3.55906 | J152: 44682 | K152: 21665.6 | L152: 6.04226 | M152: 8.50233 | N152: 0.77 | O152: =(C818/C806-1)*100 -> 6.0215373 | P152: 8.5198957
B153: 24442 | C153: 34.1 | D153: 5.4 | E153: 480.2 | F153: 4.57317 | G153: =(C153/C141-1)*100 -> 3.3333333 | H153: 3.3595 | J153: 44713 | K153: 21666.4 | L153: 5.65574 | M153: 8.93299 | N153: 1.21 | O153: =(C819/C807-1)*100 -> 5.9169428 | P153: 8.9683715
B154: 24473 | C154: 34.1 | D154: 4.94 | E154: 481.6 | F154: 4.24242 | G154: =(C154/C142-1)*100 -> 3.6474164 | H154: 3.1995 | J154: 44743 | K154: 21703.6 | L154: 5.03605 | M154: 8.41318 | N154: 1.68 | O154: =(C820/C808-1)*100 -> 5.9108853 | P154: 8.4617217
B155: 24504 | C155: 34.2 | D155: 5 | E155: 485.1 | F155: 4.4124 | G155: =(C155/C143-1)*100 -> 3.6363636 | H155: 2.86783 | J155: 44774 | K155: 21659.9 | L155: 3.89488 | M155: 8.22736 | N155: 2.33 | O155: =(C821/C809-1)*100 -> 6.322203 | P155: 8.2149894
B156: 24532 | C156: 34.3 | D156: 4.53 | E156: 489.7 | F156: 4.81592 | G156: =(C156/C144-1)*100 -> 3.6253776 | H156: 2.54817 | J156: 44805 | K156: 21525.2 | L156: 2.6755 | M156: 8.21485 | N156: 2.56 | O156: =(C822/C810-1)*100 -> 6.6306041 | P156: 8.1891084
B157: 24563 | C157: 34.4 | D157: 4.05 | E157: 492.1 | F157: 4.8583 | G157: =(C157/C145-1)*100 -> 3.3033033 | H157: 2.54027 | J157: 44835 | K157: 21433.3 | L157: 1.50121 | M157: 7.76249 | N157: 3.08 | O157: =(C823/C811-1)*100 -> 6.2844218 | P157: 7.7466916
B158: 24593 | C158: 34.5 | D158: 3.94 | E158: 497.2 | F158: 5.76473 | G158: =(C158/C146-1)*100 -> 3.2934132 | H158: 2.31839 | J158: 44866 | K158: 21399.3 | L158: 0.38937 | M158: 7.13535 | N158: 3.78 | O158: =(C824/C812-1)*100 -> 5.9578291 | P158: 7.1283444
B159: 24624 | C159: 34.6 | D159: 3.98 | E159: 502 | F159: 6.5365 | G159: =(C159/C147-1)*100 -> 3.2835821 | H159: 2.84126 | J159: 44896 | K159: 21358.2 | L159: -0.8868 | M159: 6.44494 | N159: 4.1 | O159: =(C825/C813-1)*100 -> 5.7078349 | P159: 6.5166735
B160: 24654 | C160: 34.7 | D160: 3.79 | E160: 506.3 | F160: 7.51752 | G160: =(C160/C148-1)*100 -> 3.2738095 | H160: 2.92758 | J160: 44927 | K160: 21222.3 | L160: -1.57591 | M160: 6.34716 | N160: 4.33 | O160: =(C826/C814-1)*100 -> 5.5825956 | P160: 6.3316671
B161: 24685 | C161: 34.8 | D161: 3.9 | E161: 510.8 | F161: 8.08295 | G161: =(C161/C149-1)*100 -> 3.264095 | H161: 2.60337 | J161: 44958 | K161: 21100.9 | L161: -2.17705 | M161: 5.98644 | N161: 4.57 | O161: =(C827/C815-1)*100 -> 5.5377544 | P161: 5.90445
... B168: 24898 | C168: 35.8 | D168: 5.05 | E168: 533.2 | F168: 8.88299 | G168: =(C168/C156-1)*100 -> 4.3731778 | H168: 3.93939 | J168: 45170 | K168: 20754.9 | L168: -3.5786 | M168: 3.6899 | N168: 5.33 | O168: =(C834/C822-1)*100 -> 4.1465343 | P168: 3.6503649
B169: 24929 | C169: 35.9 | D169: 5.76 | E169: 535.7 | F169: 8.85999 | G169: =(C169/C157-1)*100 -> 4.3604651 | H169: 3.92749 | J169: 45200 | M169: 3.23236 | N169: 5.33 | O169: =(C835/C823-1)*100 -> 4.0308705
B170: 24959 | C170: 36 | D170: 6.12 | E170: 538.9 | F170: 8.38697 | G170: =(C170/C158-1)*100 -> 4.3478261 | H170: 4.22961 | J170: 45231
B171: 24990 | C171: 36.2 | D171: 6.07 | E171: 542.6 | F171: 8.08765 | G171: =(C171/C159-1)*100 -> 4.6242775 | H171: 4.2042 | J171: 45261
B172: 25020 | C172: 36.4 | D172: 6.03 | E172: 545.6 | F172: 7.7622 | G172: =(C172/C160-1)*100 -> 4.8991354 | H172: 4.49102 | J172: 45292 | K172: =K168*0.94 -> 19509.606
B173: 25051 | C173: 36.5 | D173: 6.03 | E173: 549.4 | F173: 7.55677 | G173: =(C173/C161-1)*100 -> 4.8850575 | H173: 4.47761 | J173: 45323
B174: 25082 | C174: 36.7 | D174: 5.78 | E174: 553.6 | F174: 7.5578 | G174: =(C174/C162-1)*100 -> 4.8571429 | H174: 4.46429 | J174: 45352
B175: 25112 | C175: 36.9 | D175: 5.91 | E175: 557.6 | F175: 7.60324 | G175: =(C175/C163-1)*100 -> 4.8295455 | H175: 4.74777 | J175: 45383
...

Sheet charts
E353: سال شمسی | F353: 1338 | G353: 1339 | H353: 1340 | I353: 1341 | J353: 1342 | K353: 1343 | L353: 1344 | M353: 1345 | N353: 1346 | O353: 1347 | P353: 1348 | Q353: 1349 | R353: 1350 | S353: 1351 | T353: 1352 | U353: 1353 | V353: 1354 | W353: 1355 | X353: 1356 | Y353: 1357 | Z353: 1358 | AA353: 1359 | AB353: 1360 | AC353: 1361 | AD353: 1362 | AE353: 1363 | AF353: 1364 | AG353: 1365 | AH353: 1366 | AI353: 1367 | AJ353: 1368 | AK353: 1369 | AL353: 1370 | AM353: 1371 | AN353: 1372 | AO353: 1373 | AP353: 1374 | AQ353: 1375 | AR353: 1376 | AS353: 1377 | AT353: 1378 | AU353: 1379 | AV353: 1380 | AW353: 1381 | AX353: 1382 | AY353: 1383 | AZ353: 1384 | BA353: 1385 | BB353: 1386 | BC353: 1387 | BD353: 1388 | BE353: 1389 | BF353: 1390 | BG353: 1391 | BH353: 1392 | BI353: 1393 | BJ353: 1394 | BK353: 1395 | BL353: 1396 | BM353: 1397 | BN353: 1398 | BO353: 1399 | BP353: 1400 | BQ353: 1401 | BR353: 1402 | BS353: 1403 | BT353: 1404 پیش بینی | BU353: پیش بینی 1405 | BV353: پیش بینی 1406
E354: میانگین نرخ ارز رویکرد پولی با نفت - عدم کاهش فروش نفت | R354: 43.735571 | S354: 44.49622 | T354: 45.309142 | U354: 27.777064 | V354: 39.73341 | W354: 40.94581 | X354: 56.680893 | Y354: 123.08365 | Z354: 131.2692 | AA354: 444.18671 | AB354: 602.73397 | AC354: 277.89634 | AD354: 301.22569 | AE354: 434.86875 | AF354: 583.58128 | AG354: 1624.8121 | AH354: 1157.9373 | AI354: 1720.5874 | AJ354: 1609.787 | AK354: 1213.0074 | AL354: 1542.5821 | AM354: 1899.4022 | AN354: 3198.7406 | AO354: 4362.4942 | AP354: 5602.9597 | AQ354: 5602.1264 | AR354: 7621.4269 | AS354: 12902.633 | AT354: 8811.3586 | AU354: 7714.8622 | AV354: 11563.715 | AW354: 11661.571 | AX354: 11415.141 | AY354: 10900.909 | AZ354: 9426.1453 | BA354: 10511.894 | BB354: 8922.052 | BC354: 9673.0073 | BD354: 13513.895 | BE354: 13312.749 | BF354: 11581.058 | BG354: 27250.254 | BH354: 40070.871 | BI354: 53752.947 | BJ354: 122971.27 | BK354: 82382.829 | BL354: 82895.449 | BM354: 116511.22 | BN354: 330401.49 | BO354: 421963.6 | BP354: 319864.43 | BQ354: 402532.93 | BR354: 538235.46 | BS354: 745710.69 | BT354: 926336.01 | BU354: 1210821.4
E355: میانگین نرخ ارز رویکرد پولی با نفت- با افت 20 درصد فروش نفت | R355: 43.735571 | S355: 44.49622 | T355: 45.309142 | U355: 27.777064 | V355: 39.73341 | W355: 40.94581 | X355: 56.680893 | Y355: 123.08365 | Z355: 131.2692 | AA355: 444.18671 | AB355: 602.73397 | AC355: 277.89634 | AD355: 301.22569 | AE355: 434.86875 | AF355: 583.58128 | AG355: 1624.8121 | AH355: 1157.9373 | AI355: 1720.5874 | AJ355: 1609.787 | AK355: 1213.0074 | AL355: 1542.5821 | AM355: 1899.4022 | AN355: 3198.7406 | AO355: 4362.4942 | AP355: 5602.9597 | AQ355: 5602.1264 | AR355: 7621.4269 | AS355: 12902.633 | AT355: 8811.3586 | AU355: 7714.8622 | AV355: 11563.715 | AW355: 11661.571 | AX355: 11415.141 | AY355: 10900.909 | AZ355: 9426.1453 | BA355: 10511.894 | BB355: 8922.052 | BC355: 9673.0073 | BD355: 13513.895 | BE355: 13312.749 | BF355: 11581.058 | BG355: 27250.254 | BH355: 40070.871 | BI355: 53752.947 | BJ355: 122971.27 | BK355: 82382.829 | BL355: 82895.449 | BM355: 116511.22 | BN355: 330401.49 | BO355: 421963.6 | BP355: 319864.43 | BQ355: 402532.93 | BR355: 538235.46 | BS355: 745710.69 | BT355: 1029262.2 | BU355: 1494841.2
E356: میانگین نرخ ارز رویکرد پولی با نفت- افت 40 درصدی فروشش نفت | R356: 43.735571 | S356: 44.49622 | T356: 45.309142 | U356: 27.777064 | V356: 39.73341 | W356: 40.94581 | X356: 56.680893 | Y356: 123.08365 | Z356: 131.2692 | AA356: 444.18671 | AB356: 602.73397 | AC356: 277.89634 | AD356: 301.22569 | AE356: 434.86875 | AF356: 583.58128 | AG356: 1624.8121 | AH356: 1157.9373 | AI356: 1720.5874 | AJ356: 1609.787 | AK356: 1213.0074 | AL356: 1542.5821 | AM356: 1899.4022 | AN356: 3198.7406 | AO356: 4362.4942 | AP356: 5602.9597 | AQ356: 5602.1264 | AR356: 7621.4269 | AS356: 12902.633 | AT356: 8811.3586 | AU356: 7714.8622 | AV356: 11563.715 | AW356: 11661.571 | AX356: 11415.141 | AY356: 10900.909 | AZ356: 9426.1453 | BA356: 10511.894 | BB356: 8922.052 | BC356: 9673.0073 | BD356: 13513.895 | BE356: 13312.749 | BF356: 11581.058 | BG356: 27250.254 | BH356: 40070.871 | BI356: 53752.947 | BJ356: 122971.27 | BK356: 82382.829 | BL356: 82895.449 | BM356: 116511.22 | BN356: 330401.49 | BO356: 421963.6 | BP356: 319864.43 | BQ356: 402532.93 | BR356: 538235.46 | BS356: 745710.69 | BT356: 1157920 | BU356: 1681696.4
E357: نرخ ارز بازار آزاد (ریال) | F357: 76 | G357: 76 | H357: 76 | I357: 76 | J357: 76 | K357: 76 | L357: 76 | M357: 76 | N357: 76 | O357: 76 | P357: 76 | Q357: 76 | R357: 76 | S357: 69 | T357: 68 | U357: 68 | V357: 68 | W357: 71 | X357: 71 | Y357: 100 | Z357: 141 | AA357: 200 | AB357: 270 | AC357: 350 | AD357: 450 | AE357: 580 | AF357: 614 | AG357: 742 | AH357: 991 | AI357: 966 | AJ357: 1207.1 | AK357: 1412.3 | AL357: 1420.2 | AM357: 1498 | AN357: 1806 | AO357: 2635 | AP357: 4036 | AQ357: 4446 | AR357: 4782 | AS357: 6468 | AT357: 8634 | AU357: 8131 | AV357: 7925 | AW357: 7991 | AX357: 8323 | AY357: 8747 | AZ357: 9042 | BA357: 9226 | BB357: 9357 | BC357: 9667 | BD357: 9979 | BE357: 10601 | BF357: 13568 | BG357: 26059 | BH357: 31839 | BI357: 32801 | BJ357: 34501 | BK357: 36440 | BL357: 40453 | BM357: 103378 | BN357: 129185 | BO357: 228809 | BP357: 259476 | BQ357: 349266 | BR357: 517807.6 | BS357: 690000 | BT357: 965656.05 | BU357: 1320232.9

Sheet oil price
F2: Crude oil, average
F3: ($/bbl)
F4: KCRUDE_PETRO
F5: 8.5149781 | G5: 8.5149781
F6: 8.0450248 | G6: 8.0450248
F7: 7.6461378 | G7: 7.6461378
F8: 7.6863294 | G8: 7.6863294
F9: 7.3275697 | G9: 7.3275697
F10: 7.107594 | G10: 7.107594
F11: 6.5652247 | G11: 6.5652247
F12: 6.3644634 | G12: 6.3644634
F13: 6.3721298 | G13: 6.3721298
F14: 5.8192247 | G14: 5.8192247
F15: 5.2122356 | G15: 5.2122356
F16: 6.9220738 | G16: 6.9220738
... F67: 87.954157 | G67: 87.954157

Sheet معاملات نیما
C1: معکوس مازاد عرضه | D1: درصد معامله شده به معکوس مازاد عرضه (متوسط 20 روزه) | E1: درصد معامله شده به معکوس مازاد عرضه (متوسط 10 روزه) | F1: درصد معامله شده به معکوس مازاد عرضه (متوسط 5 روزه) | G1: متوسط 20روزه مازاد عرضه (میلیون دلار) | H1: متوسط 10روزه مازاد عرضه (میلیون دلار) | I1: متوسط 5 روزه مازاد عرضه (میلیون دلار) | J1: مازاد عرضه (میلیون دلار) | K1: متوسط 20 روزه عرضه در سامانه نیما | L1: متوسط 20 روزه تقاضا (معامله شده) در سامانه نیما | M1: متوسط 10 روزه تقاضا (معامله شده) در سامانه نیما | N1: متوسط 5 روزه تقاضا (معامله شده) در سامانه نیما | O1: متوسط 20 روزه رشد تقاضا (معامله شده) | P1: متوسط 10روزه رشد تقاضا (معامله شده) | Q1: متوسط 5 روزه رشد تقاضا (معامله شده) | R1: رشد تقاضا (معامله شده) در سامانه نیما | S1: درصد معامله نسبت به عرضه (میانگین 20 روزه) | T1: درصد معامله نسبت به عرضه (میانگین 10 روزه) | U1: درصد معامله نسبت به عرضه (میانگین 5 روزه) | V1: درصد معامله نسبت به عرضه | W1: معامله شده (میلیون دلار) | X1: عرضه (میلیون دلار) | Y1: تاریخ
J2: =1/(X2-W2) -> 0.001333689 | V2: =W2/X2 -> 0.22525315 | W2: 218 | X2: 967.8 | Y2: 1401/06/23
J3: =X3-W3 -> 725 | R3: =W3/W2-1 -> -0.77522936 | V3: =W3/X3 -> 0.063307494 | W3: 49 | X3: 774 | Y3: 1401/06/24
J4: =X4-W4 -> 768 | R4: =W4/W3-1 -> 1.3877551 | V4: =W4/X4 -> 0.13220339 | W4: 117 | X4: 885 | Y4: 1401/06/27
J5: =X5-W5 -> 799 | R5: =W5/W4-1 -> 1.025641 | V5: =W5/X5 -> 0.22876448 | W5: 237 | X5: 1036 | Y5: 1401/06/28
F6: =U6/(1/I6) -> 94.957857 | I6: =AVERAGE(J2:J6) -> 631.00027 | J6: =X6-W6 -> 863 | N6: =AVERAGE(W2:W6) -> 144 | Q6: =AVERAGE(R2:R6) -> 0.26397207 | R6: =W6/W5-1 -> -0.58227848 | U6: =AVERAGE(V2:V6) -> 0.15048782 | V6: =W6/X6 -> 0.1029106 | W6: 99 | X6: 962 | Y6: 1401/06/29
F7: =U7/(1/I7) -> 103.26705 | I7: =AVERAGE(J3:J7) -> 780.8 | J7: =X7-W7 -> 749 | N7: =AVERAGE(W3:W7) -> 123.6 | Q7: =AVERAGE(R3:R7) -> 0.24552109 | R7: =W7/W6-1 -> 0.17171717 | U7: =AVERAGE(V3:V7) -> 0.132258 | V7: =W7/X7 -> 0.13410405 | W7: 116 | X7: 865 | Y7: 1401/06/30
F8: =U8/(1/I8) -> 96.818903 | I8: =AVERAGE(J4:J8) -> 779.4 | J8: =X8-W8 -> 718 | N8: =AVERAGE(W4:W8) -> 117.2 | Q8: =AVERAGE(R4:R8) -> 0.22987731 | R8: =W8/W7-1 -> -0.85344828 | U8: =AVERAGE(V4:V8) -> 0.12422235 | V8: =W8/X8 -> 0.023129252 | W8: 17 | X8: 735 | Y8: 1401/06/31
F9: =U9/(1/I9) -> 99.073485 | I9: =AVERAGE(J5:J9) -> 779 | J9: =X9-W9 -> 766 | N9: =AVERAGE(W5:W9) -> 120.2 | Q9: =AVERAGE(R5:R9) -> 1.3052675 | R9: =W9/W8-1 -> 6.7647059 | U9: =AVERAGE(V5:V9) -> 0.12718034 | V9: =W9/X9 -> 0.14699332 | W9: 132 | X9: 898 | Y9: 1401/07/02
F10: =U10/(1/I10) -> 81.047749 | I10: =AVERAGE(J6:J10) -> 771.6 | J10: =X10-W10 -> 762 | N10: =AVERAGE(W6:W10) -> 93.2 | Q10: =AVERAGE(R6:R10) -> 1.0546847 | R10: =W10/W9-1 -> -0.22727273 | U10: =AVERAGE(V6:V10) -> 0.10503855 | V10: =W10/X10 -> 0.11805556 | W10: 102 | X10: 864 | Y10: 1401/07/04
E11: =T11/(1/H11) -> 90.621068 | F11: =U11/(1/I11) -> 83.901313 | H11: =AVERAGE(J2:J11) -> 692.00013 | I11: =AVERAGE(J7:J11) -> 753 | J11: =X11-W11 -> 770 | M11: =AVERAGE(W2:W11) -> 120.7 | N11: =AVERAGE(W7:W11) -> 97.4 | Q11: =AVERAGE(R7:R11) -> 1.2064345 | R11: =W11/W10-1 -> 0.17647059 | T11: =AVERAGE(V2:V11) -> 0.13095527 | U11: =AVERAGE(V7:V11) -> 0.11142273 | V11: =W11/X11 -> 0.13483146 | W11: 120 | X11: 890 | Y11: 1401/07/06
E12: =T12/(1/H12) -> 85.700382 | F12: =U12/(1/I12) -> 68.808563 | H12: =AVERAGE(J3:J12) -> 764 | I12: =AVERAGE(J8:J12) -> 747.2 | J12: =X12-W12 -> 720 | M12: =AVERAGE(W3:W12) -> 101.7 | N12: =AVERAGE(W8:W12) -> 79.8 | P12: =AVERAGE(R3:R12) -> 0.63213943 | Q12: =AVERAGE(R8:R12) -> 1.0187578 | R12: =W12/W11-1 -> -0.76666667 | T12: =AVERAGE(V3:V12) -> 0.11217328 | U12: =AVERAGE(V8:V12) -> 0.092088548 | V12: =W12/X12 -> 0.037433155 | W12: 28 | X12: 748 | Y12: 1401/07/07
E13: =T13/(1/H13) -> 90.798565 | F13: =U13/(1/I13) -> 84.906122 | H13: =AVERAGE(J4:J13) -> 769 | I13: =AVERAGE(J9:J13) -> 758.6 | J13: =X13-W13 -> 775 | M13: =AVERAGE(W4:W13) -> 107.6 | N13: =AVERAGE(W9:W13) -> 98 | P13: =AVERAGE(R4:R13) -> 0.99537665 | Q13: =AVERAGE(R9:R13) -> 1.760876 | R13: =W13/W12-1 -> 2.8571429 | T13: =AVERAGE(V4:V13) -> 0.11807356 | U13: =AVERAGE(V9:V13) -> 0.11192476 | V13: =W13/X13 -> 0.12231031 | W13: 108 | X13: 883 | Y13: 1401/07/10
E14: =T14/(1/H14) -> 94.5751 | F14: =U14/(1/I14) -> 90.1774 | H14: =AVERAGE(J5:J14) -> 764.5 | I14: =AVERAGE(J10:J14) -> 750 | J14: =X14-W14 -> 723 | M14: =AVERAGE(W5:W14) -> 112.7 | N14: =AVERAGE(W10:W14) -> 105.2 | P14: =AVERAGE(R5:R14) -> 0.91215669 | Q14: =AVERAGE(R10:R14) -> 0.51904592 | R14: =W14/W13-1 -> 0.55555556 | T14: =AVERAGE(V5:V14) -> 0.12370844 | U14: =AVERAGE(V10:V14) -> 0.12023653 | V14: =W14/X14 -> 0.18855219 | W14: 168 | X14: 891 | Y14: 1401/07/12
E15: =T15/(1/H15) -> 84.181342 | F15: =U15/(1/I15) -> 87.109301 | H15: =AVERAGE(J6:J15) -> 755.5 | I15: =AVERAGE(J11:J15) -> 739.4 | J15: =X15-W15 -> 709 | M15: =AVERAGE(W6:W15) -> 97.4 | N15: =AVERAGE(W11:W15) -> 101.6 | P15: =AVERAGE(R6:R15) -> 0.75959259 | Q15: =AVERAGE(R11:R15) -> 0.46450047 | R15: =W15/W14-1 -> -0.5 | T15: =AVERAGE(V6:V15) -> 0.11142467 | U15: =AVERAGE(V11:V15) -> 0.11781079 | V15: =W15/X15 -> 0.10592686 | W15: 84 | X15: 793 | Y15: 1401/07/14
E16: =T16/(1/H16) -> 89.548344 | F16: =U16/(1/I16) -> 95.03241 | H16: =AVERAGE(J7:J16) -> 743.9 | I16: =AVERAGE(J12:J16) -> 734.8 | J16: =X16-W16 -> 747 | M16: =AVERAGE(W7:W16) -> 105.3 | N16: =AVERAGE(W12:W16) -> 113.2 | P16: =AVERAGE(R7:R16) -> 0.9297252 | Q16: =AVERAGE(R12:R16) -> 0.65301587 | R16: =W16/W15-1 -> 1.1190476 | T16: =AVERAGE(V7:V16) -> 0.12037686 | U16: =AVERAGE(V12:V16) -> 0.12933099 | V16: =W16/X16 -> 0.19243243 | W16: 178 | X16: 925 | Y16: 1401/07/16
E17: =T17/(1/H17) -> 94.444633 | F17: =U17/(1/I17) -> 119.97701 | H17: =AVERAGE(J8:J17) -> 745.7 | I17: =AVERAGE(J13:J17) -> 744.2 | J17: =X17-W17 -> 767 | M17: =AVERAGE(W8:W17) -> 112.5 | N17: =AVERAGE(W13:W17) -> 145.2 | P17: =AVERAGE(R8:R17) -> 0.91817146 | Q17: =AVERAGE(R13:R17) -> 0.81758516 | R17: =W17/W16-1 -> 0.056179775 | T17: =AVERAGE(V8:V17) -> 0.12665232 | U17: =AVERAGE(V13:V17) -> 0.16121609 | V17: =W17/X17 -> 0.19685864 | W17: 188 | X17: 955 | Y17: 1401/07/17
E18: =T18/(1/H18) -> 110.94901 | F18: =U18/(1/I18) -> 136.53655 | H18: =AVERAGE(J9:J18) -> 752.2 | I18: =AVERAGE(J14:J18) -> 745.8 | J18: =X18-W18 -> 783 | M18: =AVERAGE(W9:W18) -> 134.4 | N18: =AVERAGE(W14:W18) -> 170.8 | P18: =AVERAGE(R9:R18) -> 1.0290482 | Q18: =AVERAGE(R14:R18) -> 0.29722042 | R18: =W18/W17-1 -> 0.25531915 | T18: =AVERAGE(V9:V18) -> 0.14749935 | U18: =AVERAGE(V14:V18) -> 0.18307395 | V18: =W18/X18 -> 0.23159961 | W18: 236 | X18: 1019 | Y18: 1401/07/18
E19: =T19/(1/H19) -> 111.85955 | F19: =U19/(1/I19) -> 133.65012 | H19: =AVERAGE(J10:J19) -> 751.9 | I19: =AVERAGE(J15:J19) -> 753.8 | J19: =X19-W19 -> 763 | M19: =AVERAGE(W10:W19) -> 135.7 | N19: =AVERAGE(W15:W19) -> 166.2 | P19: =AVERAGE(R10:R19) -> 0.31401829 | Q19: =AVERAGE(R15:R19) -> 0.10899066 | R19: =W19/W18-1 -> -0.38559322 | T19: =AVERAGE(V10:V19) -> 0.14876918 | U19: =AVERAGE(V15:V19) -> 0.17730183 | V19: =W19/X19 -> 0.15969163 | W19: 145 | X19: 908 | Y19: 1401/07/20
E20: =T20/(1/H20) -> 106.36238 | F20: =U20/(1/I20) -> 126.11998 | H20: =AVERAGE(J11:J20) -> 749.9 | I20: =AVERAGE(J16:J20) -> 760.4 | J20: =X20-W20 -> 742 | M20: =AVERAGE(W11:W20) -> 129.3 | N20: =AVERAGE(W16:W20) -> 157 | P20: =AVERAGE(R11:R20) -> 0.26295246 | Q20: =AVERAGE(R16:R20) -> 0.061404458 | R20: =W20/W19-1 -> -0.73793103 | T20: =AVERAGE(V11:V20) -> 0.14183542 | U20: =AVERAGE(V16:V20) -> 0.16586005 | V20: =W20/X20 -> 0.048717949 | W20: 38 | X20: 780 | Y20: 1401/07/21
D21: =S21/(1/G21) -> 100.0053 | E21: =T21/(1/H21) -> 109.84642 | F21: =U21/(1/I21) -> 125.29346 | G21: =AVERAGE(J2:J21) -> 723.10007 | H21: =AVERAGE(J12:J21) -> 754.2 | I21: =AVERAGE(J17:J21) -> 773.6 | J21: =X21-W21 -> 813 | K21: =AVERAGE(X2:X21) -> 888.09 | L21: =AVERAGE(W2:W21) -> 127.5 | M21: =AVERAGE(W12:W21) -> 134.3 | N21: =AVERAGE(W17:W21) -> 155.4 | P21: =AVERAGE(R12:R21) -> 0.59267382 | Q21: =AVERAGE(R17:R21) -> 0.53233178 | R21: =W21/W20-1 -> 3.4736842 | S21: =AVERAGE(V2:V21) -> 0.13830077 | T21: =AVERAGE(V12:V21) -> 0.14564627 | U21: =AVERAGE(V17:V21) -> 0.16196156 | V21: =W21/X21 -> 0.17293998 | W21: 170 | X21: 983 | Y21: 1401/07/23
D22: =S22/(1/G22) -> 103.54829 | E22: =T22/(1/H22) -> 120.79469 | F22: =U22/(1/I22) -> 121.5977 | G22: =AVERAGE(J3:J22) -> 752.2 | H22: =AVERAGE(J13:J22) -> 740.4 | I22: =AVERAGE(J18:J22) -> 736.6 | J22: =X22-W22 -> 582 | K22: =AVERAGE(X3:X22) -> 876.65 | L22: =AVERAGE(W3:W22) -> 124.45 | M22: =AVERAGE(W13:W22) -> 147.2 | N22: =AVERAGE(W18:W22) -> 149.2 | O22: =AVERAGE(R3:R22) -> 0.64691643 | P22: =AVERAGE(R13:R22) -> 0.66169343 | Q22: =AVERAGE(R18:R22) -> 0.5058017 | R22: =W22/W21-1 -> -0.076470588 | S22: =AVERAGE(V3:V22) -> 0.13766058 | T22: =AVERAGE(V13:V22) -> 0.16314788 | U22: =AVERAGE(V18:V22) -> 0.16507968 | V22: =W22/X22 -> 0.21244926 | W22: 157 | X22: 739 | Y22: 1401/07/24
D23: =S23/(1/G23) -> 110.26181 | E23: =T23/(1/H23) -> 128.17992 | F23: =U23/(1/I23) -> 120.07582 | G23: =AVERAGE(J4:J23) -> 743.45 | H23: =AVERAGE(J14:J23) -> 717.9 | I23: =AVERAGE(J19:J23) -> 690 | J23: =X23-W23 -> 550 | K23: =AVERAGE(X4:X23) -> 875.95 | L23: =AVERAGE(W4:W23) -> 132.5 | M23: =AVERAGE(W14:W23) -> 157.4 | N23: =AVERAGE(W19:W23) -> 144 | O23: =AVERAGE(R4:R23) -> 0.70255688 | P23: =AVERAGE(R14:R23) -> 0.40973711 | Q23: =AVERAGE(R19:R23) -> 0.5222538 | R23: =W23/W22-1 -> 0.33757962 | S23: =AVERAGE(V4:V23) -> 0.14831099 | T23: =AVERAGE(V14:V23) -> 0.17854843 | U23: =AVERAGE(V19:V23) -> 0.17402292 | V23: =W23/X23 -> 0.27631579 | W23: 210 | X23: 760 | Y23: 1401/07/25
D24: =S24/(1/G24) -> 112.39753 | E24: =T24/(1/H24) -> 128.40372 | F24: =U24/(1/I24) -> 122.61012 | G24: =AVERAGE(J5:J24) -> 733.7 | H24: =AVERAGE(J15:J24) -> 702.9 | I24: =AVERAGE(J20:J24) -> 652 | J24: =X24-W24 -> 573 | K24: =AVERAGE(X5:X24) -> 868.9 | L24: =AVERAGE(W5:W24) -> 135.2 | M24: =AVERAGE(W15:W24) -> 157.7 | N24: =AVERAGE(W20:W24) -> 149.2 | O24: =AVERAGE(R5:R24) -> 0.62388341 | P24: =AVERAGE(R15:R24) -> 0.33561012 | Q24: =AVERAGE(R20:R24) -> 0.56222958 | R24: =W24/W23-1 -> -0.18571429 | S24: =AVERAGE(V5:V24) -> 0.15319276 | T24: =AVERAGE(V15:V24) -> 0.18267709 | U24: =AVERAGE(V20:V24) -> 0.18805234 | V24: =W24/X24 -> 0.22983871 | W24: 171 | X24: 744 | Y24: 1401/07/26
D25: =S25/(1/G25) -> 112.43233 | E25: =T25/(1/H25) -> 137.64813 | F25: =U25/(1/I25) -> 144.13385 | G25: =AVERAGE(J6:J25) -> 721.35 | H25: =AVERAGE(J16:J25) -> 687.2 | I25: =AVERAGE(J21:J25) -> 614 | J25: =X25-W25 -> 552 | K25: =AVERAGE(X6:X25) -> 855.55 | L25: =AVERAGE(W6:W25) -> 134.2 | M25: =AVERAGE(W16:W25) -> 171 | N25: =AVERAGE(W21:W25) -> 185 | O25: =AVERAGE(R6:R25) -> 0.58605165 | P25: =AVERAGE(R16:R25) -> 0.41251071 | Q25: =AVERAGE(R21:R25) -> 0.76361696 | R25: =W25/W24-1 -> 0.26900585 | S25: =AVERAGE(V6:V25) -> 0.15586377 | T25: =AVERAGE(V16:V25) -> 0.20030286 | U25: =AVERAGE(V21:V25) -> 0.23474568 | V25: =W25/X25 -> 0.28218466 | W25: 217 | X25: 769 | Y25: 1401/07/27
D26: =S26/(1/G26) -> 107.45554 | E26: =T26/(1/H26) -> 122.81706 | F26: =U26/(1/I26) -> 115.38344 | G26: =AVERAGE(J7:J26) -> 704.35 | H26: =AVERAGE(J17:J26) -> 664.8 | I26: =AVERAGE(J22:J26) -> 556 | J26: =X26-W26 -> 523 | K26: =AVERAGE(X7:X26) -> 834.6 | L26: =AVERAGE(W7:W26) -> 130.25 | M26: =AVERAGE(W17:W26) -> 155.2 | N26: =AVERAGE(W22:W26) -> 155 | O26: =AVERAGE(R7:R26) -> 0.56977387 | P26: =AVERAGE(R17:R26) -> 0.20982254 | Q26: =AVERAGE(R22:R26) -> -0.1126867 | R26: =W26/W25-1 -> -0.9078341 | S26: =AVERAGE(V7:V26) -> 0.15255986 | T26: =AVERAGE(V17:V26) -> 0.18474286 | U26: =AVERAGE(V22:V26) -> 0.20752416 | V26: =W26/X26 -> 0.036832413 | W26: 20 | X26: 543 | Y26: 1401/07/28
D27: =S27/(1/G27) -> 109.75581 | E27: =T27/(1/H27) -> 122.00246 | F27: =U27/(1/I27) -> 118.17854 | G27: =AVERAGE(J8:J27) -> 696.25 | H27: =AVERAGE(J18:J27) -> 646.8 | I27: =AVERAGE(J23:J27) -> 557 | J27: =X27-W27 -> 587 | K27: =AVERAGE(X8:X27) -> 829.75 | L27: =AVERAGE(W8:W27) -> 133.5 | M27: =AVERAGE(W18:W27) -> 154.5 | N27: =AVERAGE(W23:W27) -> 159.8 | O27: =AVERAGE(R8:R27) -> 0.96368801 | P27: =AVERAGE(R18:R27) -> 1.0092046 | Q27: =AVERAGE(R23:R27) -> 1.5126074 | R27: =W27/W26-1 -> 8.05 | S27: =AVERAGE(V8:V27) -> 0.15763851 | T27: =AVERAGE(V18:V27) -> 0.18862471 | U27: =AVERAGE(V23:V27) -> 0.21216973 | V27: =W27/X27 -> 0.23567708 | W27: 181 | X27: 768 | Y27: 1401/07/30
D28: =S28/(1/G28) -> 117.14337 | E28: =T28/(1/H28) -> 120.39894 | F28: =U28/(1/I28) -> 118.17665 | G28: =AVERAGE(J9:J28) -> 687.8 | H28: =AVERAGE(J19:J28) -> 623.4 | I28: =AVERAGE(J24:J28) -> 556.8 | J28: =X28-W28 -> 549 | K28: =AVERAGE(X9:X28) -> 830.95 | L28: =AVERAGE(W9:W28) -> 143.15 | M28: =AVERAGE(W19:W28) -> 151.9 | N28: =AVERAGE(W24:W28) -> 159.8 | O28: =AVERAGE(R9:R28) -> 1.0143715 | P28: =AVERAGE(R19:R28) -> 0.99969474 | Q28: =AVERAGE(R24:R28) -> 1.4771357 | R28: =W28/W27-1 -> 0.16022099 | S28: =AVERAGE(V9:V28) -> 0.17031604 | T28: =AVERAGE(V19:V28) -> 0.19313273 | U28: =AVERAGE(V24:V28) -> 0.21224254 | V28: =W28/X28 -> 0.27667984 | W28: 210 | X28: 759 | Y28: 1401/08/01
D29: =S29/(1/G29) -> 118.50924 | E29: =T29/(1/H29) -> 121.20369 | F29: =U29/(1/I29) -> 118.45091 | G29: =AVERAGE(J10:J29) -> 676.8 | H29: =AVERAGE(J20:J29) -> 601.7 | I29: =AVERAGE(J25:J29) -> 551.4 | J29: =X29-W29 -> 546 | K29: =AVERAGE(X10:X29) -> 822.1 | L29: =AVERAGE(W10:W29) -> 145.3 | M29: =AVERAGE(W20:W29) -> 154.9 | N29: =AVERAGE(W25:W29) -> 160.6 | O29: =AVERAGE(R10:R29) -> 0.66780285 | P29: =AVERAGE(R20:R29) -> 1.0215874 | Q29: =AVERAGE(R25:R29) -> 1.4809452 | R29: =W29/W28-1 -> -0.16666667 | S29: =AVERAGE(V10:V29) -> 0.1751023 | T29: =AVERAGE(V20:V29) -> 0.20143541 | U29: =AVERAGE(V25:V29) -> 0.21481849 | V29: =W29/X29 -> 0.24271845 | W29: 175 | X29: 721 | Y29: 1401/08/02
D30: =S30/(1/G30) -> 117.14329 | E30: =T30/(1/H30) -> 122.09669 | F30: =U30/(1/I30) -> 101.70506 | G30: =AVERAGE(J11:J30) -> 665 | H30: =AVERAGE(J21:J30) -> 580.1 | I30: =AVERAGE(J26:J30) -> 546.2 | J30: =X30-W30 -> 526 | K30: =AVERAGE(X11:X30) -> 809.45 | L30: =AVERAGE(W11:W30) -> 144.45 | M30: =AVERAGE(W21:W30) -> 159.6 | N30: =AVERAGE(W26:W30) -> 134.2 | O30: =AVERAGE(R11:R30) -> 0.6534522 | P30: =AVERAGE(R21:R30) -> 1.0439519 | Q30: =AVERAGE(R26:R30) -> 1.3242869 | R30: =W30/W29-1 -> -0.51428571 | S30: =AVERAGE(V11:V30) -> 0.17615533 | T30: =AVERAGE(V21:V30) -> 0.21047524 | U30: =AVERAGE(V26:V30) -> 0.1862048 | V30: =W30/X30 -> 0.1391162 | W30: 85 | X30: 611 | Y30: 1401/08/03
D31: =S31/(1/G31) -> 118.93736 | E31: =T31/(1/H31) -> 120.73871 | F31: =U31/(1/I31) -> 126.03624 | G31: =AVERAGE(J12:J31) -> 653.75 | H31: =AVERAGE(J22:J31) -> 553.3 | I31: =AVERAGE(J27:J31) -> 550.6 | J31: =X31-W31 -> 545 | K31: =AVERAGE(X12:X31) -> 801.3 | L31: =AVERAGE(W12:W31) -> 147.55 | M31: =AVERAGE(W22:W31) -> 160.8 | N31: =AVERAGE(W27:W31) -> 166.6 | O31: =AVERAGE(R12:R31) -> 0.70168749 | P31: =AVERAGE(R22:R31) -> 0.81070116 | Q31: =AVERAGE(R27:R31) -> 1.734089 | R31: =W31/W30-1 -> 1.1411765 | S31: =AVERAGE(V12:V31) -> 0.18193095 | T31: =AVERAGE(V22:V31) -> 0.21821563 | U31: =AVERAGE(V27:V31) -> 0.22890709 | V31: =W31/X31 -> 0.25034388 | W31: 182 | X31: 727 | Y31: 1401/08/04
D32: =S32/(1/G32) -> 117.31528 | E32: =T32/(1/H32) -> 110.28376 | F32: =U32/(1/I32) -> 102.5503 | G32: =AVERAGE(J13:J32) -> 645.25 | H32: =AVERAGE(J23:J32) -> 550.1 | I32: =AVERAGE(J28:J32) -> 543.2 | J32: =X32-W32 -> 550 | K32: =AVERAGE(X13:X32) -> 792.4 | L32: =AVERAGE(W13:W32) -> 147.15 | M32: =AVERAGE(W23:W32) -> 147.1 | N32: =AVERAGE(W28:W32) -> 134.4 | O32: =AVERAGE(R13:R32) -> 0.69551533 | P32: =AVERAGE(R23:R32) -> 0.72933723 | Q32: =AVERAGE(R28:R32) -> -0.053932961 | R32: =W32/W31-1 -> -0.89010989 | S32: =AVERAGE(V13:V32) -> 0.18181368 | T32: =AVERAGE(V23:V32) -> 0.20047947 | U32: =AVERAGE(V28:V32) -> 0.18878922 | V32: =W32/X32 -> 0.035087719 | W32: 20 | X32: 570 | Y32: 1401/08/05
D33: =S33/(1/G33) -> 113.91873 | E33: =T33/(1/H33) -> 99.915274 | F33: =U33/(1/I33) -> 80.612349 | G33: =AVERAGE(J14:J33) -> 644.35 | H33: =AVERAGE(J24:J33) -> 570.8 | I33: =AVERAGE(J29:J33) -> 584.8 | J33: =X33-W33 -> 757 | K33: =AVERAGE(X14:X33) -> 786.95 | L33: =AVERAGE(W14:W33) -> 142.6 | M33: =AVERAGE(W24:W33) -> 127.8 | N33: =AVERAGE(W29:W33) -> 95.8 | O33: =AVERAGE(R14:R33) -> 0.54515819 | P33: =AVERAGE(R24:R33) -> 0.68057927 | Q33: =AVERAGE(R29:R33) -> -0.11597716 | R33: =W33/W32-1 -> -0.15 | S33: =AVERAGE(V14:V33) -> 0.17679636 | T33: =AVERAGE(V24:V33) -> 0.17504428 | U33: =AVERAGE(V29:V33) -> 0.13784601 | V33: =W33/X33 -> 0.021963824 | W33: 17 | X33: 774 | Y33: 1401/08/07
... D325: =S325/(1/G325) -> 78.304144 | E325: =T325/(1/H325) -> 80.986946 | F325: =U325/(1/I325) -> 77.797111 | G325: =AVERAGE(J306:J325) -> 205.75 | H325: =AVERAGE(J316:J325) -> 220.33 | I325: =AVERAGE(J321:J325) -> 207.48 | J325: =X325-W325 -> 234.5 | K325: =AVERAGE(X306:X325) -> 333.73 | L325: =AVERAGE(W306:W325) -> 127.98 | M325: =AVERAGE(W316:W325) -> 128.9 | N325: =AVERAGE(W321:W325) -> 125.18 | O325: =AVERAGE(R306:R325) -> 0.13856511 | P325: =AVERAGE(R316:R325) -> 0.081486382 | Q325: =AVERAGE(R321:R325) -> 0.036444256 | R325: =W325/W324-1 -> -0.075522589 | S325: =AVERAGE(V306:V325) -> 0.38057907 | T325: =AVERAGE(V316:V325) -> 0.36757113 | U325: =AVERAGE(V321:V325) -> 0.37496198 | V325: =W325/X325 -> 0.3689451 | W325: 137.1 | X325: 371.6 | Y325: 1402/10/26
D326: =S326/(1/G326) -> 79.255643 | E326: =T326/(1/H326) -> 83.527874 | F326: =U326/(1/I326) -> 83.71888 | G326: =AVERAGE(J307:J326) -> 207.12 | H326: =AVERAGE(J317:J326) -> 213.88 | I326: =AVERAGE(J322:J326) -> 196.34 | J326: =X326-W326 -> 149.3 | K326: =AVERAGE(X307:X326) -> 338.705 | L326: =AVERAGE(W307:W326) -> 131.585 | M326: =AVERAGE(W317:W326) -> 139.02 | N326: =AVERAGE(W322:W326) -> 149.28 | O326: =AVERAGE(R307:R326) -> 0.11200126 | P326: =AVERAGE(R317:R326) -> 0.10765197 | R326: =W326/W325-1 -> 0.68490153 | S326: =AVERAGE(V307:V326) -> 0.38265567 | T326: =AVERAGE(V317:V326) -> 0.39053616 | U326: =AVERAGE(V322:V326) -> 0.42639747 | V326: =W326/X326 -> 0.6074152 | W326: 231 | X326: 380.3 | Y326: 1402/10/27
D327: =S327/(1/G327) -> 79.497356 | E327: =T327/(1/H327) -> 83.856725 | F327: =U327/(1/I327) -> 88.326218 | G327: =AVERAGE(J308:J327) -> 210.27 | H327: =AVERAGE(J318:J327) -> 209.68 | I327: =AVERAGE(J323:J327) -> 196.34 | J327: =X327-W327 -> 205 | K327: =AVERAGE(X308:X327) -> 341.805 | L327: =AVERAGE(W308:W327) -> 131.535 | M327: =AVERAGE(W318:W327) -> 142.72 | N327: =AVERAGE(W323:W327) -> 165.28 | O327: =AVERAGE(R308:R327) -> 0.090963639 | P327: =AVERAGE(R318:R327) -> 0.064941577 | R327: =W327/W326-1 -> -0.086580087 | S327: =AVERAGE(V308:V327) -> 0.37807275 | T327: =AVERAGE(V318:V327) -> 0.39992715 | U327: =AVERAGE(V323:V327) -> 0.44986359 | V327: =W327/X327 -> 0.50721154 | W327: 211 | X327: 416 | Y327: 1402/10/30
D328: =S328/(1/G328) -> 80.950565 | E328: =T328/(1/H328) -> 83.56814 | F328: =U328/(1/I328) -> 91.585735 | G328: =AVERAGE(J309:J328) -> 213.37 | H328: =AVERAGE(J319:J328) -> 210.17 | I328: =AVERAGE(J324:J328) -> 204.34 | J328: =X328-W328 -> 240 | K328: =AVERAGE(X309:X328) -> 346.875 | L328: =AVERAGE(W309:W328) -> 133.505 | M328: =AVERAGE(W319:W328) -> 141.73 | N328: =AVERAGE(W324:W328) -> 168.36 | O328: =AVERAGE(R309:R328) -> 0.10038396 | P328: =AVERAGE(R319:R328) -> 0.047722805 | R328: =W328/W327-1 -> -0.45781991 | S328: =AVERAGE(V309:V328) -> 0.37939057 | T328: =AVERAGE(V319:V328) -> 0.39762164 | U328: =AVERAGE(V324:V328) -> 0.44820267 | V328: =W328/X328 -> 0.3227991 | W328: 114.4 | X328: 354.4 | Y328: 1402/11/03
D329: =S329/(1/G329) -> 80.669249 | E329: =T329/(1/H329) -> 83.808482 | F329: =U329/(1/I329) -> 90.018114 | G329: =AVERAGE(J310:J329) -> 211.865 | H329: =AVERAGE(J320:J329) -> 205.07 | I329: =AVERAGE(J325:J329) -> 203.56 | J329: =X329-W329 -> 189 | K329: =AVERAGE(X310:X329) -> 345.155 | L329: =AVERAGE(W310:W329) -> 133.29 | M329: =AVERAGE(W320:W329) -> 144.58 | N329: =AVERAGE(W325:W329) -> 164.4 | O329: =AVERAGE(R310:R329) -> 0.068013218 | P329: =AVERAGE(R320:R329) -> 0.079597457 | R329: =W329/W328-1 -> 0.12325175 | S329: =AVERAGE(V310:V329) -> 0.38075779 | T329: =AVERAGE(V320:V329) -> 0.40868231 | U329: =AVERAGE(V325:V329) -> 0.44221907 | V329: =W329/X329 -> 0.40472441 | W329: 128.5 | X329: 317.5 | Y329: 1402/11/04
D330: =S330/(1/G330) -> 80.458102 | E330: =T330/(1/H330) -> 81.422867 | F330: =U330/(1/I330) -> 84.745858 | G330: =AVERAGE(J311:J330) -> 213.12 | H330: =AVERAGE(J321:J330) -> 202.07 | I330: =AVERAGE(J326:J330) -> 196.66 | J330: =X330-W330 -> 200 | K330: =AVERAGE(X311:X330) -> 345.66 | L330: =AVERAGE(W311:W330) -> 132.54 | M330: =AVERAGE(W321:W330) -> 140.17 | N330: =AVERAGE(W326:W330) -> 155.16 | O330: =AVERAGE(R311:R330) -> 0.06351088 | P330: =AVERAGE(R321:R330) -> 0.015336756 | R330: =W330/W329-1 -> -0.292607 | S330: =AVERAGE(V311:V330) -> 0.37752488 | T330: =AVERAGE(V321:V330) -> 0.40294386 | U330: =AVERAGE(V326:V330) -> 0.43092575 | V330: =W330/X330 -> 0.31247851 | W330: 90.9 | X330: 290.9 | Y330: 1402/11/07
D331: =S331/(1/G331) -> 79.499114 | E331: =T331/(1/H331) -> 79.279115 | F331: =U331/(1/I331) -> 74.676846 | G331: =AVERAGE(J312:J331) -> 209.355 | H331: =AVERAGE(J322:J331) -> 199.2 | I331: =AVERAGE(J327:J331) -> 202.06 | J331: =X331-W331 -> 176.3 | K331: =AVERAGE(X312:X331) -> 341.345 | L331: =AVERAGE(W312:W331) -> 131.99 | M331: =AVERAGE(W322:W331) -> 136.7 | N331: =AVERAGE(W327:W331) -> 124.12 | O331: =AVERAGE(R312:R331) -> 0.064222991 | P331: =AVERAGE(R322:R331) -> 0.016873243 | R331: =W331/W330-1 -> -0.16611661 | S331: =AVERAGE(V312:V331) -> 0.37973354 | T331: =AVERAGE(V322:V331) -> 0.39798753 | U331: =AVERAGE(V327:V331) -> 0.36957758 | V331: =W331/X331 -> 0.30067434 | W331: 75.8 | X331: 252.1 | Y331: 1402/11/08
D332: =S332/(1/G332) -> 77.690092 | E332: =T332/(1/H332) -> 77.583795 | F332: =U332/(1/I332) -> 67.076928 | G332: =AVERAGE(J313:J332) -> 206.37 | H332: =AVERAGE(J323:J332) -> 193.98 | I332: =AVERAGE(J328:J332) -> 191.62 | J332: =X332-W332 -> 152.8 | K332: =AVERAGE(X313:X332) -> 334.045 | L332: =AVERAGE(W313:W332) -> 127.675 | M332: =AVERAGE(W323:W332) -> 134.2 | N332: =AVERAGE(W328:W332) -> 103.12 | O332: =AVERAGE(R313:R332) -> 0.023371946 | P332: =AVERAGE(R323:R332) -> 0.038162896 | R332: =W332/W331-1 -> 0.39841689 | S332: =AVERAGE(V313:V332) -> 0.3764602 | T332: =AVERAGE(V323:V332) -> 0.3999577 | U332: =AVERAGE(V328:V332) -> 0.35005181 | V332: =W332/X332 -> 0.40958269 | W332: 106 | X332: 258.8 | Y332: 1402/11/09
D333: =S333/(1/G333) -> 77.358178 | E333: =T333/(1/H333) -> 78.820733 | F333: =U333/(1/I333) -> 66.444984 | G333: =AVERAGE(J314:J333) -> 209.495 | H333: =AVERAGE(J324:J333) -> 200.85 | I333: =AVERAGE(J329:J333) -> 197.36 | J333: =X333-W333 -> 268.7 | K333: =AVERAGE(X314:X333) -> 334.92 | L333: =AVERAGE(W314:W333) -> 125.425 | M333: =AVERAGE(W324:W333) -> 133.54 | N333: =AVERAGE(W329:W333) -> 98.72 | O333: =AVERAGE(R314:R333) -> 0.031231422 | P333: =AVERAGE(R324:R333) -> 0.049760188 | R333: =W333/W332-1 -> -0.12830189 | S333: =AVERAGE(V314:V333) -> 0.36926026 | T333: =AVERAGE(V324:V333) -> 0.39243581 | U333: =AVERAGE(V329:V333) -> 0.33666895 | V333: =W333/X333 -> 0.2558848 | W333: 92.4 | X333: 361.1 | Y333: 1402/11/10
D334: =S334/(1/G334) -> 78.481409 | E334: =T334/(1/H334) -> 78.299044 | F334: =U334/(1/I334) -> 66.036895 | G334: =AVERAGE(J315:J334) -> 212.595 | H334: =AVERAGE(J325:J334) -> 207.72 | I334: =AVERAGE(J330:J334) -> 211.88 | J334: =X334-W334 -> 261.6 | K334: =AVERAGE(X315:X334) -> 339.185 | L334: =AVERAGE(W315:W334) -> 126.59 | M334: =AVERAGE(W325:W334) -> 128.87 | N334: =AVERAGE(W330:W334) -> 93.34 | O334: =AVERAGE(R315:R334) -> 0.057716328 | P334: =AVERAGE(R325:R334) -> 0.0099189183 | R334: =W334/W333-1 -> 0.0995671 | S334: =AVERAGE(V315:V334) -> 0.36915924 | T334: =AVERAGE(V325:V334) -> 0.37694514 | U334: =AVERAGE(V330:V334) -> 0.3116712 | V334: =W334/X334 -> 0.27973568 | W334: 101.6 | X334: 363.2 | Y334: 1402/11/11
D335: =S335/(1/G335) -> 79.599297 | E335: =T335/(1/H335) -> 78.148011 | F335: =U335/(1/I335) -> 70.422658 | G335: =AVERAGE(J316:J335) -> 213.745 | H335: =AVERAGE(J326:J335) -> 207.16 | I335: =AVERAGE(J331:J335) -> 217.66 | J335: =X335-W335 -> 228.9 | K335: =AVERAGE(X316:X335) -> 342.55 | L335: =AVERAGE(W316:W335) -> 128.805 | M335: =AVERAGE(W326:W335) -> 128.71 | N335: =AVERAGE(W331:W335) -> 102.26 | O335: =AVERAGE(R316:R335) -> 0.066161851 | P335: =AVERAGE(R326:R335) -> 0.050837319 | R335: =W335/W334-1 -> 0.33366142 | S335: =AVERAGE(V316:V335) -> 0.37240308 | T335: =AVERAGE(V326:V335) -> 0.37723504 | U335: =AVERAGE(V331:V335) -> 0.32354433 | V335: =W335/X335 -> 0.37184413 | W335: 135.5 | X335: 364.4 | Y335: 1402/11/14
D336: =S336/(1/G336) -> 78.684414 | E336: =T336/(1/H336) -> 73.885268 | F336: =U336/(1/I336) -> 72.693481 | G336: =AVERAGE(J317:J336) -> 212.815 | H336: =AVERAGE(J327:J336) -> 211.75 | I336: =AVERAGE(J332:J336) -> 221.44 | J336: =X336-W336 -> 195.2 | K336: =AVERAGE(X317:X336) -> 339.815 | L336: =AVERAGE(W317:W336) -> 127 | M336: =AVERAGE(W327:W336) -> 114.98 | N336: =AVERAGE(W332:W336) -> 105.84 | O336: =AVERAGE(R317:R336) -> 0.029575216 | P336: =AVERAGE(R327:R336) -> -0.048501543 | R336: =W336/W335-1 -> -0.30848708 | S336: =AVERAGE(V317:V336) -> 0.36973152 | T336: =AVERAGE(V327:V336) -> 0.34892689 | U336: =AVERAGE(V332:V336) -> 0.3282762 | V336: =W336/X336 -> 0.32433368 | W336: 93.7 | X336: 288.9 | Y336: 1402/11/15
D337: =S337/(1/G337) -> 77.518869 | E337: =T337/(1/H337) -> 71.249227 | F337: =U337/(1/I337) -> 75.225593 | G337: =AVERAGE(J318:J337) -> 208.465 | H337: =AVERAGE(J328:J337) -> 207.25 | I337: =AVERAGE(J333:J337) -> 222.88 | J337: =X337-W337 -> 160 | K337: =AVERAGE(X318:X337) -> 333.465 | L337: =AVERAGE(W318:W337) -> 125 | M337: =AVERAGE(W328:W337) -> 107.28 | N337: =AVERAGE(W333:W337) -> 111.44 | O337: =AVERAGE(R318:R337) -> 0.034053824 | P337: =AVERAGE(R328:R337) -> 0.003166071 | R337: =W337/W336-1 -> 0.43009605 | S337: =AVERAGE(V318:V337) -> 0.37185556 | T337: =AVERAGE(V328:V337) -> 0.34378396 | U337: =AVERAGE(V333:V337) -> 0.33751612 | V337: =W337/X337 -> 0.45578231 | W337: 134 | X337: 294 | Y337: 1402/11/16
... D370: =S370/(1/G370) -> 83.942015 | E370: =T370/(1/H370) -> 77.739134 | F370: =U370/(1/I370) -> 75.517348 | G370: =AVERAGE(J351:J370) -> 187.165 | H370: =AVERAGE(J361:J370) -> 220.28 | I370: =AVERAGE(J366:J370) -> 206.62 | J370: =X370-W370 -> 302 | K370: =AVERAGE(X351:X370) -> 336.005 | L370: =AVERAGE(W351:W370) -> 148.84 | M370: =AVERAGE(W361:W370) -> 111.84 | N370: =AVERAGE(W366:W370) -> 113.48 | O370: =AVERAGE(R351:R370) -> 0.083850316 | P370: =AVERAGE(R361:R370) -> 0.1080547 | R370: =W370/W369-1 -> 0.16963449 | S370: =AVERAGE(V351:V370) -> 0.44849205 | T370: =AVERAGE(V361:V370) -> 0.35291054 | U370: =AVERAGE(V366:V370) -> 0.36548905 | V370: =W370/X370 -> 0.29240862 | W370: 124.8 | X370: 426.8 | Y370: 1403/02/04

Sheet تراز تجاری 
S3: امار سایت گمرک- میلیارد دلار
F4: آمار صادرات و واردات غیر نفتی (داده گمرک- بدون احتساب صادرات چمدانی)
A5: پنج ماهه 1403 | B5: چهارماهه1403 | C5: سه ماهه1403 | D5: دو ماهه1403 | E5: یک ماه 1403 | F5: دوزاده ماه 1402 | G5: یازده ماه 1402 | H5: ده ماهه 1402 | I5: نه ماهه 1402 | J5: هشت ماهه 1402 | K5: هفت ماهه 1402 | L5: شش ماهه 1402 | M5: پنج ماهه 1402 | N5: چهار ماه 1402 | O5: سه ماهه 1402 | P5: دو ماهه 1402 | Q5: یک ماهه 1402 | R5: 1402 | S5: 1401 | T5: 1400 | U5: 1399 | V5: 1398 | W5: 1397 | X5: 1396 | Y5: 1395 | Z5: 1394 | AA5: 1393 | AB5: 1392 | AC5: شرح
A6: 21.9 | B6: 17.4 | C6: 13.5 | D6: 8.02 | E6: 3.17 | F6: =49329446425/1000000000 -> 49.329446 | G6: =44889615169.8203/1000000000 -> 44.889615 | H6: 36.43 | I6: 36.684 | J6: 32.243 | K6: =28344696441/1000000000 -> 28.344696 | L6: =24143676946/1000000000 -> 24.143677 | M6: =19341546535/1000000000 -> 19.341547 | N6: =15906358060/1000000000 -> 15.906358 | O6: =12462385366/1000000000 -> 12.462385 | P6: =7513428628/1000000000 -> 7.5134286 | Q6: =3645393431/1000000000 -> 3.6453934 | R6: =49329446425/1000000000 -> 49.329446 | S6: 54.139404 | T6: 48.44 | U6: 34.807 | V6: 41.423827 | W6: 44.670433 | X6: 46.982171 | Y6: 44.041765 | Z6: 44.041765 | AA6: 36.555198 | AB6: 31.552399 | AC6: صادرات (میلیارد دلار)
A7: 26.3 | B7: 19.4 | C7: 14.3 | D7: 9.07 | E7: 2.7 | F7: =66204006867.2595/1000000000 -> 66.204007 | G7: =59883755635.7003/1000000000 -> 59.883756 | H7: 48.35 | I7: 43.066 | J7: 42.199 | K7: 36.006041 | L7: =30442849403.1645/1000000000 -> 30.442849 | M7: =24188374944.2201/1000000000 -> 24.188375 | N7: =19538642625.801/1000000000 -> 19.538643 | O7: =14018532773.3004/1000000000 -> 14.018533 | P7: =7940520794.30424/1000000000 -> 7.9405208 | Q7: =3086672014.6531/1000000000 -> 3.086672 | R7: =66204006867.2595/1000000000 -> 66.204007 | S7: 60.308688 | T7: 52.996 | U7: 38.890281 | V7: 44.091577 | W7: 43.168759 | X7: 54.459213 | Y7: 43.683869 | Z7: 41.538521 | AA7: 53.569482 | AB7: 49.709303 | AC7: واردات (میلیارد دلار)
A8: =A6-A7 -> -4.4 | B8: =B6-B7 -> -2 | C8: =C6-C7 -> -0.8 | D8: =D6-D7 -> -1.05 | E8: =E6-E7 -> 0.47 | F8: =F6-F7 -> -16.87456 | G8: =G6-G7 -> -14.99414 | H8: =H6-H7 -> -11.92 | ... AB8: =AB6-AB7 -> -18.156903 | AC8: تراز تجاری
A9: =A11/1000000 -> 15687.909 | B9: =B11/1000000 -> 12591.626 | C9: =C11/1000000 -> 9388.6472 | D9: =D11/1000000 -> 5847.7959 | E9: =E11/1000000 -> 2439.9526 | F9: =F11/1000000 -> 39016.264 | G9: =G11/1000000 -> 35765.603 | H9: =H11/1000000 -> 32682.531 | ... AB9: =AB11/1000000 -> 33683.877 | AC9: واردات (میلیون تن)
A10: =A12/1000000 -> 60511.676 | B10: =B12/1000000 -> 47978.153 | C10: =C12/1000000 -> 37837.619 | D10: =D12/1000000 -> 23459.915 | E10: =E12/1000000 -> 9684.1988 | F10: =F12/1000000 -> 136408.84 | G10: =G12/1000000 -> 124755.98 | H10: =H12/1000000 -> 113050.8 | ... AB10: =AB12/1000000 -> 81102.908 | AC10: صادرات (میلیون تن)
A11: 1.5687909e+10 | B11: 12591626421 | C11: 9.3886472e+09 | D11: 5.8477959e+09 | E11: 2439952555 | F11: 3.9016264e+10 | G11: 3.5765603e+10 | H11: 3.2682531e+10 | I11: 2.873688e+10 | J11: 2.4709006e+10 | K11: 2.0915921e+10 | L11: 1.7609098e+10 | M11: 1.4422806e+10 | N11: 1.1841827e+10 | O11: 8.5569595e+09 | P11: 4.7316111e+09 | Q11: 1.8293426e+09 | R11: 3.9016264e+10 | S11: 3.7358195e+10 | T11: 4.1193221e+10 | U11: 33729541567 | V11: 3.5824818e+10 | W11: 3.2355759e+10 | X11: 3.8855736e+10 | Y11: 33299000000 | Z11: 3.5152105e+10 | AA11: 4.3015789e+10 | AB11: 3.3683877e+10 | AC11: واردات (کیلوگرم)
A12: 60511676119 | B12: 47978152523 | C12: 37837618745 | D12: 23459914616 | E12: 9684198795 | F12: 136408840391 | G12: 1.2475598e+11 | H12: 113050798587 | I12: 1.0190438e+11 | J12: 90044118504 | K12: 79490184880 | L12: 67733553229 | M12: 55910040040 | N12: 45757669223 | O12: 35494527150 | P12: 20999543515 | Q12: 10470775718 | R12: 136408840391 | S12: 124251546127 | T12: 122416874662 | U12: 113189417306 | V12: 1.3433121e+11 | W12: 1.1796764e+11 | X12: 1.3288176e+11 | Y12: 129892000000 | Z12: 9.3906989e+10 | AA12: 8.1634488e+10 | AB12: 8.1102908e+10 | AC12: صادرات(کیلوگرم)
A13: =A10-A9 -> 44823.768 | B13: =B10-B9 -> 35386.526 | C13: =C10-C9 -> 28448.972 | D13: =D10-D9 -> 17612.119 | E13: =E10-E9 -> 7244.2462 | F13: =F10-F9 -> 97392.576 | G13: =G10-G9 -> 88990.38 | H13: =H10-H9 -> 80368.268 | ... AB13: =AB10-AB9 -> 47419.031 | AC13: تراز تجاری ( هزار تن)
S17: آمار اتاق بازرگانی- میلیارد دلار
G18: 1402 | H18: 1401 | I18: 1400 | J18: 1399 | K18: 1398 | L18: 1397 | M18: 1396 | N18: 1395 | O18: 1394 | P18: 1393 | Q18: 1392 | R18: 1391 | S18: 1390 | T18: 1389 | U18: 1388 | V18: شرح
G19: =49329446425/1000000000 -> 49.329446 | H19: 52.999956 | I19: 48.169253 | J19: 24.48945 | K19: 0 | L19: 44.300594 | M19: 46.773679 | N19: 43.837103 | O19: 32.61614 | P19: 36.538669 | Q19: 31.239468 | R19: 31.86688 | S19: 33.80524 | T19: 26.548624 | U19: 21.88731 | V19: صادرات
G20: =66204006867.2595/1000000000 -> 66.204007 | H20: 59.521593 | I20: 52.938473 | J20: 38.800863 | K20: 0 | L20: 41.236168 | M20: 51.612282 | N20: 42.701475 | O20: 33.769861 | P20: 44.987828 | Q20: 48.138749 | R20: 51.457988 | S20: 57.487546 | T20: 23.967098 | U20: 54.889534 | V20: واردات
G21: =(G19-G20)/1000000000 -> -1.687456e-08 | H21: -6.5216369 | I21: -4.7692205 | J21: -14.311413 | K21: 0 | L21: 3.0644252 | M21: -4.8386032 | N21: 1.135628 | O21: -1.153721 | P21: -8.4491599 | Q21: -16.899281 | R21: -19.591109 | S21: -23.682307 | T21: 2.5815252 | U21: -33.002224 | V21: تراز تجاری
L24: آمار اتاق بازرگانی | M24: دلار
G25: 1402 | H25: 1401 | I25: 1400 | J25: 1399 | K25: 1398 | L25: 1397 | M25: 1396 | N25: 1395 | O25: 1394 | P25: 1393 | Q25: 1392 | R25: 1391 | S25: 1390 | T25: 1389 | U25: 1388 | V25: شرح
H26: 52999955953 | I26: 48169252889 | J26: 24489449951 | L26: 44300593601 | M26: 46773679196 | N26: 43837103086 | O26: 32616139751 | P26: 36538668512 | Q26: 31239468246 | R26: 31866879659 | S26: 33805239741 | T26: 26548623533 | U26: 21887309569 | V26: صادرات
H27: 59521592893 | I27: 52938473430 | J27: 38800862525 | L27: 41236168446 | M27: 51612282367 | N27: 42701475123 | O27: 33769860792 | P27: 44987828401 | Q27: 48138749461 | R27: 51457988435 | S27: 57487546346 | T27: 23967098352 | U27: 54889533895 | V27: واردات
H28: 122045471683 | I28: 122402988205 | J28: 76864854184 | L28: 117226187800 | M28: 132295469805 | N28: 129646357433 | O28: 75493640599 | P28: 81631906393 | Q28: 80141664806 | R28: 69933874342 | S28: 66427558221 | T28: 60197457807 | U28: 47500966791 | V28: صادرات (وزنی- کیلوگرم)
H29: 37178639500 | I29: 41192176322 | J29: 33734126785 | L29: 30180774634 | M29: 34411049322 | N29: 31817237533 | O29: 29636099923 | P29: 37587097690 | Q29: 32724531430 | R29: 38568361554 | S29: 35191839396 | T29: 23728889750 | U29: 51913726607 | V29: واردات (وزنی- کیلوگرم)
G30: =(G26-G27)/1000000000 -> 0 | H30: =(H26-H27)/1000000000 -> -6.5216369 | I30: =(I26-I27)/1000000000 -> -4.7692205 | J30: =(J26-J27)/1000000000 -> -14.311413 | K30: =(K26-K27)/1000000000 -> 0 | L30: =(L26-L27)/1000000000 -> 3.0644252 | M30: =(M26-M27)/1000000000 -> -4.8386032 | N30: =(N26-N27)/1000000000 -> 1.135628 | ... U30: =(U26-U27)/1000000000 -> -33.002224 | V30: تراز تجاری
AB36: نه ماهه 1402
X37: سهم از کل واردات | Y37: میلیارد دلار | Z37: مبادی وارداتی | AA37: سهم از کل صادرات | AB37: میلیارد دلار | AC37: مقاصد صادراتی
X38: =Y38/$I$7 -> 0.34851159 | Y38: 15.009 | Z38: امارات | AA38: =AB38/$I$6 -> 0.28110348 | AB38: 10.312 | AC38: چین
X39: =Y39/$I$7 -> 0.31909163 | Y39: 13.742 | Z39: چین | AA39: =AB39/$I$6 -> 0.1886381 | AB39: 6.92 | AC39: عراق
X40: =Y40/$I$7 -> 0.12225421 | Y40: 5.265 | Z40: ترکیه | AA40: =AB40/$I$6 -> 0.12812125 | AB40: 4.7 | AC40: امارات
X41: =Y41/$I$7 -> 0.037129058 | Y41: 1.599 | Z41: آلمان | AA41: =AB41/$I$6 -> 0.088948861 | AB41: 3.263 | AC41: ترکیه
X42: =Y42/$I$7 -> 0.033158408 | Y42: 1.428 | Z42: هند | AA42: =AB42/$I$6 -> 0.045060517 | AB42: 1.653 | AC42: هند

Sheet bop
B1: تراز حساب جاری (حساب جاری) ◄ تراز بازرگانی (حساب کالا) ◄ صادرات ▼ استاندارد 4 | C1: تراز حساب جاری (حساب جاری) ◄ تراز بازرگانی (حساب کالا) ◄ صادرات- استاندارد 4 | D1: تراز حساب جاری (حساب جاری) ◄ تراز بازرگانی (حساب کالا) ◄ صادرات- استاندارد 4 | E1: حساب جاری ◄ حساب کالا ◄ صادرات کالا (فوب) ▼ استاندارد 5 | F1: حساب جاری ◄ حساب کالا ◄ صادرات کالا (فوب) ▼ استاندارد 5 | G1: حساب جاری ◄ حساب کالا ◄ صادرات کالا (فوب) ▼ استاندارد 5 | H1: حساب کالا (میلیون دلار) | K1: خالص حساب کالا (میلیون دلار) | L1: بخش خارجي/ موازنه پرداخت ها/ استاندارد شماره 5 | M1: بخش خارجي/ موازنه پرداخت ها/ استاندارد شماره 5 | N1: بخش خارجي/ موازنه پرداخت ها/ استاندارد شماره 5 | O1: محاسباتی | P1: محاسباتی | Q1: محاسباتی | R1: توانگر | S1: بخش خارجی ◄ موازنه پرداخت ها ◄ استاندارد شماره 4 ▼ | T1: بخش خارجی ◄ موازنه پرداخت ها ◄ استاندارد شماره 4 ▼ | U1: بخش خارجی ◄ موازنه پرداخت ها ◄ استاندارد شماره 4 ▼ | V1: بخش انرژی ◄ نفت ▼ | W1: بخش انرژی ◄ نفت ▼ | X1: بخش انرژی ◄ نفت ▼ | Y1: بخش انرژی ◄ نفت ▼ | Z1: بخش انرژی ◄ نفت ◄ مصرف فرآورده های نفتی ▼ | AA1: بخش انرژی ◄ نفت ◄ مصرف فرآورده های نفتی ▼ | AB1: بخش انرژی ◄ نفت ◄ مصرف فرآورده های نفتی ▼ | AC1: بخش انرژی ◄ نفت ◄ مصرف فرآورده های نفتی ▼ | AD1: بخش انرژی ◄ نفت ◄ مصرف فرآورده های نفتی ▼ | AE1: بخش انرژی ◄ گاز طبیعی ◄ تولید گاز ▼ | AF1: بخش انرژی ◄ گاز طبیعی ◄ تولید گاز ▼ | AG1: بخش انرژی ◄ گاز طبیعی ◄ تولید گاز ▼ | AH1: بخش انرژی ◄ گاز طبیعی ◄ تولید گاز ▼ | AI1: بخش انرژی ◄ گاز طبیعی ▼
A2: سال | B2: صادرات نفت و گاز (ميليون دلار) | C2: صادرات غیرنفتی (ميليون دلار) _با احتساب میعانات | D2: صادرات (نفتی و غیرنفتی) | E2: صادرات نفتی (ميليون دلار) - شامل میعانات و گاز است | F2: صادرات غیرنفتی (ميليون دلار) | G2: صادرات کالا- فوب (نفتی و غیرنفتی) | H2: واردات کالا (فوب) | I2: گاز و فرآورده‌هاي نفتي (2) | J2: ساير کالاها | L2: حساب مالي و سرمايه (ميليون دلار) | M2: حساب جاري (ميليون دلار) | N2: اشتباهات و از قلم افتادگي (ميليون دلار) | O2: صادرات گاز طبیعی و میعانات نفتی و گازی | P2: صادرات میعانات (ميليون دلار) | Q2: صادرات نفت (ميليون دلار) | R2: صادرات گاز (ميليون دلار) | S2: موازنه کل(تغییر در ذخایر بین المللی) (ميليون دلار) | T2: تراز حساب جاری (حساب جاری) (ميليون دلار) | U2: تراز حساب سرمایه (حساب مالی و سرمایه) (ميليون دلار) | V2: تولید نفت خام (هزار بشکه در روز) | W2: صادرات نفت خام (هزار بشکه در روز) | X2: واردات فرآورده (هزار بشکه در روز) | Y2: مصرف فرآورده های نفتی (هزار بشکه در روز) | Z2: نفت گاز (هزار بشکه در روز) | AA2: نفت کوره (هزار بشکه در روز) | AB2: بنزین موتور (هزار بشکه در روز) | AC2: نفت سفید (هزار بشکه در روز) | AD2: سایر فرآورده ها (هزار بشکه در روز) | AE2: تولید (ميليارد مترمکعب) | AF2: مصرف داخلی (ميليارد مترمکعب) | AG2: صادرات (ميليارد مترمکعب) | AH2: سایر (ميليارد مترمکعب) | AI2: واردات گاز (ميليارد مترمکعب)
A3: 1338 | B3: NA | C3: NA | E3: NA | F3: NA | S3: NA | T3: NA | U3: NA | V3: NA | W3: NA | X3: NA | Y3: NA | Z3: NA | AA3: NA | AB3: NA | AC3: NA | AD3: NA | AE3: NA | AF3: NA | AG3: NA | AH3: NA | AI3: NA
A4: 1339 | B4: NA | C4: NA | E4: NA | F4: NA | S4: NA | T4: NA | U4: NA | V4: NA | W4: NA | X4: NA | Y4: NA | Z4: NA | AA4: NA | AB4: NA | AC4: NA | AD4: NA | AE4: NA | AF4: NA | AG4: NA | AH4: NA | AI4: NA
A5: 1340 | B5: NA | C5: NA | E5: NA | F5: NA | S5: NA | T5: NA | U5: NA | V5: NA | W5: NA | X5: NA | Y5: NA | Z5: NA | AA5: NA | AB5: NA | AC5: NA | AD5: NA | AE5: NA | AF5: NA | AG5: NA | AH5: NA | AI5: NA
A6: 1341 | B6: NA | C6: NA | E6: NA | F6: NA | S6: NA | T6: NA | U6: NA | V6: NA | W6: NA | X6: NA | Y6: NA | Z6: NA | AA6: NA | AB6: NA | AC6: NA | AD6: NA | AE6: NA | AF6: NA | AG6: NA | AH6: NA | AI6: NA
A7: 1342 | B7: NA | C7: NA | E7: NA | F7: NA | S7: NA | T7: NA | U7: NA | V7: NA | W7: NA | X7: NA | Y7: NA | Z7: NA | AA7: NA | AB7: NA | AC7: NA | AD7: NA | AE7: NA | AF7: NA | AG7: NA | AH7: NA | AI7: NA
A8: 1343 | B8: NA | C8: NA | E8: NA | F8: NA | S8: NA | T8: NA | U8: NA | V8: NA | W8: NA | X8: NA | Y8: NA | Z8: NA | AA8: NA | AB8: NA | AC8: NA | AD8: NA | AE8: NA | AF8: NA | AG8: NA | AH8: NA | AI8: NA
A9: 1344 | B9: NA | C9: NA | E9: NA | F9: NA | S9: NA | T9: NA | U9: NA | V9: NA | W9: NA | X9: NA | Y9: NA | Z9: NA | AA9: NA | AB9: NA | AC9: NA | AD9: NA | AE9: NA | AF9: NA | AG9: NA | AH9: NA | AI9: NA
A10: 1345 | B10: NA | C10: NA | E10: NA | F10: NA | S10: NA | T10: NA | U10: NA | V10: NA | W10: NA | X10: NA | Y10: NA | Z10: NA | AA10: NA | AB10: NA | AC10: NA | AD10: NA | AE10: NA | AF10: NA | AG10: NA | AH10: NA | AI10: NA
A11: 1346 | B11: NA | C11: NA | E11: NA | F11: NA | S11: NA | T11: NA | U11: NA | V11: NA | W11: NA | X11: NA | Y11: NA | Z11: NA | AA11: NA | AB11: NA | AC11: NA | AD11: NA | AE11: NA | AF11: NA | AG11: NA | AH11: NA | AI11: NA
A12: 1347 | B12: NA | C12: NA | E12: NA | F12: NA | S12: NA | T12: NA | U12: NA | V12: NA | W12: NA | X12: NA | Y12: NA | Z12: NA | AA12: NA | AB12: NA | AC12: NA | AD12: NA | AE12: NA | AF12: NA | AG12: NA | AH12: NA | AI12: NA
A13: 1348 | B13: NA | C13: NA | E13: NA | F13: NA | S13: NA | T13: NA | U13: NA | V13: NA | W13: NA | X13: NA | Y13: NA | Z13: NA | AA13: NA | AB13: NA | AC13: NA | AD13: NA | AE13: NA | AF13: NA | AG13: NA | AH13: NA | AI13: NA
A14: 1349 | B14: NA | C14: NA | E14: NA | F14: NA | S14: NA | T14: NA | U14: NA | V14: NA | W14: NA | X14: NA | Y14: NA | Z14: NA | AA14: NA | AB14: NA | AC14: NA | AD14: NA | AE14: NA | AF14: NA | AG14: NA | AH14: NA | AI14: NA
... A16: 1351 | B16: NA | C16: NA | E16: NA | F16: NA | S16: NA | T16: NA | U16: NA | V16: NA | W16: NA | X16: NA | Y16: NA | Z16: NA | AA16: NA | AB16: NA | AC16: NA | AD16: NA | AE16: NA | AF16: NA | AG16: NA | AH16: NA | AI16: NA
A17: 1352 | B17: 8318 | C17: 635 | D17: =B17+C17 -> 8953 | E17: NA | F17: NA | S17: 996 | T17: 3555 | U17: -2180 | V17: 5942 | W17: 5320 | X17: NA | Y17: 277.7 | Z17: 81.1 | AA17: 69.9 | AB17: 34.2 | AC17: 60.8 | AD17: 23.6 | AE17: 48.7 | AF17: 12.1 | AG17: 8.6 | AH17: 28 | AI17: 0
A18: 1353 | B18: 21014 | C18: 582 | D18: =B18+C18 -> 21596 | E18: NA | F18: NA | S18: 5184 | T18: 11793 | U18: -4699 | V18: 5904 | W18: 5244 | X18: NA | Y18: 320.3 | Z18: 91.8 | AA18: 80.3 | AB18: 42.7 | AC18: 67.7 | AD18: 27.4 | AE18: 49.3 | AF18: 12.8 | AG18: 9.2 | AH18: 27.3 | AI18: 0
A19: 1354 | B19: 20034 | C19: 592 | D19: =B19+C19 -> 20626 | E19: NA | F19: NA | S19: -689 | T19: 4360 | U19: -3471 | V19: 5249 | W19: 4607 | X19: NA | Y19: 380 | Z19: 110.6 | AA19: 89.1 | AB19: 53.6 | AC19: 81.1 | AD19: 33 | AE19: 44.6 | AF19: 12.3 | AG19: 9.6 | AH19: 22.7 | AI19: 0
A20: 1355 | B20: 24179 | C20: 540 | D20: =B20+C20 -> 24719 | E20: NA | F20: NA | S20: 2784 | T20: 7233 | U20: -3953 | V20: 6019 | W20: 5280 | X20: NA | Y20: 444 | Z20: 128.7 | AA20: 101.1 | AB20: 68 | AC20: 90.7 | AD20: 40.8 | AE20: 52.3 | AF20: 14 | AG20: 9.3 | AH20: 29 | AI20: 0
A21: 1356 | B21: 23451 | C21: 523 | D21: =B21+C21 -> 23974 | E21: NA | F21: NA | S21: 1831 | T21: 3037 | U21: -1274 | V21: 5586 | W21: 4816 | X21: NA | Y21: 510.4 | Z21: 155.9 | AA21: 109.3 | AB21: 79.7 | AC21: 102.2 | AD21: 48.5 | AE21: 59.5 | AF21: 23.9 | AG21: 9.2 | AH21: 26.4 | AI21: 0
A22: 1357 | B22: 15660 | C22: 543 | D22: =B22+C22 -> 16203 | E22: NA | F22: NA | S22: -169 | T22: -1353 | U22: 1760 | V22: 4252 | W22: 3455 | X22: 10.7 | Y22: 522.5 | Z22: 165.6 | AA22: 106.5 | AB22: 87.7 | AC22: 103.8 | AD22: 44 | AE22: 44.4 | AF22: 16.6 | AG22: 5.3 | AH22: 22.5 | AI22: 0
A23: 1358 | B23: 24158 | C23: 812 | D23: =B23+C23 -> 24970 | E23: NA | F23: NA | S23: 3643 | T23: 12784 | U23: -6974 | V23: 3433 | W23: 2632 | X23: 10.1 | Y23: 548.9 | Z23: 161.6 | AA23: 111.9 | AB23: 98 | AC23: 126 | AD23: 33.9 | AE23: 41.7 | AF23: 21.4 | AG23: 3.5 | AH23: 16.8 | AI23: 0
A24: 1359 | B24: 11648 | C24: 645 | D24: =B24+C24 -> 12293 | E24: NA | F24: NA | S24: -3590 | T24: -2740 | U24: -906 | V24: 1476 | W24: 770 | X24: 8.2 | Y24: 523.9 | Z24: 159.5 | AA24: 132.3 | AB24: 82.6 | AC24: 98.1 | AD24: 34.7 | AE24: 16.6 | AF24: 9.4 | AG24: 0 | AH24: 7.2 | AI24: 0
A25: 1360 | B25: 10619 | C25: 340 | D25: =B25+C25 -> 10959 | E25: NA | F25: NA | S25: -2501 | T25: -4815 | U25: 2069 | V25: 1441 | W25: 791 | X25: 56.6 | Y25: 542.5 | Z25: 173 | AA25: 153.6 | AB25: 76.3 | AC25: 88.3 | AD25: 34.6 | AE25: 15.7 | AF25: 9.7 | AG25: 0 | AH25: 6 | AI25: 0
A26: 1361 | B26: 21798 | C26: 284 | D26: =B26+C26 -> 22082 | E26: NA | F26: NA | S26: 574 | T26: 7368 | U26: -7730 | V26: 2684 | W26: 1686 | X26: 83 | Y26: 581.4 | Z26: 196.3 | AA26: 147.4 | AB26: 78.3 | AC26: 106.4 | AD26: 34.6 | AE26: 30.4 | AF26: 18 | AG26: 0 | AH26: 12.4 | AI26: 0
A27: 1362 | B27: 21150 | C27: 357 | D27: =B27+C27 -> 21507 | E27: NA | F27: NA | S27: 1234 | T27: 358 | U27: 16 | V27: 2709 | W27: 2045 | X27: 154.7 | Y27: 719.7 | Z27: 237.8 | AA27: 175.1 | AB27: 102.4 | AC27: 136.4 | AD27: 43.6 | AE27: 27.8 | AF27: 15.5 | AG27: 0 | AH27: 12.3 | AI27: 0
A28: 1363 | B28: 16726 | C28: 361 | D28: =B28+C28 -> 17087 | E28: NA | F28: NA | S28: -4838 | T28: 1924 | U28: -5102 | V28: 2371 | W28: 1607 | X28: 101.9 | Y28: 779.3 | Z28: 258.4 | AA28: 197.4 | AB28: 113.9 | AC28: 133.6 | AD28: 48.2 | AE28: 30.9 | AF28: 21.5 | AG28: 0 | AH28: 9.4 | AI28: 0
A29: 1364 | B29: 13710 | C29: 465 | D29: =B29+C29 -> 14175 | E29: NA | F29: NA | S29: 1012 | T29: -476 | U29: 542 | V29: 2504 | W29: 1460 | X29: 165.4 | Y29: 848.2 | Z29: 298.7 | AA29: 198.7 | AB29: 123.9 | AC29: 147.2 | AD29: 47.3 | AE29: 34.4 | AF29: 24.1 | AG29: 0 | AH29: 10.3 | AI29: 0
A30: 1365 | B30: 6255 | C30: 916 | D30: =B30+C30 -> 7171 | E30: NA | F30: NA | S30: -1172 | T30: -5155 | U30: 2172 | V30: 2176 | W30: 1250 | X30: 148.4 | Y30: 788.8 | Z30: 279.9 | AA30: 213.4 | AB30: 116.2 | AC30: 103.3 | AD30: 42.5 | AE30: 25.3 | AF30: 15.6 | AG30: 0 | AH30: 9.7 | AI30: 0
A31: 1366 | B31: 10755 | C31: 1161 | D31: =B31+C31 -> 11916 | E31: NA | F31: NA | S31: -191 | T31: -2090 | U31: 1068 | V31: 2460 | W31: 1546 | X31: 191.2 | Y31: 805.7 | Z31: 293.9 | AA31: 186.5 | AB31: 121.3 | AC31: 126.4 | AD31: 43.9 | AE31: 30.9 | AF31: 20.3 | AG31: 0 | AH31: 10.6 | AI31: 0
A32: 1367 | B32: 9673 | C32: 1036 | D32: =B32+C32 -> 10709 | E32: NA | F32: NA | S32: -956 | T32: -1869 | U32: 320 | V32: 2557 | W32: 1647 | X32: 183 | Y32: 839.4 | Z32: 298.8 | AA32: 205.9 | AB32: 128.5 | AC32: 122.5 | AD32: 45.3 | AE32: 30.7 | AF32: 20.2 | AG32: 0 | AH32: 10.5 | AI32: 0
A33: 1368 | B33: 12037 | C33: 1044 | D33: =B33+C33 -> 13081 | E33: NA | F33: NA | S33: 2329 | T33: -191 | U33: 3261 | V33: 2947 | W33: 1823 | X33: 131.4 | Y33: 881.1 | Z33: 302.5 | AA33: 203.7 | AB33: 153.3 | AC33: 131.1 | AD33: 47.8 | AE33: 32.2 | AF33: 21.3 | AG33: 0 | AH33: 10.9 | AI33: 0
... A40: 1375 | B40: 19271 | C40: 3120 | D40: =B40+C40 -> 22391 | E40: NA | F40: NA | S40: 943 | T40: 5232 | U40: -5508 | V40: 3610 | W40: 2441 | X40: 76.7 | Y40: 1155 | Z40: 390 | AA40: 263 | AB40: 201 | AC40: 187 | AD40: 59 | AE40: 64.2 | AF40: 42.4 | AG40: 0 | AH40: 21.8 | AI40: 0
A41: 1376 | B41: 15471.3 | C41: 3131.01 | D41: =B41+C41 -> 18602.31 | E41: 15931.9 | F41: 2670.4 | G41: =F41+E41 -> 18602.3 | L41: -1882.567 | M41: 2110.7653 | N41: -228.19838 | O41: =E41-B41 -> 460.6 | S41: -4038.1 | T41: 2110.8 | U41: -5920.7 | V41: 3623 | W41: 2342 | X41: 67.9 | Y41: 1161 | Z41: 405 | AA41: 230 | AB41: 220 | AC41: 183 | AD41: 65 | AE41: 69.5 | AF41: 47.6 | AG41: 0 | AH41: 21.9 | AI41: 0.4
A42: 1377 | B42: 9933 | C42: 3171.22 | D42: =B42+C42 -> 13104.22 | E42: 10659.2 | F42: 2445 | G42: =F42+E42 -> 13104.2 | L42: 4125.2036 | M42: -3884.0456 | N42: -241.15799 | O42: =E42-B42 -> 726.2 | S42: -1548.2 | T42: -3884 | U42: 2577 | V42: 3666 | W42: 2300 | X42: 23.9 | Y42: 1251 | Z42: 376 | AA42: 310 | AB42: 212 | AC42: 174 | AD42: 135 | AE42: 72.5 | AF42: 51.5 | AG42: 0 | AH42: 21 | AI42: 1.9
A43: 1378 | B43: 17089 | C43: 3793.34 | D43: =B43+C43 -> 20882.34 | E43: 17976.9 | F43: 2905.4 | G43: =F43+E43 -> 20882.3 | L43: -8160.1742 | M43: 5080.3663 | N43: 3079.8079 | O43: =E43-B43 -> 887.9 | S43: 2116.6 | T43: 5080.4 | U43: -6043.5 | V43: 3373 | W43: 2079 | X43: 21.4 | Y43: 1131 | Z43: 364 | AA43: 225 | AB43: 212 | AC43: 157 | AD43: 130 | AE43: 80 | AF43: 58.7 | AG43: 0 | AH43: 21.3 | AI43: 2.1
A44: 1379 | B44: 24279.9 | C44: 4194.69 | D44: =B44+C44 -> 28474.59 | E44: 24955.2 | F44: 3519.4 | G44: =F44+E44 -> 28474.6 | L44: -10898.03 | M44: 9271.2585 | N44: 1626.7716 | O44: =E44-B44 -> 675.3 | S44: 7008.7 | T44: 9271.3 | U44: -3889.3 | V44: 3660 | W44: 2345 | X44: 33.3 | Y44: 1099 | Z44: 348 | AA44: 231 | AB44: 202 | AC44: 151 | AD44: 125 | AE44: 83.2 | AF44: 62.8 | AG44: 0 | AH44: 20.4 | AI44: 3.3
A45: 1380 | B45: 19338.64 | C45: 4649.82 | D45: =B45+C45 -> 23988.46 | E45: 20152.6 | F45: 3835.9 | G45: =F45+E45 -> 23988.5 | L45: -1473.5494 | M45: 1730.7309 | N45: -257.18154 | O45: =E45-B45 -> 813.96 | P45: =O45-R45 -> 767.56 | Q45: =B45-R45 -> 19292.24 | R45: 46.4 | S45: 3768.6 | T45: 1730.7 | U45: 2295 | V45: 3574 | W45: 2208 | X45: 49.1 | Y45: 1132 | Z45: 362 | AA45: 208 | AB45: 226 | AC45: 161 | AD45: 123 | AE45: 86.5 | AF45: 67.2 | AG45: 0.356 | AH45: 18.8 | AI45: 4.5
A46: 1381 | B46: 22965.6 | C46: 5144 | D46: =B46+C46 -> 28109.6 | E46: 23784.9 | F46: 4324.7 | G46: =F46+E46 -> 28109.6 | L46: -1760.7225 | M46: 1919.894 | N46: -159.1715 | O46: =E46-B46 -> 819.3 | P46: =O46-R46 -> 644.1 | Q46: =B46-R46 -> 22790.4 | R46: 175.2 | S46: 2946.4 | T46: 1919.9 | U46: 1185.7 | V46: 3305 | W46: 2021 | X46: 65.4 | Y46: 1049 | Z46: 343 | AA46: 151 | AB46: 237 | AC46: 149 | AD46: 115 | AE46: 96.1 | AF46: 76 | AG46: 1.3 | AH46: 18.8 | AI46: 5.3
A47: 1382 | B47: 27355.02 | C47: 6636.65 | D47: =B47+C47 -> 33991.67 | E47: 28407 | F47: 5584.7 | G47: =F47+E47 -> 33991.7 | L47: 553.98111 | M47: -621.85723 | N47: 67.876113 | O47: =E47-B47 -> 1051.98 | P47: =O47-R47 -> 566.98 | Q47: =B47-R47 -> 26870.02 | R47: 485 | S47: 2636.4 | T47: -621.9 | U47: 3190.4 | V47: 3736 | W47: 2396 | X47: 95 | Y47: oo | Z47: 359 | AA47: 145 | AB47: 276 | AC47: 154 | AD47: NA | AE47: 115.4 | AF47: 86.6 | AG47: 3.4 | AH47: 25.4 | AI47: 5.7
A48: 1383 | B48: 36314.74 | C48: 7519.86 | D48: =B48+C48 -> 43834.6 | E48: 37448.2 | F48: 6386.4 | G48: =F48+E48 -> 43834.6 | L48: -464.48937 | M48: -216.18286 | N48: 680.67223 | O48: =E48-B48 -> 1133.46 | P48: =O48-R48 -> 594.46 | Q48: =B48-R48 -> 35775.74 | R48: 539 | S48: 6644.1 | T48: -216.2 | U48: 6179.7 | V48: 3834 | W48: 2548 | X48: 142.8 | Y48: 1216 | Z48: 348 | AA48: 178 | AB48: 335 | AC48: 174 | AD48: 127 | AE48: 119.4 | AF48: 97.7 | AG48: 3.5 | AH48: 24.1 | AI48: 5.9
A49: 1384 | B49: 53819.7 | C49: 10705.09 | D49: =B49+C49 -> 64524.79 | E49: 55790.7 | F49: 8734.1 | G49: =F49+E49 -> 64524.8 | L49: -14730.614 | M49: 15391.653 | N49: -661.03836 | O49: =E49-B49 -> 1971 | P49: =O49-R49 -> 882 | Q49: =B49-R49 -> 52730.7 | R49: 1089 | S49: 14566.6 | T49: 15391.7 | U49: -164 | V49: 4106 | W49: 2602 | X49: 155.9 | Y49: 1176 | Z49: 417 | AA49: 218 | AB49: 373 | AC49: 169 | AD49: 153 | AE49: 130.6 | AF49: 106.7 | AG49: 4.7 | AH49: 23.2 | AI49: 5.2
A50: 1385 | B50: 62011.49 | C50: 14178.76 | D50: =B50+C50 -> 76190.25 | E50: 64665.3 | F50: 11525 | G50: =F50+E50 -> 76190.3 | L50: -17695.1 | M50: 20585.155 | N50: -2890.0553 | O50: =E50-B50 -> 2653.81 | P50: =O50-R50 -> 1046.81 | Q50: =B50-R50 -> 60404.49 | R50: 1607 | S50: 11389.5 | T50: 20585.2 | U50: -6305.6 | V50: 4051 | W50: 2433 | X50: 213 | Y50: 1492 | Z50: 500 | AA50: 243 | AB50: 422 | AC50: 142 | AD50: 143 | AE50: 141.2 | AF50: 109.1 | AG50: 5.7 | AH50: 20.1 | AI50: 6.3
A51: 1386 | B51: 81566.66 | C51: 16100.57 | D51: =B51+C51 -> 97667.23 | E51: 84505.2 | F51: 13162.1 | G51: =F51+E51 -> 97667.3 | L51: -28850.962 | M51: 32593.921 | N51: -3742.9594 | O51: =E51-B51 -> 2938.54 | P51: =O51-R51 -> 1338.54 | Q51: =B51-R51 -> 79966.66 | R51: 1600 | S51: 15254.1 | T51: 32593.9 | U51: -13596.9 | V51: 4058.1 | W51: 2480.5 | X51: 157.8 | Y51: 1531.8 | Z51: 525.3 | AA51: 296.1 | AB51: 362.7 | AC51: 145.7 | AD51: 142.8 | AE51: 144.2 | AF51: 122.5 | AG51: 5.6 | AH51: 22.3 | AI51: 6.2
A52: 1387 | B52: 82402.52 | C52: 18886.3 | D52: =B52+C52 -> 101288.82 | E52: 86618.9 | F52: 14670 | G52: =F52+E52 -> 101288.9 | L52: -19135.491 | M52: 22837.603 | N52: -3702.1114 | O52: =E52-B52 -> 4216.38 | P52: =O52-R52 -> 2391.38 | Q52: =B52-R52 -> 80577.52 | R52: 1825 | S52: 8228.6 | T52: 22837.6 | U52: -10906.9 | V52: 3946.4 | W52: 2370.8 | X52: 158.4 | Y52: 1618.1 | Z52: 541.4 | AA52: 367.8 | AB52: 413 | AC52: 156.8 | AD52: 95.5 | AE52: NA | AF52: NA | AG52: 4.7 | AH52: NA | AI52: 7.1
A53: 1388 | B53: 66189.64 | C53: 22136.44 | D53: =B53+C53 -> 88326.08 | E53: 69957.1 | F53: 18369 | G53: =F53+E53 -> 88326.1 | L53: -6460.4526 | M53: 9476.6638 | N53: -3016.2112 | O53: =E53-B53 -> 3767.46 | P53: =O53-R53 -> 1981.46 | Q53: =B53-R53 -> 64403.64 | R53: 1786 | S53: -7268 | T53: 9476.7 | U53: -13728.5 | V53: 3556.6 | W53: 2056 | X53: 141.8 | Y53: 1512.1 | Z53: 489 | AA53: 353.4 | AB53: 402.3 | AC53: 136.2 | AD53: 102 | AE53: NA | AF53: NA | AG53: 6.8 | AH53: NA | AI53: 5.8
A54: 1389 | B54: 86192.87 | C54: 26594.82 | D54: =B54+C54 -> 112787.69 | E54: 90191.2 | F54: 22596.5 | G54: =F54+E54 -> 112787.7 | L54: -22373.018 | M54: 27545.962 | N54: -5172.9445 | O54: =E54-B54 -> 3998.33 | P54: =O54-R54 -> 1378.33 | Q54: =B54-R54 -> 83572.87 | R54: 2620 | S54: -946.6 | T54: 27554.5 | U54: -17968.5 | V54: 3535.8 | W54: 2021 | X54: 100.3 | Y54: 1468 | Z54: 496.7 | AA54: 356.8 | AB54: 331.4 | AC54: 136.2 | AD54: 110.9 | AE54: NA | AF54: NA | AG54: 8.5 | AH54: NA | AI54: 9
A55: 1390 | B55: 112622.5 | C55: 33183.05 | D55: =B55+C55 -> 145805.55 | E55: 119147.8 | F55: 26657.8 | G55: =F55+E55 -> 145805.6 | L55: -34639.258 | M55: 58474.509 | N55: -23835.251 | O55: =E55-B55 -> 6525.3 | P55: =O55-R55 -> 2585.3 | Q55: =B55-R55 -> 108682.5 | R55: 3940 | S55: 21436.3 | T55: 58507 | U55: -19304.3 | V55: 3618.7 | W55: 2032.7 | X55: 13.5 | Y55: 1463.2 | Z55: 507 | AA55: 343.1 | AB55: 359.9 | AC55: 125.1 | AD55: 81 | AE55: NA | AF55: NA | AG55: 9.5 | AH55: NA | AI55: 11.8
A56: 1391 | B56: 63173.68 | C56: 34122.55 | D56: =B56+C56 -> 97296.23 | E56: 68082.9 | F56: 29213.3 | G56: =F56+E56 -> 97296.2 | L56: -18902.213 | M56: 23118.802 | N56: -4216.5886 | O56: =E56-B56 -> 4909.22 | P56: =O56-R56 -> 615.22 | Q56: =B56-R56 -> 58879.68 | R56: 4294 | S56: 12212.8 | T56: 23361.9 | U56: -9948.3 | V56: 3731.8 | W56: 1803.1 | X56: 6.9 | Y56: 1692 | Z56: 570.3 | AA56: 405.2 | AB56: 448.3 | AC56: 147.1 | AD56: 65.3 | AE56: NA | AF56: NA | AG56: 9.31 | AH56: NA | AI56: 4.7
A57: 1392 | B57: 58832.03 | C57: 34077.8 | D57: =B57+C57 -> 92909.83 | E57: 64540.3 | F57: 28369.5 | G57: =F57+E57 -> 92909.8 | L57: -22604.292 | M57: 24866.578 | N57: -2262.286 | O57: =E57-B57 -> 5708.27 | P57: =O57-R57 -> 1669.27 | Q57: =B57-R57 -> 54793.03 | R57: 4039 | S57: 13188.8 | T57: 25104.7 | U57: -9321.2 | V57: 3481.2 | W57: 1605.7 | X57: 20.4 | Y57: 1731.2 | Z57: 575.97567 | AA57: 428.44466 | AB57: 465.13041 | AC57: 149.25526 | AD57: 59.23789 | AE57: NA | AF57: NA | AG57: 9.28 | AH57: NA | AI57: 5.4
A58: 1393 | B58: 48773.8 | C58: 40201.86 | D58: =B58+C58 -> 88975.66 | E58: 55406.5 | F58: 33569.2 | G58: =F58+E58 -> 88975.7 | L58: -8359.7103 | M58: 13795.747 | N58: -5436.0363 | O58: =E58-B58 -> 6632.7 | P58: =O58-R58 -> 2624.7 | Q58: =B58-R58 -> 44765.8 | R58: 4008 | S58: 8560.9 | T58: 13570.7 | U58: 559.2 | V58: 3063 | W58: 1342.7 | X58: 27.1 | Y58: 1558.3 | Z58: 528.7 | AA58: 377.7 | AB58: 433.1 | AC58: 136.1 | AD58: 50.3 | AE58: NA | AF58: NA | AG58: 9.7 | AH58: NA | AI58: 7.6
A59: 1394 | B59: 26948.76 | C59: 36046.66 | D59: =B59+C59 -> 62995.42 | E59: 31848.4 | F59: 31147 | G59: =F59+E59 -> 62995.4 | L59: 113.06741 | M59: 1236.9893 | N59: -1350.0567 | O59: =E59-B59 -> 4899.64 | P59: =O59-R59 -> 2785.64 | Q59: =B59-R59 -> 24834.76 | R59: 2114 | S59: 2233.2 | T59: 1237.4 | U59: 2346.3 | V59: 3230.9 | W59: 1433.9 | X59: 35.9 | Y59: 1545.3 | Z59: 547.8 | AA59: 326.4 | AB59: 462.7 | AC59: 126.2 | AD59: 57.3 | AE59: NA | AF59: NA | AG59: 8.6 | AH59: NA | AI59: 9.1
A60: 1395 | B60: 50239.74 | C60: 31703.29 | D60: =B60+C60 -> 81943.03 | E60: 53362 | F60: 28581 | G60: =F60+E60 -> 81943 | L60: -4671.6645 | M60: 13235.679 | N60: -8564.0145 | O60: =E60-B60 -> 3122.26 | P60: =O60-R60 -> 1906.26 | Q60: =B60-R60 -> 49023.74 | R60: 1216 | S60: -7666.1 | T60: 13236.1 | U60: -12337.7 | V60: 3761.9 | W60: 2130.7 | X60: 52.8 | Y60: 1503.3 | Z60: 484.7 | AA60: 340.3 | AB60: 443.9 | AC60: 130.2 | AD60: 72.5 | AE60: NA | AF60: NA | AG60: 9.1 | AH60: NA | AI60: 5.87
A61: 1396 | B61: 59673.1 | C61: 36360.64 | D61: =B61+C61 -> 96033.74 | E61: 62768 | F61: 33266 | G61: =F61+E61 -> 96034 | L61: -11301.549 | M61: 14914.241 | N61: -3612.6923 | O61: =E61-B61 -> 3094.9 | P61: =O61-R61 -> 1002.9 | Q61: =B61-R61 -> 57581.1 | R61: 2092 | S61: -8139.6 | T61: 14915.3 | U61: -19441.1 | V61: 3849.3 | W61: 2144.9 | X61: 76.4 | Y61: 1505.8 | Z61: 501.46 | AA61: 165.3 | AB61: 591.3 | AC61: 107.1 | AD61: 104.8 | AE61: NA | AF61: NA | AG61: 13.23 | AH61: NA | AI61: 3.86
